Workbook

Sheet 実施記録シート
B1: 【生成AI】実施記録分析シート
AR2: 分析
B3: output_row_id | C3: No. | D3: interaction_id | E3: message_id | F3: conversation_id | G3: reset_session_id | H3: reset_session_no | I3: interaction_no_in_session | J3: is_first_interaction_row | K3: 質問投入者 | L3: チーム名 | M3: 質問内容 | N3: user_content_raw | O3: is_natural_language_query | P3: is_reset_request | Q3: is_category_selection | R3: is_system_command | S3: started_at_utc | T3: completed_at_utc | U3: started_at_jst | V3: completed_at_jst | W3: latency_sec | X3: selected_function | Y3: predicted_category | Z3: user_selected_category | AA3: 第一カテゴリ | AB3: final_category | AC3: category_source | AD3: is_unclassified | AE3: 回答内容 | AF3: has_answer | AG3: is_no_answer | AH3: assistant_event_count | AI3: has_error | AJ3: error_count | AK3: error_message | AL3: retrieval_count | AM3: retrieval_stored_count | AN3: retrieval_truncated | AO3: 参照文書① | AP3: 参考箇所① | AQ3: score① | AR3: 参照文書② | AS3: 参考箇所② | AT3: score② | AU3: 参照文書➂ | AV3: 参考箇所➂ | AW3: score③ | AX3: 参照文書④ | AY3: 参考箇所④ | AZ3: score④ | BA3: 参照文書⑤ | BB3: 参考箇所⑤ | BC3: score⑤ | BD3: 参照文書⑥ | BE3: 参考箇所⑥ | BF3: score⑥ | BG3: 参照文書⑦ | BH3: 参考箇所⑦ | BI3: score⑦ | BJ3: 参照文書⑧ | BK3: 参考箇所⑧ | BL3: score⑧ | BM3: 参照文書➈ | BN3: 参考箇所➈ | BO3: score➈ | BP3: 参照文書➉ | BQ3: 参考箇所➉ | BR3: score➉ | BS3: feedback_id | BT3: feedback_seq | BU3: feedback_count | BV3: 回答評価 | BW3: 評価理由 | BX3: feedback_at_utc | BY3: feedback_at_jst | BZ3: is_latest_feedback | CA3: session_ends_with_reset | CB3: source_files | CC3: source_event_row_count | CD3: source_event_types | CE3: normalization_version | CF3: normalization_warnings | CG3: 質問/回答 分類 | CH3: 対象/ 対象外 | CI3: 参照箇所① | CJ3: 参照箇所② | CK3: 参照箇所➂ | CL3: 参照箇所④ | CM3: 参照箇所⑤ | CN3: 参照箇所⑥ | CO3: 参照箇所⑦ | CP3: 参照箇所⑧ | CQ3: 参照箇所➈ | CR3: 参照箇所➉ | CS3: 教師データ有無 | CT3: キーワード1 | CU3: キーワード2 | CV3: キーワード3 | CW3: Hit判定 | CX3: 回答判定 | CY3: 正答判定 | CZ3: 分析コメント | DA3: 原因 | DB3: 対応方針 | DC3: 対応進捗 | DD3: Vantiq相談 | DE3: 日付 | DF3: 所属 | DG3: messageID
B4: a:1omqjbhub5JIc_5FhNKbUGVjE57wIHZd4XRyWB2-vQ88Xs_NQ3anUe3ETxUmMWwvMWebbd9pg74lN0B4BHFnuC8XT7VOk1CrVz5XQuTIU29Pc-C2tG70xw6Ef9QslptPg-1779142431837-FB000 | C4: =ROW(A4)-3 | D4: a:1omqjbhub5JIc_5FhNKbUGVjE57wIHZd4XRyWB2-vQ88Xs_NQ3anUe3ETxUmMWwvMWebbd9pg74lN0B4BHFnuC8XT7VOk1CrVz5XQuTIU29Pc-C2tG70xw6Ef9QslptPg-1779142431837 | E4: 1779142431837 | F4: a:1omqjbhub5JIc_5FhNKbUGVjE57wIHZd4XRyWB2-vQ88Xs_NQ3anUe3ETxUmMWwvMWebbd9pg74lN0B4BHFnuC8XT7VOk1CrVz5XQuTIU29Pc-C2tG70xw6Ef9QslptPg | G4: a:1omqjbhub5JIc_5FhNKbUGVjE57wIHZd4XRyWB2-vQ88Xs_NQ3anUe3ETxUmMWwvMWebbd9pg74lN0B4BHFnuC8XT7VOk1CrVz5XQuTIU29Pc-C2tG70xw6Ef9QslptPg-S001 | H4: 1 | I4: 1 | J4: 1 | K4: Hiromichi Nagano (長野 裕充) | L4: DM | M4: 上長設定を変更したい。 | N4: 上長設定を変更したい。 | O4: 1 | P4: 0 | Q4: 0 | R4: 0 | S4: 46160.926 | T4: 46160.926 | U4: 46161.301 | V4: 46161.301 | W4: 5.374 | X4: searchEmployeeRules | Y4: システム操作 | AA4: システム操作 | AB4: システム操作 | AC4: predicted | AD4: 0 | AE4: 上長設定の変更方法については、以下のURLで詳細な手順が案内されています。 https://www.hdservice1.nttls.co.jp/hc/ja/articles/19023196852503 上記のページをご確認いただくことで、具体的な操作方法や注意点を確認できます。 ※AIの回答は必ずしも正確ではありません。参照情報も確認いただき、最終判断は所属部署の公式情報をご確認ください。 | AF4: 1 | AG4: 0 | AH4: 3 | AI4: 0 | AJ4: 0 | AL4: 4 | AM4: 4 | AN4: 0 | AO4: QA592_system_talemane_talemane-employee.md | AP4: 質問 派遣社員から上長設定する方法を教えてください。 回答 派遣社員から上長設定する方法がわからない場合は以下URLをご確認ください。 https://www.hdservice1.nttls.co.jp/hc/ja/articles/19023196852503 | AQ4: 0.93496073 | AR4: QA620_system_talemane_talemane-employee.md | AS4: 質問 上長設定を変更したのに申請の承認が新上長に表示されない場合、どうしたらいいでしょうか。 回答 上長設定を変更したのに申請の承認が新上長に表示されない場合は以下URLをご確認ください。 https://www.hdservice1.nttls.co.jp/hc/ja/articles/360057335353 | AT4: 0.94158808 | AU4: QA617_system_talemane_talemane-employee.md | AV4: 質問 上長が社員のポジションを割り当てることができない場合、どうしたらいいでしょうか。 回答 上長が社員のポジションを割り当てることができない場合は以下URLをご確認ください。 https://www.hdservice1.nttls.co.jp/hc/ja/articles/25013787582487 | AW4: 0.93496073 | AX4: QA614_system_talemane_talemane-employee.md | AY4: 質問 プロファイル画面から上長設定を行って新上長に変更したが、「一次評価者」が異なったまま(古い情報のまま)となっている場合、どうしたらいいでしょうか。 回答 「一次評価者」が異なったまま(古い情報のまま)となっている場合は以下URLをご確認ください。 https://www.hdservice1.nttls.co.jp/hc/ja/articles/17842855242519 | AZ4: 0.92931769 | BT4: 0 | BU4: 0 | BZ4: 0 | CA4: 0 | CB4: 20260519T071352-20260519T182604.csv | CC4: 5 | CD4: user > assistant > assistant > tool > assistant | CE4: 1.0.0 | CH4: =IF(OR(CG4="①", CG4="⑤"), "〇", "×") | CI4: =IF(OR(AND($CT4<>"",ISNUMBER(SEARCH($CT4, AP4))),AND($CU4<>"",ISNUMBER(SEARCH($CU4, AP4))),AND($CV4<>"",ISNUMBER(SEARCH($CV4, AP4)))),"〇","-") | CJ4: =IF(OR(AND($CT4<>"",ISNUMBER(SEARCH($CT4, AS4))),AND($CU4<>"",ISNUMBER(SEARCH($CU4, AS4))),AND($CV4<>"",ISNUMBER(SEARCH($CV4, AS4)))),"〇","-") | CK4: =IF(OR(AND($CT4<>"",ISNUMBER(SEARCH($CT4, AV4))),AND($CU4<>"",ISNUMBER(SEARCH($CU4, AV4))),AND($CV4<>"",ISNUMBER(SEARCH($CV4, AV4)))),"〇","-") | CL4: =IF(OR(AND($CT4<>"",ISNUMBER(SEARCH($CT4, AY4))),AND($CU4<>"",ISNUMBER(SEARCH($CU4, AY4))),AND($CV4<>"",ISNUMBER(SEARCH($CV4, AY4)))),"〇","-") | CM4: =IF(OR(AND($CT4<>"",ISNUMBER(SEARCH($CT4, BB4))),AND($CU4<>"",ISNUMBER(SEARCH($CU4, BB4))),AND($CV4<>"",ISNUMBER(SEARCH($CV4, BB4)))),"〇","-") | CN4: =IF(OR(AND($CT4<>"",ISNUMBER(SEARCH($CT4, BE4))),AND($CU4<>"",ISNUMBER(SEARCH($CU4, BE4))),AND($CV4<>"",ISNUMBER(SEARCH($CV4, BE4)))),"〇","-") | CO4: =IF(OR(AND($CT4<>"",ISNUMBER(SEARCH($CT4, BH4))),AND($CU4<>"",ISNUMBER(SEARCH($CU4, BH4))),AND($CV4<>"",ISNUMBER(SEARCH($CV4, BH4)))),"〇","-") | CP4: =IF(OR(AND($CT4<>"",ISNUMBER(SEARCH($CT4, BK4))),AND($CU4<>"",ISNUMBER(SEARCH($CU4, BK4))),AND($CV4<>"",ISNUMBER(SEARCH($CV4, BK4)))),"〇","-") | CQ4: =IF(OR(AND($CT4<>"",ISNUMBER(SEARCH($CT4, BN4))),AND($CU4<>"",ISNUMBER(SEARCH($CU4, BN4))),AND($CV4<>"",ISNUMBER(SEARCH($CV4, BN4)))),"〇","-") | CR4: =IF(OR(AND($CT4<>"",ISNUMBER(SEARCH($CT4, BQ4))),AND($CU4<>"",ISNUMBER(SEARCH($CU4, BQ4))),AND($CV4<>"",ISNUMBER(SEARCH($CV4, BQ4)))),"〇","-") | CW4: =IF(OR(CI4="〇",CJ4="〇",CK4="〇",CL4="〇",CM4="〇",CN4="〇",CO4="〇",CP4="〇",CQ4="〇",CR4="〇"),"〇","") | DE4: =TEXT(U4,"yyyy/mm/dd") | DF4: =VLOOKUP(K4,社員マスタ!C:D,2,0) | DG4: 1779142431837
B5: a:1iSKy7qXCPUl6lHy-2B3xgvRc_tKz1v0JykSQbNaMY5vJSp_4_w19tMqhUwM_oTGTKXV3N-8UzSVsmI-kFbz0LUhY29S-4UuWaWst7uPr3IGvm-BhrKY6KzPsnWAHxMJR-1779150199248-FB000 | C5: =ROW(A5)-3 | D5: a:1iSKy7qXCPUl6lHy-2B3xgvRc_tKz1v0JykSQbNaMY5vJSp_4_w19tMqhUwM_oTGTKXV3N-8UzSVsmI-kFbz0LUhY29S-4UuWaWst7uPr3IGvm-BhrKY6KzPsnWAHxMJR-1779150199248 | E5: 1779150199248 | F5: a:1iSKy7qXCPUl6lHy-2B3xgvRc_tKz1v0JykSQbNaMY5vJSp_4_w19tMqhUwM_oTGTKXV3N-8UzSVsmI-kFbz0LUhY29S-4UuWaWst7uPr3IGvm-BhrKY6KzPsnWAHxMJR | G5: a:1iSKy7qXCPUl6lHy-2B3xgvRc_tKz1v0JykSQbNaMY5vJSp_4_w19tMqhUwM_oTGTKXV3N-8UzSVsmI-kFbz0LUhY29S-4UuWaWst7uPr3IGvm-BhrKY6KzPsnWAHxMJR-S001 | H5: 1 | I5: 1 | J5: 1 | K5: Kazuyo Sorimachi (返町 和代) | L5: DM | M5: 添付の画面キャプチャのように、休憩時間と時間休を連続させてもよいのでしょうか？ | N5: 添付の画面キャプチャのように、休憩時間と時間休を連続させてもよいのでしょうか？ | O5: 1 | P5: 0 | Q5: 0 | R5: 0 | S5: 46161.016 | T5: 46161.016 | U5: 46161.391 | V5: 46161.391 | W5: 5.706 | X5: searchEmployeeRules | Y5: 制度・運用 | AA5: 制度・運用 | AB5: 制度・運用 | AC5: predicted | AD5: 0 | AE5: 休憩時間は勤務の途中において、継続または分割して与えられると定められています。 この規定から、休憩時間と時間休（年次休暇などの時間単位休暇）を連続して取得すること自体は、特に禁止されていません。 ただし、勤務形態や制度によって細かい運用が異なる場合もあるため、実際の申請時には所属部署のルールや運用状況を確認することが望ましいです。 ※AIの回答は必ずしも正確ではありません。参照情報も確認いただき、最終判断は所属部署の公式情報をご確認ください。 | AF5: 1 | AG5: 0 | AH5: 3 | AI5: 0 | AJ5: 0 | AL5: 4 | AM5: 4 | AN5: 0 | AO5: 02 臨時雇就業規則_202512.docx | AP5: ２ 前項の始業及び終業の時刻は、業務の都合又は本人の希望により変更することがある。 休憩時間 第 11 条 休憩時間は、少なくとも拘束２時間について15分の割合で計算した時間を与えられる。 ただし、勤務時間が拘束４時間以下であるときは与えられないことがある。 ２ 休憩時間は勤務の途中において、継続し、又は分割して与えられる。 時間外及び休日の勤務 第 12 条 １日について勤務時間８時間、１週間について勤務時間40時間を超えない限りにおいて第９条及び第14条の規定にかかわらず、１日の所定勤務時間を超えて、又は４週４日以外の休日に勤務を命ぜられることがある。 ２ 次の各号の一に該当する場合においては、前項の規定にかかわらず、時間外又は休日に勤務を命ぜられることがある。 (1) 労働基準法第36条の規定により協定を締結したとき (2) 労働基準法第33条の規定により労働基準監督署に所定の手続きをしたとき ３ 労働基準法第41条第３号の許可を受けた者は、前各項の規定にかかわらず、時間外又は休日に勤務を命ぜられることがある。 第２節 リモートワーク リモートワーク 第 13 条 臨時雇が所属長にリモートワークを申し出たとき、または会社指示により、勤務事業所以外を勤務場所とすることがある。 ２ 会社が貸与する情報通信機器等を除き、リモートワークに関わる費用については、臨時雇が負担する。 第３節 休日及び休暇 休 日 第 14 条 休日は、原則として次のとおりとし、４週４日を下回らないよう個別の雇用契約において定める。 (1) 毎週日曜日及び土曜日 (2) 個別の雇用契約において定めた日 ２ 前項の休日は、業務上やむを得ない理由があるときは、他の日に変更されることがある。 休暇の種類 第 15 条 休暇には、次の種類がある。 （１）有給休暇 ア 年次休暇 イ 特別休暇 ウ 病気休暇 エ 特別連続休暇 （２）無給休暇 ア 看護等休暇 イ 介護のための短期の休暇 （３）その他 ア 公傷休暇 イ 通勤災害休暇 ２ 前項の休暇のほか、社長が必要と認めた場合に休暇が与えられることがある。 年次休暇 | AQ5: 0.90772143 | AR5: 36 社員の勤務時間、休日及び休暇について_202504.docx | AS5: （８）宿直宿明服務の全勤務時間にかかる休暇は、１日単位の休暇２回とする。 （９）勤務軽減の措置により休養時間を与えている社員が休暇を取得する場合においては、その社員の所定の拘束時間は、休養時間を与えない場合の時間とし、休暇が休養時間と連続する場合は、その休養時間は与えなかったものとして取り扱う。 ６ 勤務時間の変更があった場合の取扱い 全日制勤務の社員が「育児のための短時間勤務制度について」(2007年４月１日人育服第６号)に定める育児のための短時間勤務又は「介護休職及び介護のための短時間勤務制度について」（1992年７月１日総第121号）第５項に定める介護のための短時間勤務（以下、「育児又は介護のための短時間勤務」という。）を取得する場合、育児又は介護のための短時間勤務を取得している社員が１日の勤務時間を変更する場合又は全日制勤務に復帰する場合（以下、「勤務時間の変更」という。）、変更又は復帰後の１時間を単位とする年次休暇の保有時間数については、以下の通りとする。 変更前の １日の勤務時間 変更後の １日の勤務時間 変更又は復帰後の保有時間数 ７時間30分 ６時間 変更又は復帰前に保有する時間数に ８分の６を乗じて得た時間数 ５時間 変更又は復帰前に保有する時間数に ８分の５を乗じて得た時間数 ４時間 変更又は復帰前に保有する時間数に ８分の４を乗じて得た時間数 ６時間 ７時間30分 変更又は復帰前に保有する時間数に ６分の８を乗じて得た時間数 ５時間 変更又は復帰前に保有する時間数に ６分の５を乗じて得た時間数 ４時間 変更又は復帰前に保有する時間数に ６分の４を乗じて得た時間数 ５時間 ７時間30分 変更又は復帰前に保有する時間数に ５分の８を乗じて得た時間数 ６時間 変更又は復帰前に保有する時間数に ５分の６を乗じて得た時間数 ４時間 変更又は復帰前に保有する時間数に ５分の４を乗じて得た時間数 ４時間 ７時間30分 変更又は復帰前に保有する時間数に ４分の８を乗じて得た時間数 ６時間 変更又は復帰前に保有する時間数に ４分の６を乗じて得た時間数 ５時間 変更又は復帰前に保有する時間数に ４分の５を乗じて得た時間数 なお、保有時間数に１時間未満の端数がある場合は、端数を切り上げた時間数に読み替える。 ７ 給 与 年次休暇は、有給とする。 | AT5: 0.9074277 | AU5: 健康管理規程.pdf | AV5: ア 日勤服務以外の服務につかせない。ただし、やむを得ぬ理由で夜勤服務につかせる場合は、組織の 長と産業医が協議して決める。 イ 健康状態に応じて、勤務時間中に休養時間を与えるか、又は作業環境、労働負荷を考慮して、勤務 内容の軽減をはかる。 (ｱ) 休養時間中は、原則として事業所内の休憩室等で休養させる。ただし、通勤所要時間、交通機 関等の諸事情を考慮して、勤務の始め又は終りに休養時間を与えることができる。 (ｲ) 休養時間は、１日の所定勤務時間から休養時間を除いた時間が、拘束４時間を下回らない範囲 で与えるものとする。 (ｳ) 勤務内容の軽減をはかる場合には、必要に応じて勤務場所の変更、業務の転換等を行うものと する。 ウ 過激な運動を伴う業務、時間外労働、宿泊出張はさせない。 (3) 要注意（Ｃ）の服務については、次の各項によることとする。 ア 日勤服務以外の服務につかせない。ただし、やむを得ぬ理由で前記の服務以外の服務につかせる場 合は、組織の長と産業医が協議して決める。 イ 時間外労働はさせない。ただし、やむを得ぬ理由で時間外労働をさせる場合は、組織の長と産業医 が協議して決める。この場合においても、１日２時間、１週２回を限度とする。 | AW5: 0.90772143 | AX5: 01 社員就業規則等_202512.docx | AY5: ２ 宿直については、睡眠時間を含み８時間以内の休憩時間が与えられる。 ３ 日直又は宿直の当直時間については、所属長が定めるところによる。 出張、赴任等の場合の勤務時間 第 29 条 社員が出張し、若しくは赴任し、又は所属長のもとを離れて勤務する場合における勤務時間については、特に命ぜられた場合を除くほか、所定の勤務時間を勤務したものとみなす。 第２節 フレックスタイム制 対象者 第 30 条 社員は、第20条から第27条までの規定にかかわらず、次条以下に規定するフレックスタイム制が適用されることがある。 基準労働時間 第 31 条 前条に定める社員は、各清算期間（各月１日から月末まで）において、基準労働時間（週休日を日曜日及び土曜日に設定する社員の当該清算期間における所定労働日の勤務時間（１日７時間30分。ただし、第64条第３項及び第67条第２項に規定する短時間勤務を行う者については、１日４時間、５時間又は６時間のいずれかの時間）を合計して得た時間をいう。）を勤務しなければならない。 コアタイム及びフレキシブルタイム 第 32 条 コアタイム及びフレキシブルタイムは、次のとおりとする。 （１） コアタイム（全員が勤務しなければならない時間帯） ① 標準的なコアタイムは、午前10時から午後３時まで（正午から午後１時までは休憩時間）の４時間とする。 なお、具体的な設定時刻は、労働基準法第32条の３に規定する協定により定める。 ② 第64条第３項及び第67条第２項に規定する短時間勤務を行う者の標準的なコアタイムは、午前10時から午後２時（正午から午後１時までは休憩時間）の３時間とする。なお、具体的な設定時刻は、労働基準法第32条の３に規定する協定により定める。 ③ コアタイムを設定しない場合は、１日の最低勤務時間を３時間とする。 なお、具体的には労働基準法第32条の３に規定する協定により定める。 また、コアタイムを設定しない場合における休憩時間は、次のとおりとし、勤務の途中において適用社員の裁量により設定する。 ア １日５時間以上７時間未満の勤務 45分 イ １日７時間以上の勤務 60分 （２）フレキシブルタイム（社員が自主的に始業・終業時刻を選択できる時間帯） | AZ5: 0.90791325 | BT5: 0 | BU5: 0 | BZ5: 0 | CA5: 1 | CB5: 20260519T071352-20260519T182604.csv | CC5: 5 | CD5: user > assistant > assistant > tool > assistant | CE5: 1.0.0 | CH5: =IF(OR(CG5="①", CG5="⑤"), "〇", "×") | CI5: =IF(OR(AND($CT5<>"",ISNUMBER(SEARCH($CT5, AP5))),AND($CU5<>"",ISNUMBER(SEARCH($CU5, AP5))),AND($CV5<>"",ISNUMBER(SEARCH($CV5, AP5)))),"〇","-") | CJ5: =IF(OR(AND($CT5<>"",ISNUMBER(SEARCH($CT5, AS5))),AND($CU5<>"",ISNUMBER(SEARCH($CU5, AS5))),AND($CV5<>"",ISNUMBER(SEARCH($CV5, AS5)))),"〇","-") | CK5: =IF(OR(AND($CT5<>"",ISNUMBER(SEARCH($CT5, AV5))),AND($CU5<>"",ISNUMBER(SEARCH($CU5, AV5))),AND($CV5<>"",ISNUMBER(SEARCH($CV5, AV5)))),"〇","-") | CL5: =IF(OR(AND($CT5<>"",ISNUMBER(SEARCH($CT5, AY5))),AND($CU5<>"",ISNUMBER(SEARCH($CU5, AY5))),AND($CV5<>"",ISNUMBER(SEARCH($CV5, AY5)))),"〇","-") | CM5: =IF(OR(AND($CT5<>"",ISNUMBER(SEARCH($CT5, BB5))),AND($CU5<>"",ISNUMBER(SEARCH($CU5, BB5))),AND($CV5<>"",ISNUMBER(SEARCH($CV5, BB5)))),"〇","-") | CN5: =IF(OR(AND($CT5<>"",ISNUMBER(SEARCH($CT5, BE5))),AND($CU5<>"",ISNUMBER(SEARCH($CU5, BE5))),AND($CV5<>"",ISNUMBER(SEARCH($CV5, BE5)))),"〇","-") | CO5: =IF(OR(AND($CT5<>"",ISNUMBER(SEARCH($CT5, BH5))),AND($CU5<>"",ISNUMBER(SEARCH($CU5, BH5))),AND($CV5<>"",ISNUMBER(SEARCH($CV5, BH5)))),"〇","-") | CP5: =IF(OR(AND($CT5<>"",ISNUMBER(SEARCH($CT5, BK5))),AND($CU5<>"",ISNUMBER(SEARCH($CU5, BK5))),AND($CV5<>"",ISNUMBER(SEARCH($CV5, BK5)))),"〇","-") | CQ5: =IF(OR(AND($CT5<>"",ISNUMBER(SEARCH($CT5, BN5))),AND($CU5<>"",ISNUMBER(SEARCH($CU5, BN5))),AND($CV5<>"",ISNUMBER(SEARCH($CV5, BN5)))),"〇","-") | CR5: =IF(OR(AND($CT5<>"",ISNUMBER(SEARCH($CT5, BQ5))),AND($CU5<>"",ISNUMBER(SEARCH($CU5, BQ5))),AND($CV5<>"",ISNUMBER(SEARCH($CV5, BQ5)))),"〇","-") | CW5: =IF(OR(CI5="〇",CJ5="〇",CK5="〇",CL5="〇",CM5="〇",CN5="〇",CO5="〇",CP5="〇",CQ5="〇",CR5="〇"),"〇","") | DE5: =TEXT(U5,"yyyy/mm/dd") | DF5: =VLOOKUP(K5,社員マスタ!C:D,2,0) | DG5: 1779150199248
B6: a:1iSKy7qXCPUl6lHy-2B3xgvRc_tKz1v0JykSQbNaMY5vJSp_4_w19tMqhUwM_oTGTKXV3N-8UzSVsmI-kFbz0LUhY29S-4UuWaWst7uPr3IGvm-BhrKY6KzPsnWAHxMJR-1779150903232-FB000 | C6: =ROW(A6)-3 | D6: a:1iSKy7qXCPUl6lHy-2B3xgvRc_tKz1v0JykSQbNaMY5vJSp_4_w19tMqhUwM_oTGTKXV3N-8UzSVsmI-kFbz0LUhY29S-4UuWaWst7uPr3IGvm-BhrKY6KzPsnWAHxMJR-1779150903232 | E6: 1779150903232 | F6: a:1iSKy7qXCPUl6lHy-2B3xgvRc_tKz1v0JykSQbNaMY5vJSp_4_w19tMqhUwM_oTGTKXV3N-8UzSVsmI-kFbz0LUhY29S-4UuWaWst7uPr3IGvm-BhrKY6KzPsnWAHxMJR | G6: a:1iSKy7qXCPUl6lHy-2B3xgvRc_tKz1v0JykSQbNaMY5vJSp_4_w19tMqhUwM_oTGTKXV3N-8UzSVsmI-kFbz0LUhY29S-4UuWaWst7uPr3IGvm-BhrKY6KzPsnWAHxMJR-S001 | H6: 1 | I6: 2 | J6: 1 | K6: Kazuyo Sorimachi (返町 和代) | L6: DM | M6: 休暇種別のうちの「不稼働」とは何ですか？ どういうときに使うのですか？ | N6: 休暇種別のうちの「不稼働」とは何ですか？ どういうときに使うのですか？ | O6: 1 | P6: 0 | Q6: 0 | R6: 0 | S6: 46161.024 | T6: 46161.024 | U6: 46161.399 | V6: 46161.399 | W6: 6.798 | X6: searchEmployeeRules | AB6: 未分類 | AC6: none | AD6: 1 | AE6: 検索結果から「不稼働」に関する直接的な定義や具体的な使用場面の記載は見当たりませんでした。 「不稼働」は一般的に、業務上の必要に基づく事務の一部または全部の停止など、会社側の事情で勤務ができない場合に使われる休暇種別です。 例えば、業務上の必要で事務が停止された場合や、非常事態の発生により出勤・勤務が不可能な場合などが該当します。 このようなケースでは、所属長が必要と認める時間や日数で「不稼働」として扱われることがあります。 ※AIの回答は必ずしも正確ではありません。参照情報も確認いただき、最終判断は所属部署の公式情報をご確認ください。 | AF6: 1 | AG6: 0 | AH6: 2 | AI6: 0 | AJ6: 0 | AL6: 4 | AM6: 4 | AN6: 0 | AO6: 40 特認休暇について_202511.docx | AP6: （注）(1) 休暇を付与する場合であって、特に必要とする場合は、臨時雇を雇用しても差し支えない。 「業務に支障がない場合」には、「業務に支障があるが、臨時雇を雇用すれば業務に支障がなくなる場合」を含む。 ２ 前項による休暇の付与は、次により行うものとする。 (1) 「休暇願」（「人事服務関係の願、届について」（1992年７月１日総第22号）に定める様式）に基づき、組織単位の長（組織単位の長が指定した者（直属上長より上位にある者に限る。）を含む。）が承認する。 (2) １年につき６週間以内であれば、夏季及び冬季の２回付与しても差し支えない。 (3) １学部の受講につき24週間以内であれば、５年以上にわたって付与しても差し支えない。 ３ 第１項に定める休暇は、社員就業規則第37条第２項による休暇とし、有給とする。 ４ 第１項に定める休暇期間中の給与については、基本給、成果手当及び採用調整加算の合算した額の10分の3を減額して得た額並びに子育て・介護手当、単身赴任手当及び住宅補助費の全額を支給するものとする。 この場合、月の初日以外の日において新たにこの休暇を付与した場合又は月の末日以外の日においてこの休暇期間が終了した場合における減額すべき額については、「社員給与規則の解釈運用について」（1992年７月１日総第45号）第11条第１項の算出式に基づき、日割によって計算するものとする。 付 則 １ 本通達は、2023年４月１日から実施する。 ２ 「第５章 大学通信教育のスクーリングに参加する者の服務の取扱について」第４項の休暇期間中の給与において、「社員給与規則」（1992年７月１日社長達第22号）の改正（2023年３月31日）付則第３項ないし第12項の措置額を含めて扱う。 ３ 本通達の実施に伴い、「特認休暇について」（1992年7月1日総第16号）、「ＮＴＴドコモグループ記念日における服務等の取扱いについて」（1992年９月24日総第294号）、「被災者支援活動に従事する社員の服務について」（1995年５月15日総勤第２号）、「骨髄バンクへの登録等を行う社員の服務について」（1993年12月24日総勤第78号）及び「大学通信教育のスクーリングに参加する者の服務の取扱について」（1992年７月１日総第23号）を廃止する。 付 則 | AQ6: 0.9295409 | AR6: 02 臨時雇就業規則_202512.docx | AS6: る。 ２ 前項における出勤率の算定にあたっては、第17条第１項第15号に定める出産のための特別休暇、第20条に定める公傷休暇、第29条に定める育児休職及び第30条に定める介護休職を付与した日は出勤したものとみなす。 ３ 年次休暇を与えた日の賃金は、当該勤務日の所定勤務時間を勤務した場合に支払われる通常の賃金とする。 ４ 年次休暇の時季の指定等の取扱いは次のとおりとする。 （1）年次休暇の時季を指定する場合は事前に行わなければならない。 ただし、指定された時季における年次休暇が事業の正常な運営を妨げる場合は、会社は他の時季に変更することができるものとする。 （2）同条第１項の年次休暇が10日以上発効された臨時雇に対して、発効日から１年以内の年次休暇の取得日数が日又は半日単位で５日に満たない場合は、その不足分について、臨時雇の希望を勘案したうえで会社があらかじめ時季を指定し、日又は半日を単位に取得させることとする。 ５ 年次休暇は、原則として日を単位とするが、１時間を単位とすることもできる。 ただし、１時間を単位とした休暇は、休暇発効日より１年以内において５日を上限とする。 なお、休暇の付与日数が５日に満たない場合、発効された日数を上限とする。 ６ １時間を単位とする場合における取り扱いは、次のとおりとする。 (1) １時間を単位とした休暇は１日の所定勤務時間内において、取得時間帯、取得時間数に制限無く取得できる。 (2) １時間単位の休暇は、１日の所定勤務時間数をもって１日分とする。 特別休暇 第 17 条 臨時雇が次の各号の一に該当する理由により勤務日に勤務しないときは、当該各号に定 めるところにより、その者に特別休暇が与えられる。 | AT6: 0.92628923 | AU6: 50 社員の選挙運動等の取扱について_200807.docx | AV6: イ 選挙運動期間中における年次休暇の取扱いについては、通常における場合と同様厳正に取り扱うものとし、組合休暇については、それを選挙運動等のために使用することのないよう厳正に取り扱うこと。 ウ 選挙運動のための会社の業務用電話の利用、会社車両の使用の承認、タクシー利用券の交付、その他これに類する便宜供与は行ってはならない。 エ 特定の候補者を支援することの疑惑を世間に抱かせるような物品の購入等の行為は厳に慎むこと。 当然のことながら、勤務時間内に会社組織を利用して資金カンパ等を行うことも同様行ってはならない。 ３ 選挙運動に係る会社施設の利用等について 会社施設（宿舎を含む。）の利用について申出があった場合、その目的、内容が自ら選挙運動又は政治的な活動を行うためのものであると認められるときは、これの使用を一切認めないこと。 選挙運動のために使用するポスター等の指示についても、その内容が選挙運動又は政治的な活動に関係があると認められるものはこれを認めないこと。 ４ その他 社員が国会又は地方公共団体の議会の議員その他公選による公職の選挙に立候補するときは、所属長に公職立候補届を提出しなければならない。 社員が前１の公職に就任するときは、すみやかに所属長に当選証明書を提出しなければならない。 | AW6: 0.9295409 | AX6: 健康管理規程.pdf | AY6: ア 日勤服務以外の服務につかせない。ただし、やむを得ぬ理由で夜勤服務につかせる場合は、組織の 長と産業医が協議して決める。 イ 健康状態に応じて、勤務時間中に休養時間を与えるか、又は作業環境、労働負荷を考慮して、勤務 内容の軽減をはかる。 (ｱ) 休養時間中は、原則として事業所内の休憩室等で休養させる。ただし、通勤所要時間、交通機 関等の諸事情を考慮して、勤務の始め又は終りに休養時間を与えることができる。 (ｲ) 休養時間は、１日の所定勤務時間から休養時間を除いた時間が、拘束４時間を下回らない範囲 で与えるものとする。 (ｳ) 勤務内容の軽減をはかる場合には、必要に応じて勤務場所の変更、業務の転換等を行うものと する。 ウ 過激な運動を伴う業務、時間外労働、宿泊出張はさせない。 (3) 要注意（Ｃ）の服務については、次の各項によることとする。 ア 日勤服務以外の服務につかせない。ただし、やむを得ぬ理由で前記の服務以外の服務につかせる場 合は、組織の長と産業医が協議して決める。 イ 時間外労働はさせない。ただし、やむを得ぬ理由で時間外労働をさせる場合は、組織の長と産業医 が協議して決める。この場合においても、１日２時間、１週２回を限度とする。 | AZ6: 0.92568737 | BT6: 0 | BU6: 0 | BZ6: 0 | CA6: 1 | CB6: 20260519T071352-20260519T182604.csv | CC6: 4 | CD6: user > assistant > tool > assistant | CE6: 1.0.0 | CH6: =IF(OR(CG6="①", CG6="⑤"), "〇", "×") | CI6: =IF(OR(AND($CT6<>"",ISNUMBER(SEARCH($CT6, AP6))),AND($CU6<>"",ISNUMBER(SEARCH($CU6, AP6))),AND($CV6<>"",ISNUMBER(SEARCH($CV6, AP6)))),"〇","-") | CJ6: =IF(OR(AND($CT6<>"",ISNUMBER(SEARCH($CT6, AS6))),AND($CU6<>"",ISNUMBER(SEARCH($CU6, AS6))),AND($CV6<>"",ISNUMBER(SEARCH($CV6, AS6)))),"〇","-") | CK6: =IF(OR(AND($CT6<>"",ISNUMBER(SEARCH($CT6, AV6))),AND($CU6<>"",ISNUMBER(SEARCH($CU6, AV6))),AND($CV6<>"",ISNUMBER(SEARCH($CV6, AV6)))),"〇","-") | CL6: =IF(OR(AND($CT6<>"",ISNUMBER(SEARCH($CT6, AY6))),AND($CU6<>"",ISNUMBER(SEARCH($CU6, AY6))),AND($CV6<>"",ISNUMBER(SEARCH($CV6, AY6)))),"〇","-") | CM6: =IF(OR(AND($CT6<>"",ISNUMBER(SEARCH($CT6, BB6))),AND($CU6<>"",ISNUMBER(SEARCH($CU6, BB6))),AND($CV6<>"",ISNUMBER(SEARCH($CV6, BB6)))),"〇","-") | CN6: =IF(OR(AND($CT6<>"",ISNUMBER(SEARCH($CT6, BE6))),AND($CU6<>"",ISNUMBER(SEARCH($CU6, BE6))),AND($CV6<>"",ISNUMBER(SEARCH($CV6, BE6)))),"〇","-") | CO6: =IF(OR(AND($CT6<>"",ISNUMBER(SEARCH($CT6, BH6))),AND($CU6<>"",ISNUMBER(SEARCH($CU6, BH6))),AND($CV6<>"",ISNUMBER(SEARCH($CV6, BH6)))),"〇","-") | CP6: =IF(OR(AND($CT6<>"",ISNUMBER(SEARCH($CT6, BK6))),AND($CU6<>"",ISNUMBER(SEARCH($CU6, BK6))),AND($CV6<>"",ISNUMBER(SEARCH($CV6, BK6)))),"〇","-") | CQ6: =IF(OR(AND($CT6<>"",ISNUMBER(SEARCH($CT6, BN6))),AND($CU6<>"",ISNUMBER(SEARCH($CU6, BN6))),AND($CV6<>"",ISNUMBER(SEARCH($CV6, BN6)))),"〇","-") | CR6: =IF(OR(AND($CT6<>"",ISNUMBER(SEARCH($CT6, BQ6))),AND($CU6<>"",ISNUMBER(SEARCH($CU6, BQ6))),AND($CV6<>"",ISNUMBER(SEARCH($CV6, BQ6)))),"〇","-") | CW6: =IF(OR(CI6="〇",CJ6="〇",CK6="〇",CL6="〇",CM6="〇",CN6="〇",CO6="〇",CP6="〇",CQ6="〇",CR6="〇"),"〇","") | DE6: =TEXT(U6,"yyyy/mm/dd") | DF6: =VLOOKUP(K6,社員マスタ!C:D,2,0) | DG6: 1779150903232
B7: a:1iSKy7qXCPUl6lHy-2B3xgvRc_tKz1v0JykSQbNaMY5vJSp_4_w19tMqhUwM_oTGTKXV3N-8UzSVsmI-kFbz0LUhY29S-4UuWaWst7uPr3IGvm-BhrKY6KzPsnWAHxMJR-1779151036941-FB000 | C7: =ROW(A7)-3 | D7: a:1iSKy7qXCPUl6lHy-2B3xgvRc_tKz1v0JykSQbNaMY5vJSp_4_w19tMqhUwM_oTGTKXV3N-8UzSVsmI-kFbz0LUhY29S-4UuWaWst7uPr3IGvm-BhrKY6KzPsnWAHxMJR-1779151036941 | E7: 1779151036941 | F7: a:1iSKy7qXCPUl6lHy-2B3xgvRc_tKz1v0JykSQbNaMY5vJSp_4_w19tMqhUwM_oTGTKXV3N-8UzSVsmI-kFbz0LUhY29S-4UuWaWst7uPr3IGvm-BhrKY6KzPsnWAHxMJR | G7: a:1iSKy7qXCPUl6lHy-2B3xgvRc_tKz1v0JykSQbNaMY5vJSp_4_w19tMqhUwM_oTGTKXV3N-8UzSVsmI-kFbz0LUhY29S-4UuWaWst7uPr3IGvm-BhrKY6KzPsnWAHxMJR-S001 | H7: 1 | I7: 3 | J7: 1 | K7: Kazuyo Sorimachi (返町 和代) | L7: DM | M7: DREAMSの休暇種別で選択できるようになっているのですが、制度の説明はありませんか？ | N7: DREAMSの休暇種別で選択できるようになっているのですが、制度の説明はありませんか？ | O7: 1 | P7: 0 | Q7: 0 | R7: 0 | S7: 46161.026 | T7: 46161.026 | U7: 46161.401 | V7: 46161.401 | W7: 4.702 | X7: searchEmployeeRules | AB7: 未分類 | AC7: none | AD7: 1 | AE7: ご質問の内容に関する情報が見つかりませんでした。 以下操作を行っていただくことで回答を得やすくなるのでお試しください。 * 「カテゴリ」を選択：質問要件が絞りこまれることで回答が得やすくなります。 * 「リセット」を選択：会話記録をリセットすることで回答が得やすくなります。 * 「ヘルプ」を選択 ：回答が得やすくなるヒントが確認できます。 有人での確認が必要な内容や個別条件に関するご質問は、「個別問合せ」をご利用ください。 | AF7: 1 | AG7: 1 | AH7: 2 | AI7: 0 | AJ7: 0 | AL7: 4 | AM7: 4 | AN7: 0 | AO7: QA231_policy-operations_commute-costs_com-others.md | AP7: 質問 DREAMSの業務一覧に実施済みの「通勤経路申請」のリストが残ったまま消えません。どうすれば消えますか？ 回答 DREAMSの業務一覧のリストは、「社員情報」の作業リストに残っている通勤経路申請を削除すると自動的に消えます。 「社員情報」の作業リストのチェックボックスがグレーアウトされ、ご自身で削除ができない場合には、当方でステータス変更の処理を行いますので、給与アシスト担当サイトのお問い合わせフォームよりご連絡ください。その際、ご自身の氏名と氏名コードをお知らせください。 | AQ7: 0.92797435 | AR7: QA227_policy-operations_commute-costs_com-others.md | AS7: 質問 以下のエラーが表示され、申請できません。どうすればいいですか。 「通勤費に関わる申請が作業リストに保留または承認処理中であるため申請できません」 「申請年月日：202●.●●.●●、株式会社●●で登録した申請が承認待ちのため、新規起票できません。」 回答 DREAMS「社員情報」の「作業リスト」、及び「異動前作業リスト」をご確認いただき、対象のリストが表示されていないか確認（表示されている場合は削除）、 または、DREAMS「進捗管理」の「共通申請」にて「ステータス：承認待ち」で検索いただき、該当リストがないか（該当リストがある場合は取り下げ）確認ください。 ※複数の立場をお持ちの場合は、それぞれの立場でご確認ください。 ※コム出向者については、■1-45もあわせてご確認ください。 | AT7: 0.9236724 | AU7: QA224_policy-operations_commute-costs_com-others.md | AV7: 質問 転居や勤務地変更はありませんが、通勤経路を変更してもいいですか。 回答 不慣れ要素等により、後に認定経路とは異なる経路が最安または最早と判明する場合「一度限り」変更は可能です。 以下の申請時の注意点を参照の上、DREAMSより通勤経路申請を行ってください。 ただし、今後異動や転居等の事由以外での変更は承れなくなるのでご注意をお願いいたします。 【申請時の注意点】 ・「経路変更事由：その他」を設定し、空欄に「一度限りの経路変更」と入力してください。 ・通勤開始日について、定期の場合は、必ず申請月の1日を通勤開始日としてください。 （実績支払やRSの場合を除いて、月途中での変更は承れません。） | AW7: 0.92797435 | AX7: QA180_policy-operations_travel_travel-assignment_office-work_domestic_training_home-travel-expenses_overseas_operational_travel-others.md | AY7: 質問 ドコモグループ外に出向となりました。出向先立場でDREAMSによる赴任旅費申請が出来ません。 回答 異動後の出向先会社での申請手続きとなるため、出向先所属の総括担当等にお問い合わせください。 ※出向先会社によっては、出向元負担の場合もございますので、出向先の総括担当へご確認ください。 | AZ7: 0.9216304 | BT7: 0 | BU7: 0 | BZ7: 0 | CA7: 1 | CB7: 20260519T071352-20260519T182604.csv | CC7: 4 | CD7: user > assistant > tool > assistant | CE7: 1.0.0 | CH7: =IF(OR(CG7="①", CG7="⑤"), "〇", "×") | CI7: =IF(OR(AND($CT7<>"",ISNUMBER(SEARCH($CT7, AP7))),AND($CU7<>"",ISNUMBER(SEARCH($CU7, AP7))),AND($CV7<>"",ISNUMBER(SEARCH($CV7, AP7)))),"〇","-") | CJ7: =IF(OR(AND($CT7<>"",ISNUMBER(SEARCH($CT7, AS7))),AND($CU7<>"",ISNUMBER(SEARCH($CU7, AS7))),AND($CV7<>"",ISNUMBER(SEARCH($CV7, AS7)))),"〇","-") | CK7: =IF(OR(AND($CT7<>"",ISNUMBER(SEARCH($CT7, AV7))),AND($CU7<>"",ISNUMBER(SEARCH($CU7, AV7))),AND($CV7<>"",ISNUMBER(SEARCH($CV7, AV7)))),"〇","-") | CL7: =IF(OR(AND($CT7<>"",ISNUMBER(SEARCH($CT7, AY7))),AND($CU7<>"",ISNUMBER(SEARCH($CU7, AY7))),AND($CV7<>"",ISNUMBER(SEARCH($CV7, AY7)))),"〇","-") | CM7: =IF(OR(AND($CT7<>"",ISNUMBER(SEARCH($CT7, BB7))),AND($CU7<>"",ISNUMBER(SEARCH($CU7, BB7))),AND($CV7<>"",ISNUMBER(SEARCH($CV7, BB7)))),"〇","-") | CN7: =IF(OR(AND($CT7<>"",ISNUMBER(SEARCH($CT7, BE7))),AND($CU7<>"",ISNUMBER(SEARCH($CU7, BE7))),AND($CV7<>"",ISNUMBER(SEARCH($CV7, BE7)))),"〇","-") | CO7: =IF(OR(AND($CT7<>"",ISNUMBER(SEARCH($CT7, BH7))),AND($CU7<>"",ISNUMBER(SEARCH($CU7, BH7))),AND($CV7<>"",ISNUMBER(SEARCH($CV7, BH7)))),"〇","-") | CP7: =IF(OR(AND($CT7<>"",ISNUMBER(SEARCH($CT7, BK7))),AND($CU7<>"",ISNUMBER(SEARCH($CU7, BK7))),AND($CV7<>"",ISNUMBER(SEARCH($CV7, BK7)))),"〇","-") | CQ7: =IF(OR(AND($CT7<>"",ISNUMBER(SEARCH($CT7, BN7))),AND($CU7<>"",ISNUMBER(SEARCH($CU7, BN7))),AND($CV7<>"",ISNUMBER(SEARCH($CV7, BN7)))),"〇","-") | CR7: =IF(OR(AND($CT7<>"",ISNUMBER(SEARCH($CT7, BQ7))),AND($CU7<>"",ISNUMBER(SEARCH($CU7, BQ7))),AND($CV7<>"",ISNUMBER(SEARCH($CV7, BQ7)))),"〇","-") | CW7: =IF(OR(CI7="〇",CJ7="〇",CK7="〇",CL7="〇",CM7="〇",CN7="〇",CO7="〇",CP7="〇",CQ7="〇",CR7="〇"),"〇","") | DE7: =TEXT(U7,"yyyy/mm/dd") | DF7: =VLOOKUP(K7,社員マスタ!C:D,2,0) | DG7: 1779151036941
B8: a:1iSKy7qXCPUl6lHy-2B3xgvRc_tKz1v0JykSQbNaMY5vJSp_4_w19tMqhUwM_oTGTKXV3N-8UzSVsmI-kFbz0LUhY29S-4UuWaWst7uPr3IGvm-BhrKY6KzPsnWAHxMJR-f:9d1db907-bb38-aaeb-0194-7253213ef40d-FB000 | C8: =ROW(A8)-3 | D8: a:1iSKy7qXCPUl6lHy-2B3xgvRc_tKz1v0JykSQbNaMY5vJSp_4_w19tMqhUwM_oTGTKXV3N-8UzSVsmI-kFbz0LUhY29S-4UuWaWst7uPr3IGvm-BhrKY6KzPsnWAHxMJR-f:9d1db907-bb38-aaeb-0194-7253213ef40d | E8: f:9d1db907-bb38-aaeb-0194-7253213ef40d | F8: a:1iSKy7qXCPUl6lHy-2B3xgvRc_tKz1v0JykSQbNaMY5vJSp_4_w19tMqhUwM_oTGTKXV3N-8UzSVsmI-kFbz0LUhY29S-4UuWaWst7uPr3IGvm-BhrKY6KzPsnWAHxMJR | G8: a:1iSKy7qXCPUl6lHy-2B3xgvRc_tKz1v0JykSQbNaMY5vJSp_4_w19tMqhUwM_oTGTKXV3N-8UzSVsmI-kFbz0LUhY29S-4UuWaWst7uPr3IGvm-BhrKY6KzPsnWAHxMJR-S001 | H8: 1 | I8: 4 | J8: 1 | K8: Kazuyo Sorimachi (返町 和代) | L8: DM | N8: リセット | O8: 0 | P8: 1 | Q8: 0 | R8: 0 | S8: 46161.026 | T8: 46161.026 | U8: 46161.401 | V8: 46161.401 | W8: 0 | AB8: 未分類 | AC8: none | AD8: 1 | AF8: 0 | AG8: 0 | AH8: 0 | AI8: 0 | AJ8: 0 | AL8: 0 | AM8: 0 | AN8: 0 | BT8: 0 | BU8: 0 | BZ8: 0 | CA8: 1 | CB8: 20260519T071352-20260519T182604.csv | CC8: 1 | CD8: user | CE8: 1.0.0 | CH8: =IF(OR(CG8="①", CG8="⑤"), "〇", "×") | CI8: =IF(OR(AND($CT8<>"",ISNUMBER(SEARCH($CT8, AP8))),AND($CU8<>"",ISNUMBER(SEARCH($CU8, AP8))),AND($CV8<>"",ISNUMBER(SEARCH($CV8, AP8)))),"〇","-") | CJ8: =IF(OR(AND($CT8<>"",ISNUMBER(SEARCH($CT8, AS8))),AND($CU8<>"",ISNUMBER(SEARCH($CU8, AS8))),AND($CV8<>"",ISNUMBER(SEARCH($CV8, AS8)))),"〇","-") | CK8: =IF(OR(AND($CT8<>"",ISNUMBER(SEARCH($CT8, AV8))),AND($CU8<>"",ISNUMBER(SEARCH($CU8, AV8))),AND($CV8<>"",ISNUMBER(SEARCH($CV8, AV8)))),"〇","-") | CL8: =IF(OR(AND($CT8<>"",ISNUMBER(SEARCH($CT8, AY8))),AND($CU8<>"",ISNUMBER(SEARCH($CU8, AY8))),AND($CV8<>"",ISNUMBER(SEARCH($CV8, AY8)))),"〇","-") | CM8: =IF(OR(AND($CT8<>"",ISNUMBER(SEARCH($CT8, BB8))),AND($CU8<>"",ISNUMBER(SEARCH($CU8, BB8))),AND($CV8<>"",ISNUMBER(SEARCH($CV8, BB8)))),"〇","-") | CN8: =IF(OR(AND($CT8<>"",ISNUMBER(SEARCH($CT8, BE8))),AND($CU8<>"",ISNUMBER(SEARCH($CU8, BE8))),AND($CV8<>"",ISNUMBER(SEARCH($CV8, BE8)))),"〇","-") | CO8: =IF(OR(AND($CT8<>"",ISNUMBER(SEARCH($CT8, BH8))),AND($CU8<>"",ISNUMBER(SEARCH($CU8, BH8))),AND($CV8<>"",ISNUMBER(SEARCH($CV8, BH8)))),"〇","-") | CP8: =IF(OR(AND($CT8<>"",ISNUMBER(SEARCH($CT8, BK8))),AND($CU8<>"",ISNUMBER(SEARCH($CU8, BK8))),AND($CV8<>"",ISNUMBER(SEARCH($CV8, BK8)))),"〇","-") | CQ8: =IF(OR(AND($CT8<>"",ISNUMBER(SEARCH($CT8, BN8))),AND($CU8<>"",ISNUMBER(SEARCH($CU8, BN8))),AND($CV8<>"",ISNUMBER(SEARCH($CV8, BN8)))),"〇","-") | CR8: =IF(OR(AND($CT8<>"",ISNUMBER(SEARCH($CT8, BQ8))),AND($CU8<>"",ISNUMBER(SEARCH($CU8, BQ8))),AND($CV8<>"",ISNUMBER(SEARCH($CV8, BQ8)))),"〇","-") | CW8: =IF(OR(CI8="〇",CJ8="〇",CK8="〇",CL8="〇",CM8="〇",CN8="〇",CO8="〇",CP8="〇",CQ8="〇",CR8="〇"),"〇","") | DE8: =TEXT(U8,"yyyy/mm/dd") | DF8: =VLOOKUP(K8,社員マスタ!C:D,2,0) | DG8: f:9d1db907-bb38-aaeb-0194-7253213ef40d
B9: a:1iSKy7qXCPUl6lHy-2B3xgvRc_tKz1v0JykSQbNaMY5vJSp_4_w19tMqhUwM_oTGTKXV3N-8UzSVsmI-kFbz0LUhY29S-4UuWaWst7uPr3IGvm-BhrKY6KzPsnWAHxMJR-1779151102632-FB000 | C9: =ROW(A9)-3 | D9: a:1iSKy7qXCPUl6lHy-2B3xgvRc_tKz1v0JykSQbNaMY5vJSp_4_w19tMqhUwM_oTGTKXV3N-8UzSVsmI-kFbz0LUhY29S-4UuWaWst7uPr3IGvm-BhrKY6KzPsnWAHxMJR-1779151102632 | E9: 1779151102632 | F9: a:1iSKy7qXCPUl6lHy-2B3xgvRc_tKz1v0JykSQbNaMY5vJSp_4_w19tMqhUwM_oTGTKXV3N-8UzSVsmI-kFbz0LUhY29S-4UuWaWst7uPr3IGvm-BhrKY6KzPsnWAHxMJR | G9: a:1iSKy7qXCPUl6lHy-2B3xgvRc_tKz1v0JykSQbNaMY5vJSp_4_w19tMqhUwM_oTGTKXV3N-8UzSVsmI-kFbz0LUhY29S-4UuWaWst7uPr3IGvm-BhrKY6KzPsnWAHxMJR-S002 | H9: 2 | I9: 1 | J9: 1 | K9: Kazuyo Sorimachi (返町 和代) | L9: DM | M9: 休暇種別のうちの「不稼働」とは何ですか？ どういうときに使うのですか？ 以下の通りDREAMSの休暇種別で選択できます。 | N9: 休暇種別のうちの「不稼働」とは何ですか？ どういうときに使うのですか？ 以下の通りDREAMSの休暇種別で選択できます。 | O9: 1 | P9: 0 | Q9: 0 | R9: 0 | S9: 46161.027 | T9: 46161.027 | U9: 46161.402 | V9: 46161.402 | W9: 5.899 | X9: searchEmployeeRules | Y9: 制度・運用 | AA9: 制度・運用 | AB9: 制度・運用 | AC9: predicted | AD9: 0 | AE9: 「不稼働」とは、業務上の必要により事務の一部または全部が停止され、出勤や勤務ができない場合に使用する休暇種別です。 具体的には、以下のようなケースで「不稼働」が適用されます。 - 業務上の必要に基づき、会社や部署の事務が一時的に停止された場合 - 非常事態の発生などで出勤・勤務が不可能となった場合 このような状況で、所属長が必要と認めた時間や日数について「不稼働」として休暇を取得できます。 ※AIの回答は必ずしも正確ではありません。参照情報も確認いただき、最終判断は所属部署の公式情報をご確認ください。 | AF9: 1 | AG9: 0 | AH9: 3 | AI9: 0 | AJ9: 0 | AL9: 4 | AM9: 4 | AN9: 0 | AO9: 40 特認休暇について_202511.docx | AP9: （注）(1) 休暇を付与する場合であって、特に必要とする場合は、臨時雇を雇用しても差し支えない。 「業務に支障がない場合」には、「業務に支障があるが、臨時雇を雇用すれば業務に支障がなくなる場合」を含む。 ２ 前項による休暇の付与は、次により行うものとする。 (1) 「休暇願」（「人事服務関係の願、届について」（1992年７月１日総第22号）に定める様式）に基づき、組織単位の長（組織単位の長が指定した者（直属上長より上位にある者に限る。）を含む。）が承認する。 (2) １年につき６週間以内であれば、夏季及び冬季の２回付与しても差し支えない。 (3) １学部の受講につき24週間以内であれば、５年以上にわたって付与しても差し支えない。 ３ 第１項に定める休暇は、社員就業規則第37条第２項による休暇とし、有給とする。 ４ 第１項に定める休暇期間中の給与については、基本給、成果手当及び採用調整加算の合算した額の10分の3を減額して得た額並びに子育て・介護手当、単身赴任手当及び住宅補助費の全額を支給するものとする。 この場合、月の初日以外の日において新たにこの休暇を付与した場合又は月の末日以外の日においてこの休暇期間が終了した場合における減額すべき額については、「社員給与規則の解釈運用について」（1992年７月１日総第45号）第11条第１項の算出式に基づき、日割によって計算するものとする。 付 則 １ 本通達は、2023年４月１日から実施する。 ２ 「第５章 大学通信教育のスクーリングに参加する者の服務の取扱について」第４項の休暇期間中の給与において、「社員給与規則」（1992年７月１日社長達第22号）の改正（2023年３月31日）付則第３項ないし第12項の措置額を含めて扱う。 ３ 本通達の実施に伴い、「特認休暇について」（1992年7月1日総第16号）、「ＮＴＴドコモグループ記念日における服務等の取扱いについて」（1992年９月24日総第294号）、「被災者支援活動に従事する社員の服務について」（1995年５月15日総勤第２号）、「骨髄バンクへの登録等を行う社員の服務について」（1993年12月24日総勤第78号）及び「大学通信教育のスクーリングに参加する者の服務の取扱について」（1992年７月１日総第23号）を廃止する。 付 則 | AQ9: 0.92271555 | AR9: 36 社員の勤務時間、休日及び休暇について_202504.docx | AS9: 第３ 特別休暇 １ 休暇の理由及び期間 理 由 期 間 | AT9: 0.92483792 | AU9: 02 臨時雇就業規則_202512.docx | AV9: る。 ２ 前項における出勤率の算定にあたっては、第17条第１項第15号に定める出産のための特別休暇、第20条に定める公傷休暇、第29条に定める育児休職及び第30条に定める介護休職を付与した日は出勤したものとみなす。 ３ 年次休暇を与えた日の賃金は、当該勤務日の所定勤務時間を勤務した場合に支払われる通常の賃金とする。 ４ 年次休暇の時季の指定等の取扱いは次のとおりとする。 （1）年次休暇の時季を指定する場合は事前に行わなければならない。 ただし、指定された時季における年次休暇が事業の正常な運営を妨げる場合は、会社は他の時季に変更することができるものとする。 （2）同条第１項の年次休暇が10日以上発効された臨時雇に対して、発効日から１年以内の年次休暇の取得日数が日又は半日単位で５日に満たない場合は、その不足分について、臨時雇の希望を勘案したうえで会社があらかじめ時季を指定し、日又は半日を単位に取得させることとする。 ５ 年次休暇は、原則として日を単位とするが、１時間を単位とすることもできる。 ただし、１時間を単位とした休暇は、休暇発効日より１年以内において５日を上限とする。 なお、休暇の付与日数が５日に満たない場合、発効された日数を上限とする。 ６ １時間を単位とする場合における取り扱いは、次のとおりとする。 (1) １時間を単位とした休暇は１日の所定勤務時間内において、取得時間帯、取得時間数に制限無く取得できる。 (2) １時間単位の休暇は、１日の所定勤務時間数をもって１日分とする。 特別休暇 第 17 条 臨時雇が次の各号の一に該当する理由により勤務日に勤務しないときは、当該各号に定 めるところにより、その者に特別休暇が与えられる。 | AW9: 0.92271555 | AX9: 12 エキスパート1就業規則_202512.docx | AY9: ２ 本条に規定する特別休暇は濫用してはならない。 | AZ9: 0.92598352 | BT9: 0 | BU9: 0 | BZ9: 0 | CA9: 0 | CB9: 20260519T071352-20260519T182604.csv | CC9: 5 | CD9: user > assistant > assistant > tool > assistant | CE9: 1.0.0 | CH9: =IF(OR(CG9="①", CG9="⑤"), "〇", "×") | CI9: =IF(OR(AND($CT9<>"",ISNUMBER(SEARCH($CT9, AP9))),AND($CU9<>"",ISNUMBER(SEARCH($CU9, AP9))),AND($CV9<>"",ISNUMBER(SEARCH($CV9, AP9)))),"〇","-") | CJ9: =IF(OR(AND($CT9<>"",ISNUMBER(SEARCH($CT9, AS9))),AND($CU9<>"",ISNUMBER(SEARCH($CU9, AS9))),AND($CV9<>"",ISNUMBER(SEARCH($CV9, AS9)))),"〇","-") | CK9: =IF(OR(AND($CT9<>"",ISNUMBER(SEARCH($CT9, AV9))),AND($CU9<>"",ISNUMBER(SEARCH($CU9, AV9))),AND($CV9<>"",ISNUMBER(SEARCH($CV9, AV9)))),"〇","-") | CL9: =IF(OR(AND($CT9<>"",ISNUMBER(SEARCH($CT9, AY9))),AND($CU9<>"",ISNUMBER(SEARCH($CU9, AY9))),AND($CV9<>"",ISNUMBER(SEARCH($CV9, AY9)))),"〇","-") | CM9: =IF(OR(AND($CT9<>"",ISNUMBER(SEARCH($CT9, BB9))),AND($CU9<>"",ISNUMBER(SEARCH($CU9, BB9))),AND($CV9<>"",ISNUMBER(SEARCH($CV9, BB9)))),"〇","-") | CN9: =IF(OR(AND($CT9<>"",ISNUMBER(SEARCH($CT9, BE9))),AND($CU9<>"",ISNUMBER(SEARCH($CU9, BE9))),AND($CV9<>"",ISNUMBER(SEARCH($CV9, BE9)))),"〇","-") | CO9: =IF(OR(AND($CT9<>"",ISNUMBER(SEARCH($CT9, BH9))),AND($CU9<>"",ISNUMBER(SEARCH($CU9, BH9))),AND($CV9<>"",ISNUMBER(SEARCH($CV9, BH9)))),"〇","-") | CP9: =IF(OR(AND($CT9<>"",ISNUMBER(SEARCH($CT9, BK9))),AND($CU9<>"",ISNUMBER(SEARCH($CU9, BK9))),AND($CV9<>"",ISNUMBER(SEARCH($CV9, BK9)))),"〇","-") | CQ9: =IF(OR(AND($CT9<>"",ISNUMBER(SEARCH($CT9, BN9))),AND($CU9<>"",ISNUMBER(SEARCH($CU9, BN9))),AND($CV9<>"",ISNUMBER(SEARCH($CV9, BN9)))),"〇","-") | CR9: =IF(OR(AND($CT9<>"",ISNUMBER(SEARCH($CT9, BQ9))),AND($CU9<>"",ISNUMBER(SEARCH($CU9, BQ9))),AND($CV9<>"",ISNUMBER(SEARCH($CV9, BQ9)))),"〇","-") | CW9: =IF(OR(CI9="〇",CJ9="〇",CK9="〇",CL9="〇",CM9="〇",CN9="〇",CO9="〇",CP9="〇",CQ9="〇",CR9="〇"),"〇","") | DE9: =TEXT(U9,"yyyy/mm/dd") | DF9: =VLOOKUP(K9,社員マスタ!C:D,2,0) | DG9: 1779151102632
B10: a:1iSKy7qXCPUl6lHy-2B3xgvRc_tKz1v0JykSQbNaMY5vJSp_4_w19tMqhUwM_oTGTKXV3N-8UzSVsmI-kFbz0LUhY29S-4UuWaWst7uPr3IGvm-BhrKY6KzPsnWAHxMJR-1779151187894-FB000 | C10: =ROW(A10)-3 | D10: a:1iSKy7qXCPUl6lHy-2B3xgvRc_tKz1v0JykSQbNaMY5vJSp_4_w19tMqhUwM_oTGTKXV3N-8UzSVsmI-kFbz0LUhY29S-4UuWaWst7uPr3IGvm-BhrKY6KzPsnWAHxMJR-1779151187894 | E10: 1779151187894 | F10: a:1iSKy7qXCPUl6lHy-2B3xgvRc_tKz1v0JykSQbNaMY5vJSp_4_w19tMqhUwM_oTGTKXV3N-8UzSVsmI-kFbz0LUhY29S-4UuWaWst7uPr3IGvm-BhrKY6KzPsnWAHxMJR | G10: a:1iSKy7qXCPUl6lHy-2B3xgvRc_tKz1v0JykSQbNaMY5vJSp_4_w19tMqhUwM_oTGTKXV3N-8UzSVsmI-kFbz0LUhY29S-4UuWaWst7uPr3IGvm-BhrKY6KzPsnWAHxMJR-S002 | H10: 2 | I10: 2 | J10: 1 | K10: Kazuyo Sorimachi (返町 和代) | L10: DM | M10: 勤務計画に重ねて（休暇）不稼働 を登録するのはあっていますか？ | N10: 勤務計画に重ねて（休暇）不稼働 を登録するのはあっていますか？ | O10: 1 | P10: 0 | Q10: 0 | R10: 0 | S10: 46161.028 | T10: 46161.028 | U10: 46161.403 | V10: 46161.403 | W10: 2.706 | AB10: 未分類 | AC10: none | AD10: 1 | AE10: はい、勤務計画に重ねて「不稼働」の休暇を登録することは適切です。 「不稼働」は業務の一部または全部が停止される場合に使う休暇種別であり、勤務計画上の勤務予定に対して、その期間に勤務できない状況を反映するために登録します。 したがって、勤務計画に対して「不稼働」を重ねて登録することで、実際の勤務が停止されることを正しく管理できます。 ※AIの回答は必ずしも正確ではありません。参照情報も確認いただき、最終判断は所属部署の公式情報をご確認ください。 | AF10: 1 | AG10: 0 | AH10: 1 | AI10: 0 | AJ10: 0 | AL10: 0 | AM10: 0 | AN10: 0 | BT10: 0 | BU10: 0 | BZ10: 0 | CA10: 0 | CB10: 20260519T071352-20260519T182604.csv | CC10: 2 | CD10: user > assistant | CE10: 1.0.0 | CH10: =IF(OR(CG10="①", CG10="⑤"), "〇", "×") | CI10: =IF(OR(AND($CT10<>"",ISNUMBER(SEARCH($CT10, AP10))),AND($CU10<>"",ISNUMBER(SEARCH($CU10, AP10))),AND($CV10<>"",ISNUMBER(SEARCH($CV10, AP10)))),"〇","-") | CJ10: =IF(OR(AND($CT10<>"",ISNUMBER(SEARCH($CT10, AS10))),AND($CU10<>"",ISNUMBER(SEARCH($CU10, AS10))),AND($CV10<>"",ISNUMBER(SEARCH($CV10, AS10)))),"〇","-") | CK10: =IF(OR(AND($CT10<>"",ISNUMBER(SEARCH($CT10, AV10))),AND($CU10<>"",ISNUMBER(SEARCH($CU10, AV10))),AND($CV10<>"",ISNUMBER(SEARCH($CV10, AV10)))),"〇","-") | CL10: =IF(OR(AND($CT10<>"",ISNUMBER(SEARCH($CT10, AY10))),AND($CU10<>"",ISNUMBER(SEARCH($CU10, AY10))),AND($CV10<>"",ISNUMBER(SEARCH($CV10, AY10)))),"〇","-") | CM10: =IF(OR(AND($CT10<>"",ISNUMBER(SEARCH($CT10, BB10))),AND($CU10<>"",ISNUMBER(SEARCH($CU10, BB10))),AND($CV10<>"",ISNUMBER(SEARCH($CV10, BB10)))),"〇","-") | CN10: =IF(OR(AND($CT10<>"",ISNUMBER(SEARCH($CT10, BE10))),AND($CU10<>"",ISNUMBER(SEARCH($CU10, BE10))),AND($CV10<>"",ISNUMBER(SEARCH($CV10, BE10)))),"〇","-") | CO10: =IF(OR(AND($CT10<>"",ISNUMBER(SEARCH($CT10, BH10))),AND($CU10<>"",ISNUMBER(SEARCH($CU10, BH10))),AND($CV10<>"",ISNUMBER(SEARCH($CV10, BH10)))),"〇","-") | CP10: =IF(OR(AND($CT10<>"",ISNUMBER(SEARCH($CT10, BK10))),AND($CU10<>"",ISNUMBER(SEARCH($CU10, BK10))),AND($CV10<>"",ISNUMBER(SEARCH($CV10, BK10)))),"〇","-") | CQ10: =IF(OR(AND($CT10<>"",ISNUMBER(SEARCH($CT10, BN10))),AND($CU10<>"",ISNUMBER(SEARCH($CU10, BN10))),AND($CV10<>"",ISNUMBER(SEARCH($CV10, BN10)))),"〇","-") | CR10: =IF(OR(AND($CT10<>"",ISNUMBER(SEARCH($CT10, BQ10))),AND($CU10<>"",ISNUMBER(SEARCH($CU10, BQ10))),AND($CV10<>"",ISNUMBER(SEARCH($CV10, BQ10)))),"〇","-") | CW10: =IF(OR(CI10="〇",CJ10="〇",CK10="〇",CL10="〇",CM10="〇",CN10="〇",CO10="〇",CP10="〇",CQ10="〇",CR10="〇"),"〇","") | DE10: =TEXT(U10,"yyyy/mm/dd") | DF10: =VLOOKUP(K10,社員マスタ!C:D,2,0) | DG10: 1779151187894
B11: a:1iSKy7qXCPUl6lHy-2B3xgvRc_tKz1v0JykSQbNaMY5vJSp_4_w19tMqhUwM_oTGTKXV3N-8UzSVsmI-kFbz0LUhY29S-4UuWaWst7uPr3IGvm-BhrKY6KzPsnWAHxMJR-1779151482515-FB000 | C11: =ROW(A11)-3 | D11: a:1iSKy7qXCPUl6lHy-2B3xgvRc_tKz1v0JykSQbNaMY5vJSp_4_w19tMqhUwM_oTGTKXV3N-8UzSVsmI-kFbz0LUhY29S-4UuWaWst7uPr3IGvm-BhrKY6KzPsnWAHxMJR-1779151482515 | E11: 1779151482515 | F11: a:1iSKy7qXCPUl6lHy-2B3xgvRc_tKz1v0JykSQbNaMY5vJSp_4_w19tMqhUwM_oTGTKXV3N-8UzSVsmI-kFbz0LUhY29S-4UuWaWst7uPr3IGvm-BhrKY6KzPsnWAHxMJR | G11: a:1iSKy7qXCPUl6lHy-2B3xgvRc_tKz1v0JykSQbNaMY5vJSp_4_w19tMqhUwM_oTGTKXV3N-8UzSVsmI-kFbz0LUhY29S-4UuWaWst7uPr3IGvm-BhrKY6KzPsnWAHxMJR-S002 | H11: 2 | I11: 3 | J11: 1 | K11: Kazuyo Sorimachi (返町 和代) | L11: DM | M11: 休憩時間について教えてください。 ↓の休憩時間の取り方はあっていますか？ | N11: 休憩時間について教えてください。 ↓の休憩時間の取り方はあっていますか？ | O11: 1 | P11: 0 | Q11: 0 | R11: 0 | S11: 46161.031 | T11: 46161.031 | U11: 46161.406 | V11: 46161.406 | W11: 6.02 | X11: searchEmployeeRules | AB11: 未分類 | AC11: none | AD11: 1 | AE11: 休憩時間の取り方について、以下の内容が基本となります。 - 休憩時間は、少なくとも拘束2時間ごとに15分の割合で与えられます。 - 勤務時間が拘束4時間以下の場合は、休憩が与えられないこともあります。 - 休憩時間は勤務の途中で、継続して取ることも、分割して取ることも可能です。 また、フレックスタイム制の場合は勤務時間に応じて休憩時間が決まります。 - 1日5時間以上7時間未満の勤務：45分 - 1日7時間以上の勤務：60分 ご自身の勤務形態や勤務時間に合わせて、上記のルールに沿って休憩を取ることが正しい取り方です。 ※AIの回答は必ずしも正確ではありません。参照情報も確認いただき、最終判断は所属部署の公式情報をご確認ください。 | AF11: 1 | AG11: 0 | AH11: 2 | AI11: 0 | AJ11: 0 | AL11: 4 | AM11: 4 | AN11: 0 | AO11: 39 勤務時間、休日、休暇、休職及び勤務票等について_202511.docx | AP11: 第３章 深夜勤務に伴う休息時間確保のための配慮措置について 深夜勤務に伴う休息時間確保のための配慮措置については、以下のとおりとする。 １．目的 社員等の健康確保並びに生産性の向上に資する観点から、深夜勤務について原則禁止としているところであるが、真にやむを得ない事由により、深夜勤務を実施した社員等が一定の休息時間を確保できる環境整備に努めることとする。 ２．対象者 管理監督者を含む全雇用区分とする。 ３．午前０時を超える深夜勤務を実施した場合、翌日における勤務時間の弾力的運用 (1) 定型勤務、交替勤務が適用される者 直属上長は、翌日の始終業時刻の変更により、社員等の休息時間を確保できる環境整備に努める。 始業時刻及び終業時刻の変更については、服務種別ごとの始終業時刻設定可能な時間帯において、30分を単位とし社員等の了解を得て実施することができる。 (2) フレックスタイム制が適用される者 直属上長は、翌日の始終業時刻の調整を促すことで、社員等の休息時間を確保できる環境整備に努める。なお、必要に応じてコアタイム解除を行う。 なお、コアタイムを設定しないフレックスタイム制が適用される者については、直属上長は、翌日の始業時刻の調整により、社員等の休息時間を確保できるよう助言指導を行う。 ４．休暇取得の環境整備 午前０時を超える深夜勤務を実施した日の翌日または翌々日について、社員等が年次休暇、ライフプラン休暇の取得を申請する場合は、最大限の配慮を行う。 リフレッシュのためのライフプラン休暇の取得については、休息時間を確保する観点から、午前０時を超える深夜勤務を実施した場合に、原則として深夜勤務明けの日に、日または時間単位のライフプラン休暇の取得を可能とする。 なお、深夜勤務明けの日に勤務した場合は、深夜勤務明けの日の翌日まで取得を可能とする。 第４章 社員の病気休職、刑事休職、解雇、降職及び退職について 社員の病気休職、刑事休職、解雇、降職及び退職については、以下のとおりとする。 第1 休職及び復職 | AQ11: 0.92762333 | AR11: 02 臨時雇就業規則_202512.docx | AS11: ２ 前項の始業及び終業の時刻は、業務の都合又は本人の希望により変更することがある。 休憩時間 第 11 条 休憩時間は、少なくとも拘束２時間について15分の割合で計算した時間を与えられる。 ただし、勤務時間が拘束４時間以下であるときは与えられないことがある。 ２ 休憩時間は勤務の途中において、継続し、又は分割して与えられる。 時間外及び休日の勤務 第 12 条 １日について勤務時間８時間、１週間について勤務時間40時間を超えない限りにおいて第９条及び第14条の規定にかかわらず、１日の所定勤務時間を超えて、又は４週４日以外の休日に勤務を命ぜられることがある。 ２ 次の各号の一に該当する場合においては、前項の規定にかかわらず、時間外又は休日に勤務を命ぜられることがある。 (1) 労働基準法第36条の規定により協定を締結したとき (2) 労働基準法第33条の規定により労働基準監督署に所定の手続きをしたとき ３ 労働基準法第41条第３号の許可を受けた者は、前各項の規定にかかわらず、時間外又は休日に勤務を命ぜられることがある。 第２節 リモートワーク リモートワーク 第 13 条 臨時雇が所属長にリモートワークを申し出たとき、または会社指示により、勤務事業所以外を勤務場所とすることがある。 ２ 会社が貸与する情報通信機器等を除き、リモートワークに関わる費用については、臨時雇が負担する。 第３節 休日及び休暇 休 日 第 14 条 休日は、原則として次のとおりとし、４週４日を下回らないよう個別の雇用契約において定める。 (1) 毎週日曜日及び土曜日 (2) 個別の雇用契約において定めた日 ２ 前項の休日は、業務上やむを得ない理由があるときは、他の日に変更されることがある。 休暇の種類 第 15 条 休暇には、次の種類がある。 （１）有給休暇 ア 年次休暇 イ 特別休暇 ウ 病気休暇 エ 特別連続休暇 （２）無給休暇 ア 看護等休暇 イ 介護のための短期の休暇 （３）その他 ア 公傷休暇 イ 通勤災害休暇 ２ 前項の休暇のほか、社長が必要と認めた場合に休暇が与えられることがある。 年次休暇 | AT11: 0.9280667 | AU11: 健康管理規程.pdf | AV11: ア 日勤服務以外の服務につかせない。ただし、やむを得ぬ理由で夜勤服務につかせる場合は、組織の 長と産業医が協議して決める。 イ 健康状態に応じて、勤務時間中に休養時間を与えるか、又は作業環境、労働負荷を考慮して、勤務 内容の軽減をはかる。 (ｱ) 休養時間中は、原則として事業所内の休憩室等で休養させる。ただし、通勤所要時間、交通機 関等の諸事情を考慮して、勤務の始め又は終りに休養時間を与えることができる。 (ｲ) 休養時間は、１日の所定勤務時間から休養時間を除いた時間が、拘束４時間を下回らない範囲 で与えるものとする。 (ｳ) 勤務内容の軽減をはかる場合には、必要に応じて勤務場所の変更、業務の転換等を行うものと する。 ウ 過激な運動を伴う業務、時間外労働、宿泊出張はさせない。 (3) 要注意（Ｃ）の服務については、次の各項によることとする。 ア 日勤服務以外の服務につかせない。ただし、やむを得ぬ理由で前記の服務以外の服務につかせる場 合は、組織の長と産業医が協議して決める。 イ 時間外労働はさせない。ただし、やむを得ぬ理由で時間外労働をさせる場合は、組織の長と産業医 が協議して決める。この場合においても、１日２時間、１週２回を限度とする。 | AW11: 0.92762333 | AX11: 01 社員就業規則等_202512.docx | AY11: ２ 宿直については、睡眠時間を含み８時間以内の休憩時間が与えられる。 ３ 日直又は宿直の当直時間については、所属長が定めるところによる。 出張、赴任等の場合の勤務時間 第 29 条 社員が出張し、若しくは赴任し、又は所属長のもとを離れて勤務する場合における勤務時間については、特に命ぜられた場合を除くほか、所定の勤務時間を勤務したものとみなす。 第２節 フレックスタイム制 対象者 第 30 条 社員は、第20条から第27条までの規定にかかわらず、次条以下に規定するフレックスタイム制が適用されることがある。 基準労働時間 第 31 条 前条に定める社員は、各清算期間（各月１日から月末まで）において、基準労働時間（週休日を日曜日及び土曜日に設定する社員の当該清算期間における所定労働日の勤務時間（１日７時間30分。ただし、第64条第３項及び第67条第２項に規定する短時間勤務を行う者については、１日４時間、５時間又は６時間のいずれかの時間）を合計して得た時間をいう。）を勤務しなければならない。 コアタイム及びフレキシブルタイム 第 32 条 コアタイム及びフレキシブルタイムは、次のとおりとする。 （１） コアタイム（全員が勤務しなければならない時間帯） ① 標準的なコアタイムは、午前10時から午後３時まで（正午から午後１時までは休憩時間）の４時間とする。 なお、具体的な設定時刻は、労働基準法第32条の３に規定する協定により定める。 ② 第64条第３項及び第67条第２項に規定する短時間勤務を行う者の標準的なコアタイムは、午前10時から午後２時（正午から午後１時までは休憩時間）の３時間とする。なお、具体的な設定時刻は、労働基準法第32条の３に規定する協定により定める。 ③ コアタイムを設定しない場合は、１日の最低勤務時間を３時間とする。 なお、具体的には労働基準法第32条の３に規定する協定により定める。 また、コアタイムを設定しない場合における休憩時間は、次のとおりとし、勤務の途中において適用社員の裁量により設定する。 ア １日５時間以上７時間未満の勤務 45分 イ １日７時間以上の勤務 60分 （２）フレキシブルタイム（社員が自主的に始業・終業時刻を選択できる時間帯） | AZ11: 0.93041365 | BT11: 0 | BU11: 0 | BZ11: 0 | CA11: 0 | CB11: 20260519T071352-20260519T182604.csv | CC11: 4 | CD11: user > assistant > tool > assistant | CE11: 1.0.0 | CH11: =IF(OR(CG11="①", CG11="⑤"), "〇", "×") | CI11: =IF(OR(AND($CT11<>"",ISNUMBER(SEARCH($CT11, AP11))),AND($CU11<>"",ISNUMBER(SEARCH($CU11, AP11))),AND($CV11<>"",ISNUMBER(SEARCH($CV11, AP11)))),"〇","-") | CJ11: =IF(OR(AND($CT11<>"",ISNUMBER(SEARCH($CT11, AS11))),AND($CU11<>"",ISNUMBER(SEARCH($CU11, AS11))),AND($CV11<>"",ISNUMBER(SEARCH($CV11, AS11)))),"〇","-") | CK11: =IF(OR(AND($CT11<>"",ISNUMBER(SEARCH($CT11, AV11))),AND($CU11<>"",ISNUMBER(SEARCH($CU11, AV11))),AND($CV11<>"",ISNUMBER(SEARCH($CV11, AV11)))),"〇","-") | CL11: =IF(OR(AND($CT11<>"",ISNUMBER(SEARCH($CT11, AY11))),AND($CU11<>"",ISNUMBER(SEARCH($CU11, AY11))),AND($CV11<>"",ISNUMBER(SEARCH($CV11, AY11)))),"〇","-") | CM11: =IF(OR(AND($CT11<>"",ISNUMBER(SEARCH($CT11, BB11))),AND($CU11<>"",ISNUMBER(SEARCH($CU11, BB11))),AND($CV11<>"",ISNUMBER(SEARCH($CV11, BB11)))),"〇","-") | CN11: =IF(OR(AND($CT11<>"",ISNUMBER(SEARCH($CT11, BE11))),AND($CU11<>"",ISNUMBER(SEARCH($CU11, BE11))),AND($CV11<>"",ISNUMBER(SEARCH($CV11, BE11)))),"〇","-") | CO11: =IF(OR(AND($CT11<>"",ISNUMBER(SEARCH($CT11, BH11))),AND($CU11<>"",ISNUMBER(SEARCH($CU11, BH11))),AND($CV11<>"",ISNUMBER(SEARCH($CV11, BH11)))),"〇","-") | CP11: =IF(OR(AND($CT11<>"",ISNUMBER(SEARCH($CT11, BK11))),AND($CU11<>"",ISNUMBER(SEARCH($CU11, BK11))),AND($CV11<>"",ISNUMBER(SEARCH($CV11, BK11)))),"〇","-") | CQ11: =IF(OR(AND($CT11<>"",ISNUMBER(SEARCH($CT11, BN11))),AND($CU11<>"",ISNUMBER(SEARCH($CU11, BN11))),AND($CV11<>"",ISNUMBER(SEARCH($CV11, BN11)))),"〇","-") | CR11: =IF(OR(AND($CT11<>"",ISNUMBER(SEARCH($CT11, BQ11))),AND($CU11<>"",ISNUMBER(SEARCH($CU11, BQ11))),AND($CV11<>"",ISNUMBER(SEARCH($CV11, BQ11)))),"〇","-") | CW11: =IF(OR(CI11="〇",CJ11="〇",CK11="〇",CL11="〇",CM11="〇",CN11="〇",CO11="〇",CP11="〇",CQ11="〇",CR11="〇"),"〇","") | DE11: =TEXT(U11,"yyyy/mm/dd") | DF11: =VLOOKUP(K11,社員マスタ!C:D,2,0) | DG11: 1779151482515
B12: a:1iSKy7qXCPUl6lHy-2B3xgvRc_tKz1v0JykSQbNaMY5vJSp_4_w19tMqhUwM_oTGTKXV3N-8UzSVsmI-kFbz0LUhY29S-4UuWaWst7uPr3IGvm-BhrKY6KzPsnWAHxMJR-1779151514894-FB000 | C12: =ROW(A12)-3 | D12: a:1iSKy7qXCPUl6lHy-2B3xgvRc_tKz1v0JykSQbNaMY5vJSp_4_w19tMqhUwM_oTGTKXV3N-8UzSVsmI-kFbz0LUhY29S-4UuWaWst7uPr3IGvm-BhrKY6KzPsnWAHxMJR-1779151514894 | E12: 1779151514894 | F12: a:1iSKy7qXCPUl6lHy-2B3xgvRc_tKz1v0JykSQbNaMY5vJSp_4_w19tMqhUwM_oTGTKXV3N-8UzSVsmI-kFbz0LUhY29S-4UuWaWst7uPr3IGvm-BhrKY6KzPsnWAHxMJR | G12: a:1iSKy7qXCPUl6lHy-2B3xgvRc_tKz1v0JykSQbNaMY5vJSp_4_w19tMqhUwM_oTGTKXV3N-8UzSVsmI-kFbz0LUhY29S-4UuWaWst7uPr3IGvm-BhrKY6KzPsnWAHxMJR-S002 | H12: 2 | I12: 4 | J12: 1 | K12: Kazuyo Sorimachi (返町 和代) | L12: DM | M12: 60分以上の休憩が与えられるケースを教えてください。 | N12: 60分以上の休憩が与えられるケースを教えてください。 | O12: 1 | P12: 0 | Q12: 0 | R12: 0 | S12: 46161.031 | T12: 46161.031 | U12: 46161.406 | V12: 46161.406 | W12: 2.558 | AB12: 未分類 | AC12: none | AD12: 1 | AE12: 検索結果には「60分以上の休憩が与えられるケース」についての具体的な記載はありません。 ただし、一般的なルールとしては、1日の勤務時間が7時間以上の場合に60分の休憩が与えられることが基本です。 60分を超える休憩が与えられるかどうかは、勤務形態や業務の特性、所属長の判断などによる場合がありますので、詳細は勤務先の規定に従うことになります。 ※AIの回答は必ずしも正確ではありません。参照情報も確認いただき、最終判断は所属部署の公式情報をご確認ください。 | AF12: 1 | AG12: 0 | AH12: 1 | AI12: 0 | AJ12: 0 | AL12: 0 | AM12: 0 | AN12: 0 | BT12: 0 | BU12: 0 | BZ12: 0 | CA12: 0 | CB12: 20260519T071352-20260519T182604.csv | CC12: 2 | CD12: user > assistant | CE12: 1.0.0 | CH12: =IF(OR(CG12="①", CG12="⑤"), "〇", "×") | CI12: =IF(OR(AND($CT12<>"",ISNUMBER(SEARCH($CT12, AP12))),AND($CU12<>"",ISNUMBER(SEARCH($CU12, AP12))),AND($CV12<>"",ISNUMBER(SEARCH($CV12, AP12)))),"〇","-") | CJ12: =IF(OR(AND($CT12<>"",ISNUMBER(SEARCH($CT12, AS12))),AND($CU12<>"",ISNUMBER(SEARCH($CU12, AS12))),AND($CV12<>"",ISNUMBER(SEARCH($CV12, AS12)))),"〇","-") | CK12: =IF(OR(AND($CT12<>"",ISNUMBER(SEARCH($CT12, AV12))),AND($CU12<>"",ISNUMBER(SEARCH($CU12, AV12))),AND($CV12<>"",ISNUMBER(SEARCH($CV12, AV12)))),"〇","-") | CL12: =IF(OR(AND($CT12<>"",ISNUMBER(SEARCH($CT12, AY12))),AND($CU12<>"",ISNUMBER(SEARCH($CU12, AY12))),AND($CV12<>"",ISNUMBER(SEARCH($CV12, AY12)))),"〇","-") | CM12: =IF(OR(AND($CT12<>"",ISNUMBER(SEARCH($CT12, BB12))),AND($CU12<>"",ISNUMBER(SEARCH($CU12, BB12))),AND($CV12<>"",ISNUMBER(SEARCH($CV12, BB12)))),"〇","-") | CN12: =IF(OR(AND($CT12<>"",ISNUMBER(SEARCH($CT12, BE12))),AND($CU12<>"",ISNUMBER(SEARCH($CU12, BE12))),AND($CV12<>"",ISNUMBER(SEARCH($CV12, BE12)))),"〇","-") | CO12: =IF(OR(AND($CT12<>"",ISNUMBER(SEARCH($CT12, BH12))),AND($CU12<>"",ISNUMBER(SEARCH($CU12, BH12))),AND($CV12<>"",ISNUMBER(SEARCH($CV12, BH12)))),"〇","-") | CP12: =IF(OR(AND($CT12<>"",ISNUMBER(SEARCH($CT12, BK12))),AND($CU12<>"",ISNUMBER(SEARCH($CU12, BK12))),AND($CV12<>"",ISNUMBER(SEARCH($CV12, BK12)))),"〇","-") | CQ12: =IF(OR(AND($CT12<>"",ISNUMBER(SEARCH($CT12, BN12))),AND($CU12<>"",ISNUMBER(SEARCH($CU12, BN12))),AND($CV12<>"",ISNUMBER(SEARCH($CV12, BN12)))),"〇","-") | CR12: =IF(OR(AND($CT12<>"",ISNUMBER(SEARCH($CT12, BQ12))),AND($CU12<>"",ISNUMBER(SEARCH($CU12, BQ12))),AND($CV12<>"",ISNUMBER(SEARCH($CV12, BQ12)))),"〇","-") | CW12: =IF(OR(CI12="〇",CJ12="〇",CK12="〇",CL12="〇",CM12="〇",CN12="〇",CO12="〇",CP12="〇",CQ12="〇",CR12="〇"),"〇","") | DE12: =TEXT(U12,"yyyy/mm/dd") | DF12: =VLOOKUP(K12,社員マスタ!C:D,2,0) | DG12: 1779151514894
B13: a:1JLO3RMA3dGDJ6trWaPOK9_WG46rAdOWrKm6T_qmj6NMRMZgHtUG8tgujTisHfxPb28jndJqRk-OtgP8ATBjscnD-HNvViO0wGLGYw1bS8Dokd9VThBEKv2raN2Y39SRt-1779158719857-FB000 | C13: =ROW(A13)-3 | D13: a:1JLO3RMA3dGDJ6trWaPOK9_WG46rAdOWrKm6T_qmj6NMRMZgHtUG8tgujTisHfxPb28jndJqRk-OtgP8ATBjscnD-HNvViO0wGLGYw1bS8Dokd9VThBEKv2raN2Y39SRt-1779158719857 | E13: 1779158719857 | F13: a:1JLO3RMA3dGDJ6trWaPOK9_WG46rAdOWrKm6T_qmj6NMRMZgHtUG8tgujTisHfxPb28jndJqRk-OtgP8ATBjscnD-HNvViO0wGLGYw1bS8Dokd9VThBEKv2raN2Y39SRt | G13: a:1JLO3RMA3dGDJ6trWaPOK9_WG46rAdOWrKm6T_qmj6NMRMZgHtUG8tgujTisHfxPb28jndJqRk-OtgP8ATBjscnD-HNvViO0wGLGYw1bS8Dokd9VThBEKv2raN2Y39SRt-S001 | H13: 1 | I13: 1 | J13: 1 | K13: Yuusuke Amano (天野 優介) | L13: DM | M13: タレマネの一次評価と2次評価それぞれみることができる？ | N13: タレマネの一次評価と2次評価それぞれみることができる？ | O13: 1 | P13: 0 | Q13: 0 | R13: 0 | S13: 46161.115 | T13: 46161.115 | U13: 46161.49 | V13: 46161.49 | W13: 5.761 | X13: searchEmployeeRules | Y13: タレマネ > 社員用 | AA13: タレマネ | AB13: タレマネ > 社員用 | AC13: predicted | AD13: 0 | AE13: 検索結果からは、タレマネの一次評価者の情報が古い場合や評価フォームの操作に関する案内が見つかっていますが、「一次評価」と「二次評価」それぞれを閲覧できるかどうかについての具体的な記載はありませんでした。 一次評価者の情報が異なったままの場合や、評価フォームの操作に関しては、下記のURLで詳細が確認できます。 https://www.hdservice1.nttls.co.jp/hc/ja/articles/17842855242519 もし評価の閲覧方法について詳細が必要な場合は、上記URLを参考にしてください。 ※AIの回答は必ずしも正確ではありません。参照情報も確認いただき、最終判断は所属部署の公式情報をご確認ください。 | AF13: 1 | AG13: 0 | AH13: 3 | AI13: 0 | AJ13: 0 | AL13: 4 | AM13: 4 | AN13: 0 | AO13: QA614_system_talemane_talemane-employee.md | AP13: 質問 プロファイル画面から上長設定を行って新上長に変更したが、「一次評価者」が異なったまま(古い情報のまま)となっている場合、どうしたらいいでしょうか。 回答 「一次評価者」が異なったまま(古い情報のまま)となっている場合は以下URLをご確認ください。 https://www.hdservice1.nttls.co.jp/hc/ja/articles/17842855242519 | AQ13: 0.91305703 | AR13: QA609_system_talemane_talemane-employee.md | AS13: 質問 目標設定・評価フォームを「システムステップ」まで進めてしまい動かせなくなった場合、どうしたらいいでしょうか。 回答 目標設定・評価フォームを「システムステップ」まで進めてしまい動かせなくなった場合は以下URLをご確認ください。 https://www.hdservice1.nttls.co.jp/hc/ja/articles/19052461933335 | AT13: 0.90775595 | AU13: QA619_system_talemane_talemane-employee.md | AV13: 質問 目標設定・評価フォームが「ロック」され上長側で記入できない場合、どうしたらいいでしょうか。 回答 目標設定・評価フォームが「ロック」され上長側で記入できない場合は以下URLをご確認ください。 https://www.hdservice1.nttls.co.jp/hc/ja/articles/18295484365591 | AW13: 0.91305703 | AX13: QA604_system_talemane_talemane-employee.md | AY13: 質問 目標設定・評価フォームを既に上長へ送ったのに「署名」を求められる場合、どうしたらいいでしょうか。 回答 目標設定・評価フォームを上長へ送ったのに「署名」を求められる場合は以下URLをご確認ください。 https://www.hdservice1.nttls.co.jp/hc/ja/articles/18241101016983 | AZ13: 0.9051388 | BT13: 0 | BU13: 0 | BZ13: 0 | CA13: 0 | CB13: 20260519T071352-20260519T182604.csv | CC13: 5 | CD13: user > assistant > assistant > tool > assistant | CE13: 1.0.0 | CH13: =IF(OR(CG13="①", CG13="⑤"), "〇", "×") | CI13: =IF(OR(AND($CT13<>"",ISNUMBER(SEARCH($CT13, AP13))),AND($CU13<>"",ISNUMBER(SEARCH($CU13, AP13))),AND($CV13<>"",ISNUMBER(SEARCH($CV13, AP13)))),"〇","-") | CJ13: =IF(OR(AND($CT13<>"",ISNUMBER(SEARCH($CT13, AS13))),AND($CU13<>"",ISNUMBER(SEARCH($CU13, AS13))),AND($CV13<>"",ISNUMBER(SEARCH($CV13, AS13)))),"〇","-") | CK13: =IF(OR(AND($CT13<>"",ISNUMBER(SEARCH($CT13, AV13))),AND($CU13<>"",ISNUMBER(SEARCH($CU13, AV13))),AND($CV13<>"",ISNUMBER(SEARCH($CV13, AV13)))),"〇","-") | CL13: =IF(OR(AND($CT13<>"",ISNUMBER(SEARCH($CT13, AY13))),AND($CU13<>"",ISNUMBER(SEARCH($CU13, AY13))),AND($CV13<>"",ISNUMBER(SEARCH($CV13, AY13)))),"〇","-") | CM13: =IF(OR(AND($CT13<>"",ISNUMBER(SEARCH($CT13, BB13))),AND($CU13<>"",ISNUMBER(SEARCH($CU13, BB13))),AND($CV13<>"",ISNUMBER(SEARCH($CV13, BB13)))),"〇","-") | CN13: =IF(OR(AND($CT13<>"",ISNUMBER(SEARCH($CT13, BE13))),AND($CU13<>"",ISNUMBER(SEARCH($CU13, BE13))),AND($CV13<>"",ISNUMBER(SEARCH($CV13, BE13)))),"〇","-") | CO13: =IF(OR(AND($CT13<>"",ISNUMBER(SEARCH($CT13, BH13))),AND($CU13<>"",ISNUMBER(SEARCH($CU13, BH13))),AND($CV13<>"",ISNUMBER(SEARCH($CV13, BH13)))),"〇","-") | CP13: =IF(OR(AND($CT13<>"",ISNUMBER(SEARCH($CT13, BK13))),AND($CU13<>"",ISNUMBER(SEARCH($CU13, BK13))),AND($CV13<>"",ISNUMBER(SEARCH($CV13, BK13)))),"〇","-") | CQ13: =IF(OR(AND($CT13<>"",ISNUMBER(SEARCH($CT13, BN13))),AND($CU13<>"",ISNUMBER(SEARCH($CU13, BN13))),AND($CV13<>"",ISNUMBER(SEARCH($CV13, BN13)))),"〇","-") | CR13: =IF(OR(AND($CT13<>"",ISNUMBER(SEARCH($CT13, BQ13))),AND($CU13<>"",ISNUMBER(SEARCH($CU13, BQ13))),AND($CV13<>"",ISNUMBER(SEARCH($CV13, BQ13)))),"〇","-") | CW13: =IF(OR(CI13="〇",CJ13="〇",CK13="〇",CL13="〇",CM13="〇",CN13="〇",CO13="〇",CP13="〇",CQ13="〇",CR13="〇"),"〇","") | DE13: =TEXT(U13,"yyyy/mm/dd") | DF13: =VLOOKUP(K13,社員マスタ!C:D,2,0) | DG13: 1779158719857
B14: a:1LUvO3KIgrjNGvMw6gRnBwZOrWZM2ktO1-kHzfdc2V7WGbo6qHI6iWXDVNfEh6DM8-szX0djZvTGtbMN46T9vUbamuuBtU9E9yXNF5dWtyuhP9ieTD5T32rvvBva6dnKz-1779165428360-FB000 | C14: =ROW(A14)-3 | D14: a:1LUvO3KIgrjNGvMw6gRnBwZOrWZM2ktO1-kHzfdc2V7WGbo6qHI6iWXDVNfEh6DM8-szX0djZvTGtbMN46T9vUbamuuBtU9E9yXNF5dWtyuhP9ieTD5T32rvvBva6dnKz-1779165428360 | E14: 1779165428360 | F14: a:1LUvO3KIgrjNGvMw6gRnBwZOrWZM2ktO1-kHzfdc2V7WGbo6qHI6iWXDVNfEh6DM8-szX0djZvTGtbMN46T9vUbamuuBtU9E9yXNF5dWtyuhP9ieTD5T32rvvBva6dnKz | G14: a:1LUvO3KIgrjNGvMw6gRnBwZOrWZM2ktO1-kHzfdc2V7WGbo6qHI6iWXDVNfEh6DM8-szX0djZvTGtbMN46T9vUbamuuBtU9E9yXNF5dWtyuhP9ieTD5T32rvvBva6dnKz-S001 | H14: 1 | I14: 1 | J14: 1 | K14: Mikiko Nakanishi (中西 美木子) | L14: DM | N14: カテゴリ | O14: 0 | P14: 0 | Q14: 0 | R14: 1 | S14: 46161.192 | T14: 46161.192 | U14: 46161.567 | V14: 46161.567 | W14: 0 | AB14: 未分類 | AC14: none | AD14: 1 | AF14: 0 | AG14: 0 | AH14: 0 | AI14: 0 | AJ14: 0 | AL14: 0 | AM14: 0 | AN14: 0 | BT14: 0 | BU14: 0 | BZ14: 0 | CA14: 0 | CB14: 20260519T071352-20260519T182604.csv | CC14: 1 | CD14: user | CE14: 1.0.0 | CF14: no answer found | CH14: =IF(OR(CG14="①", CG14="⑤"), "〇", "×") | CI14: =IF(OR(AND($CT14<>"",ISNUMBER(SEARCH($CT14, AP14))),AND($CU14<>"",ISNUMBER(SEARCH($CU14, AP14))),AND($CV14<>"",ISNUMBER(SEARCH($CV14, AP14)))),"〇","-") | CJ14: =IF(OR(AND($CT14<>"",ISNUMBER(SEARCH($CT14, AS14))),AND($CU14<>"",ISNUMBER(SEARCH($CU14, AS14))),AND($CV14<>"",ISNUMBER(SEARCH($CV14, AS14)))),"〇","-") | CK14: =IF(OR(AND($CT14<>"",ISNUMBER(SEARCH($CT14, AV14))),AND($CU14<>"",ISNUMBER(SEARCH($CU14, AV14))),AND($CV14<>"",ISNUMBER(SEARCH($CV14, AV14)))),"〇","-") | CL14: =IF(OR(AND($CT14<>"",ISNUMBER(SEARCH($CT14, AY14))),AND($CU14<>"",ISNUMBER(SEARCH($CU14, AY14))),AND($CV14<>"",ISNUMBER(SEARCH($CV14, AY14)))),"〇","-") | CM14: =IF(OR(AND($CT14<>"",ISNUMBER(SEARCH($CT14, BB14))),AND($CU14<>"",ISNUMBER(SEARCH($CU14, BB14))),AND($CV14<>"",ISNUMBER(SEARCH($CV14, BB14)))),"〇","-") | CN14: =IF(OR(AND($CT14<>"",ISNUMBER(SEARCH($CT14, BE14))),AND($CU14<>"",ISNUMBER(SEARCH($CU14, BE14))),AND($CV14<>"",ISNUMBER(SEARCH($CV14, BE14)))),"〇","-") | CO14: =IF(OR(AND($CT14<>"",ISNUMBER(SEARCH($CT14, BH14))),AND($CU14<>"",ISNUMBER(SEARCH($CU14, BH14))),AND($CV14<>"",ISNUMBER(SEARCH($CV14, BH14)))),"〇","-") | CP14: =IF(OR(AND($CT14<>"",ISNUMBER(SEARCH($CT14, BK14))),AND($CU14<>"",ISNUMBER(SEARCH($CU14, BK14))),AND($CV14<>"",ISNUMBER(SEARCH($CV14, BK14)))),"〇","-") | CQ14: =IF(OR(AND($CT14<>"",ISNUMBER(SEARCH($CT14, BN14))),AND($CU14<>"",ISNUMBER(SEARCH($CU14, BN14))),AND($CV14<>"",ISNUMBER(SEARCH($CV14, BN14)))),"〇","-") | CR14: =IF(OR(AND($CT14<>"",ISNUMBER(SEARCH($CT14, BQ14))),AND($CU14<>"",ISNUMBER(SEARCH($CU14, BQ14))),AND($CV14<>"",ISNUMBER(SEARCH($CV14, BQ14)))),"〇","-") | CW14: =IF(OR(CI14="〇",CJ14="〇",CK14="〇",CL14="〇",CM14="〇",CN14="〇",CO14="〇",CP14="〇",CQ14="〇",CR14="〇"),"〇","") | DE14: =TEXT(U14,"yyyy/mm/dd") | DF14: =VLOOKUP(K14,社員マスタ!C:D,2,0) | DG14: 1779165428360
B15: a:1LUvO3KIgrjNGvMw6gRnBwZOrWZM2ktO1-kHzfdc2V7WGbo6qHI6iWXDVNfEh6DM8-szX0djZvTGtbMN46T9vUbamuuBtU9E9yXNF5dWtyuhP9ieTD5T32rvvBva6dnKz-f:7c38f845-69e4-4c97-b890-7c24a715e079-FB000 | C15: =ROW(A15)-3 | D15: a:1LUvO3KIgrjNGvMw6gRnBwZOrWZM2ktO1-kHzfdc2V7WGbo6qHI6iWXDVNfEh6DM8-szX0djZvTGtbMN46T9vUbamuuBtU9E9yXNF5dWtyuhP9ieTD5T32rvvBva6dnKz-f:7c38f845-69e4-4c97-b890-7c24a715e079 | E15: f:7c38f845-69e4-4c97-b890-7c24a715e079 | F15: a:1LUvO3KIgrjNGvMw6gRnBwZOrWZM2ktO1-kHzfdc2V7WGbo6qHI6iWXDVNfEh6DM8-szX0djZvTGtbMN46T9vUbamuuBtU9E9yXNF5dWtyuhP9ieTD5T32rvvBva6dnKz | G15: a:1LUvO3KIgrjNGvMw6gRnBwZOrWZM2ktO1-kHzfdc2V7WGbo6qHI6iWXDVNfEh6DM8-szX0djZvTGtbMN46T9vUbamuuBtU9E9yXNF5dWtyuhP9ieTD5T32rvvBva6dnKz-S001 | H15: 1 | I15: 2 | J15: 1 | K15: Mikiko Nakanishi (中西 美木子) | L15: DM | N15: [カテゴリ選択] | O15: 0 | P15: 0 | Q15: 1 | R15: 0 | S15: 46161.193 | T15: 46161.193 | U15: 46161.568 | V15: 46161.568 | W15: 0 | Z15: システム操作 | AB15: システム操作 | AC15: user_selected | AD15: 0 | AF15: 0 | AG15: 0 | AH15: 0 | AI15: 0 | AJ15: 0 | AL15: 0 | AM15: 0 | AN15: 0 | BT15: 0 | BU15: 0 | BZ15: 0 | CA15: 0 | CB15: 20260519T071352-20260519T182604.csv | CC15: 1 | CD15: user | CE15: 1.0.0 | CH15: =IF(OR(CG15="①", CG15="⑤"), "〇", "×") | CI15: =IF(OR(AND($CT15<>"",ISNUMBER(SEARCH($CT15, AP15))),AND($CU15<>"",ISNUMBER(SEARCH($CU15, AP15))),AND($CV15<>"",ISNUMBER(SEARCH($CV15, AP15)))),"〇","-") | CJ15: =IF(OR(AND($CT15<>"",ISNUMBER(SEARCH($CT15, AS15))),AND($CU15<>"",ISNUMBER(SEARCH($CU15, AS15))),AND($CV15<>"",ISNUMBER(SEARCH($CV15, AS15)))),"〇","-") | CK15: =IF(OR(AND($CT15<>"",ISNUMBER(SEARCH($CT15, AV15))),AND($CU15<>"",ISNUMBER(SEARCH($CU15, AV15))),AND($CV15<>"",ISNUMBER(SEARCH($CV15, AV15)))),"〇","-") | CL15: =IF(OR(AND($CT15<>"",ISNUMBER(SEARCH($CT15, AY15))),AND($CU15<>"",ISNUMBER(SEARCH($CU15, AY15))),AND($CV15<>"",ISNUMBER(SEARCH($CV15, AY15)))),"〇","-") | CM15: =IF(OR(AND($CT15<>"",ISNUMBER(SEARCH($CT15, BB15))),AND($CU15<>"",ISNUMBER(SEARCH($CU15, BB15))),AND($CV15<>"",ISNUMBER(SEARCH($CV15, BB15)))),"〇","-") | CN15: =IF(OR(AND($CT15<>"",ISNUMBER(SEARCH($CT15, BE15))),AND($CU15<>"",ISNUMBER(SEARCH($CU15, BE15))),AND($CV15<>"",ISNUMBER(SEARCH($CV15, BE15)))),"〇","-") | CO15: =IF(OR(AND($CT15<>"",ISNUMBER(SEARCH($CT15, BH15))),AND($CU15<>"",ISNUMBER(SEARCH($CU15, BH15))),AND($CV15<>"",ISNUMBER(SEARCH($CV15, BH15)))),"〇","-") | CP15: =IF(OR(AND($CT15<>"",ISNUMBER(SEARCH($CT15, BK15))),AND($CU15<>"",ISNUMBER(SEARCH($CU15, BK15))),AND($CV15<>"",ISNUMBER(SEARCH($CV15, BK15)))),"〇","-") | CQ15: =IF(OR(AND($CT15<>"",ISNUMBER(SEARCH($CT15, BN15))),AND($CU15<>"",ISNUMBER(SEARCH($CU15, BN15))),AND($CV15<>"",ISNUMBER(SEARCH($CV15, BN15)))),"〇","-") | CR15: =IF(OR(AND($CT15<>"",ISNUMBER(SEARCH($CT15, BQ15))),AND($CU15<>"",ISNUMBER(SEARCH($CU15, BQ15))),AND($CV15<>"",ISNUMBER(SEARCH($CV15, BQ15)))),"〇","-") | CW15: =IF(OR(CI15="〇",CJ15="〇",CK15="〇",CL15="〇",CM15="〇",CN15="〇",CO15="〇",CP15="〇",CQ15="〇",CR15="〇"),"〇","") | DE15: =TEXT(U15,"yyyy/mm/dd") | DF15: =VLOOKUP(K15,社員マスタ!C:D,2,0) | DG15: f:7c38f845-69e4-4c97-b890-7c24a715e079
B16: a:1LUvO3KIgrjNGvMw6gRnBwZOrWZM2ktO1-kHzfdc2V7WGbo6qHI6iWXDVNfEh6DM8-szX0djZvTGtbMN46T9vUbamuuBtU9E9yXNF5dWtyuhP9ieTD5T32rvvBva6dnKz-f:e0621053-12fb-5c23-0389-27dd460e7c84-FB000 | C16: =ROW(A16)-3 | D16: a:1LUvO3KIgrjNGvMw6gRnBwZOrWZM2ktO1-kHzfdc2V7WGbo6qHI6iWXDVNfEh6DM8-szX0djZvTGtbMN46T9vUbamuuBtU9E9yXNF5dWtyuhP9ieTD5T32rvvBva6dnKz-f:e0621053-12fb-5c23-0389-27dd460e7c84 | E16: f:e0621053-12fb-5c23-0389-27dd460e7c84 | F16: a:1LUvO3KIgrjNGvMw6gRnBwZOrWZM2ktO1-kHzfdc2V7WGbo6qHI6iWXDVNfEh6DM8-szX0djZvTGtbMN46T9vUbamuuBtU9E9yXNF5dWtyuhP9ieTD5T32rvvBva6dnKz | G16: a:1LUvO3KIgrjNGvMw6gRnBwZOrWZM2ktO1-kHzfdc2V7WGbo6qHI6iWXDVNfEh6DM8-szX0djZvTGtbMN46T9vUbamuuBtU9E9yXNF5dWtyuhP9ieTD5T32rvvBva6dnKz-S001 | H16: 1 | I16: 3 | J16: 1 | K16: Mikiko Nakanishi (中西 美木子) | L16: DM | N16: [カテゴリ選択] | O16: 0 | P16: 0 | Q16: 1 | R16: 0 | S16: 46161.193 | T16: 46161.193 | U16: 46161.568 | V16: 46161.568 | W16: 0 | Z16: システム操作 > タレマネ | AB16: システム操作 > タレマネ | AC16: user_selected | AD16: 0 | AF16: 0 | AG16: 0 | AH16: 0 | AI16: 0 | AJ16: 0 | AL16: 0 | AM16: 0 | AN16: 0 | BT16: 0 | BU16: 0 | BZ16: 0 | CA16: 0 | CB16: 20260519T071352-20260519T182604.csv | CC16: 1 | CD16: user | CE16: 1.0.0 | CH16: =IF(OR(CG16="①", CG16="⑤"), "〇", "×") | CI16: =IF(OR(AND($CT16<>"",ISNUMBER(SEARCH($CT16, AP16))),AND($CU16<>"",ISNUMBER(SEARCH($CU16, AP16))),AND($CV16<>"",ISNUMBER(SEARCH($CV16, AP16)))),"〇","-") | CJ16: =IF(OR(AND($CT16<>"",ISNUMBER(SEARCH($CT16, AS16))),AND($CU16<>"",ISNUMBER(SEARCH($CU16, AS16))),AND($CV16<>"",ISNUMBER(SEARCH($CV16, AS16)))),"〇","-") | CK16: =IF(OR(AND($CT16<>"",ISNUMBER(SEARCH($CT16, AV16))),AND($CU16<>"",ISNUMBER(SEARCH($CU16, AV16))),AND($CV16<>"",ISNUMBER(SEARCH($CV16, AV16)))),"〇","-") | CL16: =IF(OR(AND($CT16<>"",ISNUMBER(SEARCH($CT16, AY16))),AND($CU16<>"",ISNUMBER(SEARCH($CU16, AY16))),AND($CV16<>"",ISNUMBER(SEARCH($CV16, AY16)))),"〇","-") | CM16: =IF(OR(AND($CT16<>"",ISNUMBER(SEARCH($CT16, BB16))),AND($CU16<>"",ISNUMBER(SEARCH($CU16, BB16))),AND($CV16<>"",ISNUMBER(SEARCH($CV16, BB16)))),"〇","-") | CN16: =IF(OR(AND($CT16<>"",ISNUMBER(SEARCH($CT16, BE16))),AND($CU16<>"",ISNUMBER(SEARCH($CU16, BE16))),AND($CV16<>"",ISNUMBER(SEARCH($CV16, BE16)))),"〇","-") | CO16: =IF(OR(AND($CT16<>"",ISNUMBER(SEARCH($CT16, BH16))),AND($CU16<>"",ISNUMBER(SEARCH($CU16, BH16))),AND($CV16<>"",ISNUMBER(SEARCH($CV16, BH16)))),"〇","-") | CP16: =IF(OR(AND($CT16<>"",ISNUMBER(SEARCH($CT16, BK16))),AND($CU16<>"",ISNUMBER(SEARCH($CU16, BK16))),AND($CV16<>"",ISNUMBER(SEARCH($CV16, BK16)))),"〇","-") | CQ16: =IF(OR(AND($CT16<>"",ISNUMBER(SEARCH($CT16, BN16))),AND($CU16<>"",ISNUMBER(SEARCH($CU16, BN16))),AND($CV16<>"",ISNUMBER(SEARCH($CV16, BN16)))),"〇","-") | CR16: =IF(OR(AND($CT16<>"",ISNUMBER(SEARCH($CT16, BQ16))),AND($CU16<>"",ISNUMBER(SEARCH($CU16, BQ16))),AND($CV16<>"",ISNUMBER(SEARCH($CV16, BQ16)))),"〇","-") | CW16: =IF(OR(CI16="〇",CJ16="〇",CK16="〇",CL16="〇",CM16="〇",CN16="〇",CO16="〇",CP16="〇",CQ16="〇",CR16="〇"),"〇","") | DE16: =TEXT(U16,"yyyy/mm/dd") | DF16: =VLOOKUP(K16,社員マスタ!C:D,2,0) | DG16: f:e0621053-12fb-5c23-0389-27dd460e7c84
B17: a:1LUvO3KIgrjNGvMw6gRnBwZOrWZM2ktO1-kHzfdc2V7WGbo6qHI6iWXDVNfEh6DM8-szX0djZvTGtbMN46T9vUbamuuBtU9E9yXNF5dWtyuhP9ieTD5T32rvvBva6dnKz-f:f03e30d5-7406-91ed-7b2f-5599b01b1d9a-FB000 | C17: =ROW(A17)-3 | D17: a:1LUvO3KIgrjNGvMw6gRnBwZOrWZM2ktO1-kHzfdc2V7WGbo6qHI6iWXDVNfEh6DM8-szX0djZvTGtbMN46T9vUbamuuBtU9E9yXNF5dWtyuhP9ieTD5T32rvvBva6dnKz-f:f03e30d5-7406-91ed-7b2f-5599b01b1d9a | E17: f:f03e30d5-7406-91ed-7b2f-5599b01b1d9a | F17: a:1LUvO3KIgrjNGvMw6gRnBwZOrWZM2ktO1-kHzfdc2V7WGbo6qHI6iWXDVNfEh6DM8-szX0djZvTGtbMN46T9vUbamuuBtU9E9yXNF5dWtyuhP9ieTD5T32rvvBva6dnKz | G17: a:1LUvO3KIgrjNGvMw6gRnBwZOrWZM2ktO1-kHzfdc2V7WGbo6qHI6iWXDVNfEh6DM8-szX0djZvTGtbMN46T9vUbamuuBtU9E9yXNF5dWtyuhP9ieTD5T32rvvBva6dnKz-S001 | H17: 1 | I17: 4 | J17: 1 | K17: Mikiko Nakanishi (中西 美木子) | L17: DM | N17: [カテゴリ選択] | O17: 0 | P17: 0 | Q17: 1 | R17: 0 | S17: 46161.193 | T17: 46161.193 | U17: 46161.568 | V17: 46161.568 | W17: 0 | Z17: タレマネ > 社員用 | AB17: タレマネ > 社員用 | AC17: user_selected | AD17: 0 | AF17: 0 | AG17: 0 | AH17: 0 | AI17: 0 | AJ17: 0 | AL17: 0 | AM17: 0 | AN17: 0 | BT17: 0 | BU17: 0 | BZ17: 0 | CA17: 0 | CB17: 20260519T071352-20260519T182604.csv | CC17: 1 | CD17: user | CE17: 1.0.0 | CH17: =IF(OR(CG17="①", CG17="⑤"), "〇", "×") | CI17: =IF(OR(AND($CT17<>"",ISNUMBER(SEARCH($CT17, AP17))),AND($CU17<>"",ISNUMBER(SEARCH($CU17, AP17))),AND($CV17<>"",ISNUMBER(SEARCH($CV17, AP17)))),"〇","-") | CJ17: =IF(OR(AND($CT17<>"",ISNUMBER(SEARCH($CT17, AS17))),AND($CU17<>"",ISNUMBER(SEARCH($CU17, AS17))),AND($CV17<>"",ISNUMBER(SEARCH($CV17, AS17)))),"〇","-") | CK17: =IF(OR(AND($CT17<>"",ISNUMBER(SEARCH($CT17, AV17))),AND($CU17<>"",ISNUMBER(SEARCH($CU17, AV17))),AND($CV17<>"",ISNUMBER(SEARCH($CV17, AV17)))),"〇","-") | CL17: =IF(OR(AND($CT17<>"",ISNUMBER(SEARCH($CT17, AY17))),AND($CU17<>"",ISNUMBER(SEARCH($CU17, AY17))),AND($CV17<>"",ISNUMBER(SEARCH($CV17, AY17)))),"〇","-") | CM17: =IF(OR(AND($CT17<>"",ISNUMBER(SEARCH($CT17, BB17))),AND($CU17<>"",ISNUMBER(SEARCH($CU17, BB17))),AND($CV17<>"",ISNUMBER(SEARCH($CV17, BB17)))),"〇","-") | CN17: =IF(OR(AND($CT17<>"",ISNUMBER(SEARCH($CT17, BE17))),AND($CU17<>"",ISNUMBER(SEARCH($CU17, BE17))),AND($CV17<>"",ISNUMBER(SEARCH($CV17, BE17)))),"〇","-") | CO17: =IF(OR(AND($CT17<>"",ISNUMBER(SEARCH($CT17, BH17))),AND($CU17<>"",ISNUMBER(SEARCH($CU17, BH17))),AND($CV17<>"",ISNUMBER(SEARCH($CV17, BH17)))),"〇","-") | CP17: =IF(OR(AND($CT17<>"",ISNUMBER(SEARCH($CT17, BK17))),AND($CU17<>"",ISNUMBER(SEARCH($CU17, BK17))),AND($CV17<>"",ISNUMBER(SEARCH($CV17, BK17)))),"〇","-") | CQ17: =IF(OR(AND($CT17<>"",ISNUMBER(SEARCH($CT17, BN17))),AND($CU17<>"",ISNUMBER(SEARCH($CU17, BN17))),AND($CV17<>"",ISNUMBER(SEARCH($CV17, BN17)))),"〇","-") | CR17: =IF(OR(AND($CT17<>"",ISNUMBER(SEARCH($CT17, BQ17))),AND($CU17<>"",ISNUMBER(SEARCH($CU17, BQ17))),AND($CV17<>"",ISNUMBER(SEARCH($CV17, BQ17)))),"〇","-") | CW17: =IF(OR(CI17="〇",CJ17="〇",CK17="〇",CL17="〇",CM17="〇",CN17="〇",CO17="〇",CP17="〇",CQ17="〇",CR17="〇"),"〇","") | DE17: =TEXT(U17,"yyyy/mm/dd") | DF17: =VLOOKUP(K17,社員マスタ!C:D,2,0) | DG17: f:f03e30d5-7406-91ed-7b2f-5599b01b1d9a
B18: a:1LUvO3KIgrjNGvMw6gRnBwZOrWZM2ktO1-kHzfdc2V7WGbo6qHI6iWXDVNfEh6DM8-szX0djZvTGtbMN46T9vUbamuuBtU9E9yXNF5dWtyuhP9ieTD5T32rvvBva6dnKz-1779165491050-FB000 | C18: =ROW(A18)-3 | D18: a:1LUvO3KIgrjNGvMw6gRnBwZOrWZM2ktO1-kHzfdc2V7WGbo6qHI6iWXDVNfEh6DM8-szX0djZvTGtbMN46T9vUbamuuBtU9E9yXNF5dWtyuhP9ieTD5T32rvvBva6dnKz-1779165491050 | E18: 1779165491050 | F18: a:1LUvO3KIgrjNGvMw6gRnBwZOrWZM2ktO1-kHzfdc2V7WGbo6qHI6iWXDVNfEh6DM8-szX0djZvTGtbMN46T9vUbamuuBtU9E9yXNF5dWtyuhP9ieTD5T32rvvBva6dnKz | G18: a:1LUvO3KIgrjNGvMw6gRnBwZOrWZM2ktO1-kHzfdc2V7WGbo6qHI6iWXDVNfEh6DM8-szX0djZvTGtbMN46T9vUbamuuBtU9E9yXNF5dWtyuhP9ieTD5T32rvvBva6dnKz-S001 | H18: 1 | I18: 5 | J18: 1 | K18: Mikiko Nakanishi (中西 美木子) | L18: DM | M18: ５月で異動になったのですが、専門分野（従事）が、前部署のまま変更できません。どうしたらいいですか | N18: ５月で異動になったのですが、専門分野（従事）が、前部署のまま変更できません。どうしたらいいですか | O18: 1 | P18: 0 | Q18: 0 | R18: 0 | S18: 46161.193 | T18: 46161.193 | U18: 46161.568 | V18: 46161.568 | W18: 6.234 | X18: searchEmployeeRules | AB18: 未分類 | AC18: none | AD18: 1 | AE18: 人事異動後に専門分野（従事）が前部署のまま変更できない場合、以下の対応が必要です。 - 上長が承認しても反映されない場合は、システムのヘルプページ（https://www.hdservice1.nttls.co.jp/hc/ja/articles/22094766203415）を確認してください。 - 異動や上長の変更があった場合、社員本人がタレマネのプロファイルから上長を変更し、再申請する必要があります。新しい上長が承認すると、専門分野の情報が更新されます。 上記の手順で処理を進めてください。 ※AIの回答は必ずしも正確ではありません。参照情報も確認いただき、最終判断は所属部署の公式情報をご確認ください。 | AF18: 1 | AG18: 0 | AH18: 2 | AI18: 0 | AJ18: 0 | AL18: 4 | AM18: 4 | AN18: 0 | AO18: QA616_system_talemane_talemane-employee.md | AP18: 質問 人事情報の「専門分野項目」について、上長が承認をしても反映されない場合、どうしたらいいでしょうか。 回答 人事情報の「専門分野項目」について、上長が承認をしても反映されない場合は以下URLをご確認ください。 https://www.hdservice1.nttls.co.jp/hc/ja/articles/22094766203415 | AQ18: 0.9418352 | AR18: QA617_system_talemane_talemane-employee.md | AS18: 質問 上長が社員のポジションを割り当てることができない場合、どうしたらいいでしょうか。 回答 上長が社員のポジションを割り当てることができない場合は以下URLをご確認ください。 https://www.hdservice1.nttls.co.jp/hc/ja/articles/25013787582487 | AT18: 0.9323526 | AU18: 【社員用】タレントマネジメントサ-ビスマニュアル.pdf | AV18: 第３９章 資格情報管理 人担 育担 上長 社員 ● ● ● ２．「承認待ちの申請」画面が開きます。 （１）「承認待ちの申請（部下からあなたへの申請）」欄、「承認待ちの申請（あなたから上長への申 請）」欄をそれぞれ確認し、「差し戻し日」の記載があることを確認します。（下図の通り、「差し戻 し」１レコードにつき、左右の欄両方に同じレコードが表示されます） （２）「[氏名]の資格情報（[氏名コード]）の変更」を押下します。 ３．「ワークフローの詳細」画面が開きます。 （１）上長からのコメント等を参考に、「差し戻し」の理由を確認します。 －221－ © 2022 NTT BUSINESS ASSOCIE | AW18: 0.9418352 | AX18: 【社員用】タレントマネジメントサ-ビスマニュアル.pdf | AY18: 第３９章 資格情報管理 人担 育担 上長 社員 ● ● ● ● 異動等で上長が変更になる場合 社員本人の異動・出向・転籍または上長の異動・出向・転籍・休職・退職により上長が変更に なる場合、上長へ申請中の承認ワークフローは自動では新上長へ移行されないため、 社員本人がタレマネのプロファイルから上長を変更後、再申請する必要があります。 上長が変更になる発令パターンと資格申請プロセス別の対応 資格申請プロセス 発令 パターン 資格申請前 上長へ資格申請中 上長の資格承認後 ①異動 ②出向 ③転籍 ④休職・ (cid:2896)職 ・社員の異動 ・上長の異動 ・社員の異動 ・上長の異動 ・社員の異動 ・上長の異動 ・上長の休職、 (cid:2896)職 ・社員本人が上長変更 した上で、 取得資格情報 登(cid:2952)申請 ・新上長が承認 ・社員本人が上長変更 した上で、 取得資格情報登(cid:2952) 再申請 ・新上長が承認 ・社員本人が上長変更 （次回以降の 申請は、 新上長が承認） （上長設定の変更方法については、「第９章 上長設定」参照） これで処理は完了です －210－ © 2022 NTT BUSINESS ASSOCIE | AZ18: 0.9204085 | BT18: 0 | BU18: 0 | BZ18: 0 | CA18: 0 | CB18: 20260519T071352-20260519T182604.csv | CC18: 4 | CD18: user > assistant > tool > assistant | CE18: 1.0.0 | CH18: =IF(OR(CG18="①", CG18="⑤"), "〇", "×") | CI18: =IF(OR(AND($CT18<>"",ISNUMBER(SEARCH($CT18, AP18))),AND($CU18<>"",ISNUMBER(SEARCH($CU18, AP18))),AND($CV18<>"",ISNUMBER(SEARCH($CV18, AP18)))),"〇","-") | CJ18: =IF(OR(AND($CT18<>"",ISNUMBER(SEARCH($CT18, AS18))),AND($CU18<>"",ISNUMBER(SEARCH($CU18, AS18))),AND($CV18<>"",ISNUMBER(SEARCH($CV18, AS18)))),"〇","-") | CK18: =IF(OR(AND($CT18<>"",ISNUMBER(SEARCH($CT18, AV18))),AND($CU18<>"",ISNUMBER(SEARCH($CU18, AV18))),AND($CV18<>"",ISNUMBER(SEARCH($CV18, AV18)))),"〇","-") | CL18: =IF(OR(AND($CT18<>"",ISNUMBER(SEARCH($CT18, AY18))),AND($CU18<>"",ISNUMBER(SEARCH($CU18, AY18))),AND($CV18<>"",ISNUMBER(SEARCH($CV18, AY18)))),"〇","-") | CM18: =IF(OR(AND($CT18<>"",ISNUMBER(SEARCH($CT18, BB18))),AND($CU18<>"",ISNUMBER(SEARCH($CU18, BB18))),AND($CV18<>"",ISNUMBER(SEARCH($CV18, BB18)))),"〇","-") | CN18: =IF(OR(AND($CT18<>"",ISNUMBER(SEARCH($CT18, BE18))),AND($CU18<>"",ISNUMBER(SEARCH($CU18, BE18))),AND($CV18<>"",ISNUMBER(SEARCH($CV18, BE18)))),"〇","-") | CO18: =IF(OR(AND($CT18<>"",ISNUMBER(SEARCH($CT18, BH18))),AND($CU18<>"",ISNUMBER(SEARCH($CU18, BH18))),AND($CV18<>"",ISNUMBER(SEARCH($CV18, BH18)))),"〇","-") | CP18: =IF(OR(AND($CT18<>"",ISNUMBER(SEARCH($CT18, BK18))),AND($CU18<>"",ISNUMBER(SEARCH($CU18, BK18))),AND($CV18<>"",ISNUMBER(SEARCH($CV18, BK18)))),"〇","-") | CQ18: =IF(OR(AND($CT18<>"",ISNUMBER(SEARCH($CT18, BN18))),AND($CU18<>"",ISNUMBER(SEARCH($CU18, BN18))),AND($CV18<>"",ISNUMBER(SEARCH($CV18, BN18)))),"〇","-") | CR18: =IF(OR(AND($CT18<>"",ISNUMBER(SEARCH($CT18, BQ18))),AND($CU18<>"",ISNUMBER(SEARCH($CU18, BQ18))),AND($CV18<>"",ISNUMBER(SEARCH($CV18, BQ18)))),"〇","-") | CW18: =IF(OR(CI18="〇",CJ18="〇",CK18="〇",CL18="〇",CM18="〇",CN18="〇",CO18="〇",CP18="〇",CQ18="〇",CR18="〇"),"〇","") | DE18: =TEXT(U18,"yyyy/mm/dd") | DF18: =VLOOKUP(K18,社員マスタ!C:D,2,0) | DG18: 1779165491050
B19: a:1LUvO3KIgrjNGvMw6gRnBwZOrWZM2ktO1-kHzfdc2V7WGbo6qHI6iWXDVNfEh6DM8-szX0djZvTGtbMN46T9vUbamuuBtU9E9yXNF5dWtyuhP9ieTD5T32rvvBva6dnKz-1779167559015-FB000 | C19: =ROW(A19)-3 | D19: a:1LUvO3KIgrjNGvMw6gRnBwZOrWZM2ktO1-kHzfdc2V7WGbo6qHI6iWXDVNfEh6DM8-szX0djZvTGtbMN46T9vUbamuuBtU9E9yXNF5dWtyuhP9ieTD5T32rvvBva6dnKz-1779167559015 | E19: 1779167559015 | F19: a:1LUvO3KIgrjNGvMw6gRnBwZOrWZM2ktO1-kHzfdc2V7WGbo6qHI6iWXDVNfEh6DM8-szX0djZvTGtbMN46T9vUbamuuBtU9E9yXNF5dWtyuhP9ieTD5T32rvvBva6dnKz | G19: a:1LUvO3KIgrjNGvMw6gRnBwZOrWZM2ktO1-kHzfdc2V7WGbo6qHI6iWXDVNfEh6DM8-szX0djZvTGtbMN46T9vUbamuuBtU9E9yXNF5dWtyuhP9ieTD5T32rvvBva6dnKz-S001 | H19: 1 | I19: 6 | J19: 1 | K19: Mikiko Nakanishi (中西 美木子) | L19: DM | M19: 一次評価者と二次評価者が前の部署のままなのですが、これはどこから変更できますか | N19: 一次評価者と二次評価者が前の部署のままなのですが、これはどこから変更できますか | O19: 1 | P19: 0 | Q19: 0 | R19: 0 | S19: 46161.217 | T19: 46161.217 | U19: 46161.592 | V19: 46161.592 | W19: 5.855 | X19: searchEmployeeRules | AB19: 未分類 | AC19: none | AD19: 1 | AE19: 一次評価者が前の部署のままになっている場合、プロファイル画面から上長設定を行って新しい上長に変更しても、一次評価者が古い情報のままになることがあります。 このような場合の対応方法については、以下のURLで詳細が案内されていますので、ご確認ください。 https://www.hdservice1.nttls.co.jp/hc/ja/articles/17842855242519 ※AIの回答は必ずしも正確ではありません。参照情報も確認いただき、最終判断は所属部署の公式情報をご確認ください。 | AF19: 1 | AG19: 0 | AH19: 2 | AI19: 0 | AJ19: 0 | AL19: 4 | AM19: 4 | AN19: 0 | AO19: QA614_system_talemane_talemane-employee.md | AP19: 質問 プロファイル画面から上長設定を行って新上長に変更したが、「一次評価者」が異なったまま(古い情報のまま)となっている場合、どうしたらいいでしょうか。 回答 「一次評価者」が異なったまま(古い情報のまま)となっている場合は以下URLをご確認ください。 https://www.hdservice1.nttls.co.jp/hc/ja/articles/17842855242519 | AQ19: 0.93575907 | AR19: QA609_system_talemane_talemane-employee.md | AS19: 質問 目標設定・評価フォームを「システムステップ」まで進めてしまい動かせなくなった場合、どうしたらいいでしょうか。 回答 目標設定・評価フォームを「システムステップ」まで進めてしまい動かせなくなった場合は以下URLをご確認ください。 https://www.hdservice1.nttls.co.jp/hc/ja/articles/19052461933335 | AT19: 0.9161744 | AU19: QA619_system_talemane_talemane-employee.md | AV19: 質問 目標設定・評価フォームが「ロック」され上長側で記入できない場合、どうしたらいいでしょうか。 回答 目標設定・評価フォームが「ロック」され上長側で記入できない場合は以下URLをご確認ください。 https://www.hdservice1.nttls.co.jp/hc/ja/articles/18295484365591 | AW19: 0.93575907 | AX19: QA604_system_talemane_talemane-employee.md | AY19: 質問 目標設定・評価フォームを既に上長へ送ったのに「署名」を求められる場合、どうしたらいいでしょうか。 回答 目標設定・評価フォームを上長へ送ったのに「署名」を求められる場合は以下URLをご確認ください。 https://www.hdservice1.nttls.co.jp/hc/ja/articles/18241101016983 | AZ19: 0.9132409 | BT19: 0 | BU19: 0 | BZ19: 0 | CA19: 0 | CB19: 20260519T071352-20260519T182604.csv | CC19: 4 | CD19: user > assistant > tool > assistant | CE19: 1.0.0 | CH19: =IF(OR(CG19="①", CG19="⑤"), "〇", "×") | CI19: =IF(OR(AND($CT19<>"",ISNUMBER(SEARCH($CT19, AP19))),AND($CU19<>"",ISNUMBER(SEARCH($CU19, AP19))),AND($CV19<>"",ISNUMBER(SEARCH($CV19, AP19)))),"〇","-") | CJ19: =IF(OR(AND($CT19<>"",ISNUMBER(SEARCH($CT19, AS19))),AND($CU19<>"",ISNUMBER(SEARCH($CU19, AS19))),AND($CV19<>"",ISNUMBER(SEARCH($CV19, AS19)))),"〇","-") | CK19: =IF(OR(AND($CT19<>"",ISNUMBER(SEARCH($CT19, AV19))),AND($CU19<>"",ISNUMBER(SEARCH($CU19, AV19))),AND($CV19<>"",ISNUMBER(SEARCH($CV19, AV19)))),"〇","-") | CL19: =IF(OR(AND($CT19<>"",ISNUMBER(SEARCH($CT19, AY19))),AND($CU19<>"",ISNUMBER(SEARCH($CU19, AY19))),AND($CV19<>"",ISNUMBER(SEARCH($CV19, AY19)))),"〇","-") | CM19: =IF(OR(AND($CT19<>"",ISNUMBER(SEARCH($CT19, BB19))),AND($CU19<>"",ISNUMBER(SEARCH($CU19, BB19))),AND($CV19<>"",ISNUMBER(SEARCH($CV19, BB19)))),"〇","-") | CN19: =IF(OR(AND($CT19<>"",ISNUMBER(SEARCH($CT19, BE19))),AND($CU19<>"",ISNUMBER(SEARCH($CU19, BE19))),AND($CV19<>"",ISNUMBER(SEARCH($CV19, BE19)))),"〇","-") | CO19: =IF(OR(AND($CT19<>"",ISNUMBER(SEARCH($CT19, BH19))),AND($CU19<>"",ISNUMBER(SEARCH($CU19, BH19))),AND($CV19<>"",ISNUMBER(SEARCH($CV19, BH19)))),"〇","-") | CP19: =IF(OR(AND($CT19<>"",ISNUMBER(SEARCH($CT19, BK19))),AND($CU19<>"",ISNUMBER(SEARCH($CU19, BK19))),AND($CV19<>"",ISNUMBER(SEARCH($CV19, BK19)))),"〇","-") | CQ19: =IF(OR(AND($CT19<>"",ISNUMBER(SEARCH($CT19, BN19))),AND($CU19<>"",ISNUMBER(SEARCH($CU19, BN19))),AND($CV19<>"",ISNUMBER(SEARCH($CV19, BN19)))),"〇","-") | CR19: =IF(OR(AND($CT19<>"",ISNUMBER(SEARCH($CT19, BQ19))),AND($CU19<>"",ISNUMBER(SEARCH($CU19, BQ19))),AND($CV19<>"",ISNUMBER(SEARCH($CV19, BQ19)))),"〇","-") | CW19: =IF(OR(CI19="〇",CJ19="〇",CK19="〇",CL19="〇",CM19="〇",CN19="〇",CO19="〇",CP19="〇",CQ19="〇",CR19="〇"),"〇","") | DE19: =TEXT(U19,"yyyy/mm/dd") | DF19: =VLOOKUP(K19,社員マスタ!C:D,2,0) | DG19: 1779167559015
B20: a:1LUvO3KIgrjNGvMw6gRnBwZOrWZM2ktO1-kHzfdc2V7WGbo6qHI6iWXDVNfEh6DM8-szX0djZvTGtbMN46T9vUbamuuBtU9E9yXNF5dWtyuhP9ieTD5T32rvvBva6dnKz-1779167667732-FB000 | C20: =ROW(A20)-3 | D20: a:1LUvO3KIgrjNGvMw6gRnBwZOrWZM2ktO1-kHzfdc2V7WGbo6qHI6iWXDVNfEh6DM8-szX0djZvTGtbMN46T9vUbamuuBtU9E9yXNF5dWtyuhP9ieTD5T32rvvBva6dnKz-1779167667732 | E20: 1779167667732 | F20: a:1LUvO3KIgrjNGvMw6gRnBwZOrWZM2ktO1-kHzfdc2V7WGbo6qHI6iWXDVNfEh6DM8-szX0djZvTGtbMN46T9vUbamuuBtU9E9yXNF5dWtyuhP9ieTD5T32rvvBva6dnKz | G20: a:1LUvO3KIgrjNGvMw6gRnBwZOrWZM2ktO1-kHzfdc2V7WGbo6qHI6iWXDVNfEh6DM8-szX0djZvTGtbMN46T9vUbamuuBtU9E9yXNF5dWtyuhP9ieTD5T32rvvBva6dnKz-S001 | H20: 1 | I20: 7 | J20: 1 | K20: Mikiko Nakanishi (中西 美木子) | L20: DM | M20: リンクが開けないので、マニュアルのありかを教えて | N20: リンクが開けないので、マニュアルのありかを教えて | O20: 1 | P20: 0 | Q20: 0 | R20: 0 | S20: 46161.218 | T20: 46161.218 | U20: 46161.593 | V20: 46161.593 | W20: 2.384 | AB20: 未分類 | AC20: none | AD20: 1 | AE20: 申し訳ありませんが、マニュアルの所在についてはご案内できません。 一次評価者・二次評価者の変更は、プロファイル画面の上長設定から行うのが基本です。変更後に反映されない場合は、システムの反映タイミングや手続きの詳細が関係している可能性があります。 具体的な操作や対応については、社内の担当部署にお問い合わせいただくのが確実です。 ※AIの回答は必ずしも正確ではありません。参照情報も確認いただき、最終判断は所属部署の公式情報をご確認ください。 | AF20: 1 | AG20: 0 | AH20: 1 | AI20: 0 | AJ20: 0 | AL20: 0 | AM20: 0 | AN20: 0 | BT20: 0 | BU20: 0 | BZ20: 0 | CA20: 0 | CB20: 20260519T071352-20260519T182604.csv | CC20: 2 | CD20: user > assistant | CE20: 1.0.0 | CH20: =IF(OR(CG20="①", CG20="⑤"), "〇", "×") | CI20: =IF(OR(AND($CT20<>"",ISNUMBER(SEARCH($CT20, AP20))),AND($CU20<>"",ISNUMBER(SEARCH($CU20, AP20))),AND($CV20<>"",ISNUMBER(SEARCH($CV20, AP20)))),"〇","-") | CJ20: =IF(OR(AND($CT20<>"",ISNUMBER(SEARCH($CT20, AS20))),AND($CU20<>"",ISNUMBER(SEARCH($CU20, AS20))),AND($CV20<>"",ISNUMBER(SEARCH($CV20, AS20)))),"〇","-") | CK20: =IF(OR(AND($CT20<>"",ISNUMBER(SEARCH($CT20, AV20))),AND($CU20<>"",ISNUMBER(SEARCH($CU20, AV20))),AND($CV20<>"",ISNUMBER(SEARCH($CV20, AV20)))),"〇","-") | CL20: =IF(OR(AND($CT20<>"",ISNUMBER(SEARCH($CT20, AY20))),AND($CU20<>"",ISNUMBER(SEARCH($CU20, AY20))),AND($CV20<>"",ISNUMBER(SEARCH($CV20, AY20)))),"〇","-") | CM20: =IF(OR(AND($CT20<>"",ISNUMBER(SEARCH($CT20, BB20))),AND($CU20<>"",ISNUMBER(SEARCH($CU20, BB20))),AND($CV20<>"",ISNUMBER(SEARCH($CV20, BB20)))),"〇","-") | CN20: =IF(OR(AND($CT20<>"",ISNUMBER(SEARCH($CT20, BE20))),AND($CU20<>"",ISNUMBER(SEARCH($CU20, BE20))),AND($CV20<>"",ISNUMBER(SEARCH($CV20, BE20)))),"〇","-") | CO20: =IF(OR(AND($CT20<>"",ISNUMBER(SEARCH($CT20, BH20))),AND($CU20<>"",ISNUMBER(SEARCH($CU20, BH20))),AND($CV20<>"",ISNUMBER(SEARCH($CV20, BH20)))),"〇","-") | CP20: =IF(OR(AND($CT20<>"",ISNUMBER(SEARCH($CT20, BK20))),AND($CU20<>"",ISNUMBER(SEARCH($CU20, BK20))),AND($CV20<>"",ISNUMBER(SEARCH($CV20, BK20)))),"〇","-") | CQ20: =IF(OR(AND($CT20<>"",ISNUMBER(SEARCH($CT20, BN20))),AND($CU20<>"",ISNUMBER(SEARCH($CU20, BN20))),AND($CV20<>"",ISNUMBER(SEARCH($CV20, BN20)))),"〇","-") | CR20: =IF(OR(AND($CT20<>"",ISNUMBER(SEARCH($CT20, BQ20))),AND($CU20<>"",ISNUMBER(SEARCH($CU20, BQ20))),AND($CV20<>"",ISNUMBER(SEARCH($CV20, BQ20)))),"〇","-") | CW20: =IF(OR(CI20="〇",CJ20="〇",CK20="〇",CL20="〇",CM20="〇",CN20="〇",CO20="〇",CP20="〇",CQ20="〇",CR20="〇"),"〇","") | DE20: =TEXT(U20,"yyyy/mm/dd") | DF20: =VLOOKUP(K20,社員マスタ!C:D,2,0) | DG20: 1779167667732
B21: a:1mBfYBf2GWtshkRp331PkSCPvzsuL7oXR-LloIbNS1_b8r7PdcvBzpJFV1qXDZsrsI8CDBB4Koqvkz8yYF_jZhErR_XVPJav2vS4Osqli0h85OcdlYbTsjeOULBj3rBT6-1779169282860-FB000 | C21: =ROW(A21)-3 | D21: a:1mBfYBf2GWtshkRp331PkSCPvzsuL7oXR-LloIbNS1_b8r7PdcvBzpJFV1qXDZsrsI8CDBB4Koqvkz8yYF_jZhErR_XVPJav2vS4Osqli0h85OcdlYbTsjeOULBj3rBT6-1779169282860 | E21: 1779169282860 | F21: a:1mBfYBf2GWtshkRp331PkSCPvzsuL7oXR-LloIbNS1_b8r7PdcvBzpJFV1qXDZsrsI8CDBB4Koqvkz8yYF_jZhErR_XVPJav2vS4Osqli0h85OcdlYbTsjeOULBj3rBT6 | G21: a:1mBfYBf2GWtshkRp331PkSCPvzsuL7oXR-LloIbNS1_b8r7PdcvBzpJFV1qXDZsrsI8CDBB4Koqvkz8yYF_jZhErR_XVPJav2vS4Osqli0h85OcdlYbTsjeOULBj3rBT6-S001 | H21: 1 | I21: 1 | J21: 1 | K21: Wakaba Yoshida (吉田 若葉) | L21: DM | M21: 総括責任者って誰 | N21: 総括責任者って誰 | O21: 1 | P21: 0 | Q21: 0 | R21: 0 | S21: 46161.237 | T21: 46161.237 | U21: 46161.612 | V21: 46161.612 | W21: 5.775 | X21: searchEmployeeRules | Y21: 服務 > 社員 | AA21: 服務 | AB21: 服務 > 社員 | AC21: predicted | AD21: 0 | AE21: 総括責任者については、社員や各職位の所属長（組織の長）を指す場合が多いです。所属長は「社員の任命に関する責任規程」に基づき任命責任を有する者とされています。 また、組織の長についての所属長は、その組織の長の直近の上位の組織の長となります。つまり、総括責任者は組織ごとに異なり、該当する組織の長やその上位の長が総括責任者となるケースが一般的です。 具体的な人物名は組織や部署によって異なりますので、該当する組織の長やその上位の長が総括責任者となります。 ※AIの回答は必ずしも正確ではありません。参照情報も確認いただき、最終判断は所属部署の公式情報をご確認ください。 | AF21: 1 | AG21: 0 | AH21: 3 | AI21: 0 | AJ21: 0 | AL21: 4 | AM21: 4 | AN21: 0 | AO21: 06 社員就業規則における所属長の範囲に関する規程_202507.docx | AP21: （社員等についての所属長の範囲） 第２条 組織の長を除く社員等（社員、キャリアS、キャリアⅠ、キャリアⅡ、キャリアⅢ、エキスパートⅠ、エキスパートⅡ及びアドバンスト・プロフェッショナルをいう。以下同じ。）についての所属長の範囲は別表１ないし６のとおりとする。 また、社員就業規則第４章及びアドバンスト・プロフェッショナル就業規則第６条におけるにおける所属長は任命責任者（「社員の任命に関する責任規程」（1992年7月1日社長達第19号）に基づき任命責任を有するものをいう。）とする。 | AQ21: 0.90227833 | AR21: 06 社員就業規則における所属長の範囲に関する規程_202507.docx | AS21: なお、キャリアS就業規則第３章第６節、キャリアⅠ就業規則第３章第６節、キャリアⅡ就業規則第３章第６節、キャリアⅢ就業規則第３章第４節、エキスパートⅠ就業規則第３章第４節及びエキスパートⅡ就業規則第３章第４節における所属長は雇用責任者（キャリアS、キャリアⅠ、キャリアⅡ、キャリアⅢ、エキスパートⅠ及びエキスパートⅡを雇用する組織の長）とする。 （直属上長の職務を行う者の指定） 第３条 組織の長は、必要と認めるときは、課に属さない所属社員については、直属上長の職務を行う者（管理職職位にある者並びに担当課長に限る。）を別に定めることができる。 （直属上長のもとを離れて工事等に従事する社員等の特例） 第４条 直属上長のもとを離れて工事等に従事する社員については、直属上長が自らその職務を行うことが困難な場合に限り、当該工事等の責任者で、直属上長が指定した者が直属上長の職務を代わって行うことができるものとする。 （直属上長に事故があるとき等の措置） 第５条 直属上長に事故があるとき、又は、不在のときは、その直近の上長が当該直属上長の職務を行うものとし、直近の上長に事故があるとき又は不在のときは、順次その直近の上長が当該直属上長の職務を行うものとする。 2 組織の長が直属上長である場合、又は前項の規定により直属上長の職務を行う者が組織の長である場合において当該組織の長に事故があるとき、又は不在のときは、当該組織の次席の社員（次席の社員に事故があるとき、又は不在のときは順次その次席の社員。ただし、管理職職位にある者並びに担当課長、又は、別に定める者に限る。）が直属上長の職務を行うものとする。 （組織の長の職務を行う者の指定） 組織の長は、必要と認めるときは、組織の長の職務を行う者（直属上長より上位にある 者に限る。）を別に定めることができる。 （組織の長に事故があるとき等の措置） 第７条 組織の長に事故があるとき、又は不在のときは、当該組織の次席の社員（管理職職位にある者並びに担当課長、又は別に定める者に限る。）が当該組織の長の職務を行うものとする。 （組織の長についての所属長） 第８条 組織の長についての所属長は、その組織の長の直近の上位の組織の長とする。 付 則 この改正は、2003年４月１日から実施する。 | AT21: 0.90421505 | AU21: 06 社員就業規則における所属長の範囲に関する規程_202507.docx | AV21: 別表１ 社員就業規則における所属長の範囲 条 項 事 項 所属長の範囲 第４条 第６条第２項 第10条 第11条 第13条 第14条 第17条 第22条 第25条 第28条第３項 第29条 第33条 第34条 第35条 第36条 第40条 第43条、第54条 第44条、第54条 第44条第10号 第45条、第54条 第45条第３項 第47条、第54条 第48条、第54条 第51条、第54条 第52条、第54条 第53条 第55条 第55条の２ 第56条 第142条第２項 所属長の命令及び所属長の任務 勤務時間中の組合活動の承認 他の業務への関与の許可 公職選挙の立候補届出及び就任の届出 遅刻、早退又は欠勤の届出及び承認 居住地の届出 赴任の遅延の承認 時間外及び休日勤務の命令 勤務割の指定 日直及び宿直の当直時間の設定 所属長のもとを離れて勤務する場合の勤務時間 リモートワークの承認 休日の設定 休日の変更 所属長のもとを離れて勤務する場合の休日 年次休暇の時季変更 ライフプラン休暇の承認 特別休暇の承認 勤務能率の発揮又は増進のための行事の計画・実施 病気休暇の承認 医師の指定 公傷休暇の承認 通勤災害休暇の承認 組合休暇の承認 市町村の議会の議員等の休暇の承認 不妊治療サポート休暇の承認 子の養育又は介護を行う者の時間外勤務の免除の申出 子の養育又は介護を行う者の時間外勤務の制限の申出 子の養育又は介護を行う者の深夜業の制限の申出 健康診断の日時及び場所の指定 別表２ キャリアS就業規則における所属長の範囲 | AW21: 0.90227833 | AX21: 01 社員就業規則等_202512.docx | AY21: ６ 社員は、会社の物品又は財産を不当に棄却し、亡失し、き損し、又は私用に供してはならない。 ７ 社員は、会社施設内において、演説、集会、貼紙、掲示、ビラの配布その他これに類する行為をしようとするときは、事前にその会社施設の管理責任者の許可を受けなければならない。 ８ 社員は、会社施設内において、選挙運動その他の政治活動をしてはならない。 ９ 前各号のほか、社員は、会社施設内において、風紀秩序を乱すような言動をしてはならない。 組合活動 第 ６ 条 社員は、次の各号の一に該当する場合を除き、勤務時間（休憩時間を除く。）中に組合活動をしてはならない。 (1) 団体交渉及び労使で構成する協議会等に委員又は説明員として出席するとき (2) 苦情処理機関の委員として苦情処理を行うとき (3) 労働組合の役員があっせん、調停及び仲裁手続の当事者として、これらの手続に参加するとき ２ 前項各号に定める組合活動のための勤務しない日又は時間については、そのつど所属長の承認を受けなければならない。 職務上の秘密及び個人情報を守る義務 第 ７ 条 社員は、通信の秘密及びその他の職務上知ることができた秘密を漏らしてはならない。 ２ 社員は、職務上知ることができた個人情報（個人番号及び特定個人情報を含む。）を正当な理由なく使用し又は漏らしてはならない。 ３ 前１項及び２項は、その職を退いた後においても同様とする。 信用失墜行為の禁止 第 ８ 条 社員は、会社の信用を傷つけ、又は従業員全体の不名誉となるような行為をしてはならない。 金品、利益の受領の禁止 第 ９ 条 社員は、職務に関して、部内部外を問わず他人から報酬その他名義のいかんにかかわらず、みだりに金銭又は物品の寄贈を受け、又はその他の利益を受けてはならない。 他の業務の関与制限 第 10 条 社員は、その職務のほかに、報酬を得て他の業務に従事し、又は営利企業を営もうとするときは、事前に所属長の許可を受けなければならない。 第 11 条 社員は、国会又は地方公共団体の議会の議員その他公選による公職の選挙に立候補するときは、所属長に届け出なければならない。また、これらに就任するときは、すみやかに所属長に届け出なければならない。 出勤退社 | AZ21: 0.91057867 | BT21: 0 | BU21: 0 | BZ21: 0 | CA21: 0 | CB21: 20260519T071352-20260519T182604.csv | CC21: 5 | CD21: user > assistant > assistant > tool > assistant | CE21: 1.0.0 | CH21: =IF(OR(CG21="①", CG21="⑤"), "〇", "×") | CI21: =IF(OR(AND($CT21<>"",ISNUMBER(SEARCH($CT21, AP21))),AND($CU21<>"",ISNUMBER(SEARCH($CU21, AP21))),AND($CV21<>"",ISNUMBER(SEARCH($CV21, AP21)))),"〇","-") | CJ21: =IF(OR(AND($CT21<>"",ISNUMBER(SEARCH($CT21, AS21))),AND($CU21<>"",ISNUMBER(SEARCH($CU21, AS21))),AND($CV21<>"",ISNUMBER(SEARCH($CV21, AS21)))),"〇","-") | CK21: =IF(OR(AND($CT21<>"",ISNUMBER(SEARCH($CT21, AV21))),AND($CU21<>"",ISNUMBER(SEARCH($CU21, AV21))),AND($CV21<>"",ISNUMBER(SEARCH($CV21, AV21)))),"〇","-") | CL21: =IF(OR(AND($CT21<>"",ISNUMBER(SEARCH($CT21, AY21))),AND($CU21<>"",ISNUMBER(SEARCH($CU21, AY21))),AND($CV21<>"",ISNUMBER(SEARCH($CV21, AY21)))),"〇","-") | CM21: =IF(OR(AND($CT21<>"",ISNUMBER(SEARCH($CT21, BB21))),AND($CU21<>"",ISNUMBER(SEARCH($CU21, BB21))),AND($CV21<>"",ISNUMBER(SEARCH($CV21, BB21)))),"〇","-") | CN21: =IF(OR(AND($CT21<>"",ISNUMBER(SEARCH($CT21, BE21))),AND($CU21<>"",ISNUMBER(SEARCH($CU21, BE21))),AND($CV21<>"",ISNUMBER(SEARCH($CV21, BE21)))),"〇","-") | CO21: =IF(OR(AND($CT21<>"",ISNUMBER(SEARCH($CT21, BH21))),AND($CU21<>"",ISNUMBER(SEARCH($CU21, BH21))),AND($CV21<>"",ISNUMBER(SEARCH($CV21, BH21)))),"〇","-") | CP21: =IF(OR(AND($CT21<>"",ISNUMBER(SEARCH($CT21, BK21))),AND($CU21<>"",ISNUMBER(SEARCH($CU21, BK21))),AND($CV21<>"",ISNUMBER(SEARCH($CV21, BK21)))),"〇","-") | CQ21: =IF(OR(AND($CT21<>"",ISNUMBER(SEARCH($CT21, BN21))),AND($CU21<>"",ISNUMBER(SEARCH($CU21, BN21))),AND($CV21<>"",ISNUMBER(SEARCH($CV21, BN21)))),"〇","-") | CR21: =IF(OR(AND($CT21<>"",ISNUMBER(SEARCH($CT21, BQ21))),AND($CU21<>"",ISNUMBER(SEARCH($CU21, BQ21))),AND($CV21<>"",ISNUMBER(SEARCH($CV21, BQ21)))),"〇","-") | CW21: =IF(OR(CI21="〇",CJ21="〇",CK21="〇",CL21="〇",CM21="〇",CN21="〇",CO21="〇",CP21="〇",CQ21="〇",CR21="〇"),"〇","") | DE21: =TEXT(U21,"yyyy/mm/dd") | DF21: =VLOOKUP(K21,社員マスタ!C:D,2,0) | DG21: 1779169282860
B22: a:1E2RWJP2bZnDPCFclv3PnYapCS7t4uHsWDivzJeqHzWoyI47EVboRjGmtacVwU0gu_ZOmSEKQ5NTwx-TdpGuDP_F95yWRq_in3EcUF9QIUSwDTwrgJU2oa7DOj2bWxJeq-1779169705944-FB000 | C22: =ROW(A22)-3 | D22: a:1E2RWJP2bZnDPCFclv3PnYapCS7t4uHsWDivzJeqHzWoyI47EVboRjGmtacVwU0gu_ZOmSEKQ5NTwx-TdpGuDP_F95yWRq_in3EcUF9QIUSwDTwrgJU2oa7DOj2bWxJeq-1779169705944 | E22: 1779169705944 | F22: a:1E2RWJP2bZnDPCFclv3PnYapCS7t4uHsWDivzJeqHzWoyI47EVboRjGmtacVwU0gu_ZOmSEKQ5NTwx-TdpGuDP_F95yWRq_in3EcUF9QIUSwDTwrgJU2oa7DOj2bWxJeq | G22: a:1E2RWJP2bZnDPCFclv3PnYapCS7t4uHsWDivzJeqHzWoyI47EVboRjGmtacVwU0gu_ZOmSEKQ5NTwx-TdpGuDP_F95yWRq_in3EcUF9QIUSwDTwrgJU2oa7DOj2bWxJeq-S001 | H22: 1 | I22: 1 | J22: 1 | K22: Mareaki Takagi (高木 希哲) | L22: DM | M22: タレマネサポートデスクに問合せしたいことがあるが、ヘルプデスクサイトに接続できない。 | N22: タレマネサポートデスクに問合せしたいことがあるが、ヘルプデスクサイトに接続できない。 | O22: 1 | P22: 0 | Q22: 0 | R22: 0 | S22: 46161.242 | T22: 46161.242 | U22: 46161.617 | V22: 46161.617 | W22: 6.538 | X22: searchEmployeeRules | Y22: システム操作 > タレマネ | AA22: システム操作 | AB22: システム操作 > タレマネ | AC22: predicted | AD22: 0 | AE22: ご質問の内容に関する情報が見つかりませんでした。 以下操作を行っていただくことで回答を得やすくなるのでお試しください。 * 「カテゴリ」を選択：質問要件が絞りこまれることで回答が得やすくなります。 * 「リセット」を選択：会話記録をリセットすることで回答が得やすくなります。 * 「ヘルプ」を選択 ：回答が得やすくなるヒントが確認できます。 有人での確認が必要な内容や個別条件に関するご質問は、「個別問合せ」をご利用ください。 | AF22: 1 | AG22: 1 | AH22: 3 | AI22: 0 | AJ22: 0 | AL22: 4 | AM22: 4 | AN22: 0 | AO22: QA578_system_talemane_talemane-employee.md | AP22: 質問 タレントマネジメントサービス利用会社(ログイン可能な会社)の一覧を教えてください。 回答 タレントマネジメントサービス利用会社(ログイン可能な会社)の一覧は以下URLをご確認ください。 https://www.hdservice1.nttls.co.jp/hc/ja/articles/17816048846615 | AQ22: 0.916993 | AR22: QA569_system_talemane_talemane-employee.md | AS22: 質問 タレントマネジメントサービスにログインできない場合、どうしたらいいでしょうか。 回答 タレントマネジメントサービスにログインできない場合、以下URLをご確認ください。 https://www.hdservice1.nttls.co.jp/hc/ja/articles/45200118603161 | AT22: 0.92355052 | AU22: QA590_system_talemane_talemane-employee.md | AV22: 質問 学習管理における推奨ダイヤログの表示について教えてください。 回答 学習管理における推奨ダイヤログの表示については以下URLをご確認ください。 https://www.hdservice1.nttls.co.jp/hc/ja/articles/23600147551511 | AW22: 0.916993 | AX22: QA608_system_talemane_talemane-employee.md | AY22: 質問 資格の登録手順を教えてください。 回答 資格の登録手順は以下URLをご確認ください。 https://www.hdservice1.nttls.co.jp/hc/ja/articles/44155161612825 | AZ22: 0.91655603 | BT22: 0 | BU22: 0 | BZ22: 0 | CA22: 0 | CB22: 20260519T071352-20260519T182604.csv | CC22: 5 | CD22: user > assistant > assistant > tool > assistant | CE22: 1.0.0 | CH22: =IF(OR(CG22="①", CG22="⑤"), "〇", "×") | CI22: =IF(OR(AND($CT22<>"",ISNUMBER(SEARCH($CT22, AP22))),AND($CU22<>"",ISNUMBER(SEARCH($CU22, AP22))),AND($CV22<>"",ISNUMBER(SEARCH($CV22, AP22)))),"〇","-") | CJ22: =IF(OR(AND($CT22<>"",ISNUMBER(SEARCH($CT22, AS22))),AND($CU22<>"",ISNUMBER(SEARCH($CU22, AS22))),AND($CV22<>"",ISNUMBER(SEARCH($CV22, AS22)))),"〇","-") | CK22: =IF(OR(AND($CT22<>"",ISNUMBER(SEARCH($CT22, AV22))),AND($CU22<>"",ISNUMBER(SEARCH($CU22, AV22))),AND($CV22<>"",ISNUMBER(SEARCH($CV22, AV22)))),"〇","-") | CL22: =IF(OR(AND($CT22<>"",ISNUMBER(SEARCH($CT22, AY22))),AND($CU22<>"",ISNUMBER(SEARCH($CU22, AY22))),AND($CV22<>"",ISNUMBER(SEARCH($CV22, AY22)))),"〇","-") | CM22: =IF(OR(AND($CT22<>"",ISNUMBER(SEARCH($CT22, BB22))),AND($CU22<>"",ISNUMBER(SEARCH($CU22, BB22))),AND($CV22<>"",ISNUMBER(SEARCH($CV22, BB22)))),"〇","-") | CN22: =IF(OR(AND($CT22<>"",ISNUMBER(SEARCH($CT22, BE22))),AND($CU22<>"",ISNUMBER(SEARCH($CU22, BE22))),AND($CV22<>"",ISNUMBER(SEARCH($CV22, BE22)))),"〇","-") | CO22: =IF(OR(AND($CT22<>"",ISNUMBER(SEARCH($CT22, BH22))),AND($CU22<>"",ISNUMBER(SEARCH($CU22, BH22))),AND($CV22<>"",ISNUMBER(SEARCH($CV22, BH22)))),"〇","-") | CP22: =IF(OR(AND($CT22<>"",ISNUMBER(SEARCH($CT22, BK22))),AND($CU22<>"",ISNUMBER(SEARCH($CU22, BK22))),AND($CV22<>"",ISNUMBER(SEARCH($CV22, BK22)))),"〇","-") | CQ22: =IF(OR(AND($CT22<>"",ISNUMBER(SEARCH($CT22, BN22))),AND($CU22<>"",ISNUMBER(SEARCH($CU22, BN22))),AND($CV22<>"",ISNUMBER(SEARCH($CV22, BN22)))),"〇","-") | CR22: =IF(OR(AND($CT22<>"",ISNUMBER(SEARCH($CT22, BQ22))),AND($CU22<>"",ISNUMBER(SEARCH($CU22, BQ22))),AND($CV22<>"",ISNUMBER(SEARCH($CV22, BQ22)))),"〇","-") | CW22: =IF(OR(CI22="〇",CJ22="〇",CK22="〇",CL22="〇",CM22="〇",CN22="〇",CO22="〇",CP22="〇",CQ22="〇",CR22="〇"),"〇","") | DE22: =TEXT(U22,"yyyy/mm/dd") | DF22: =VLOOKUP(K22,社員マスタ!C:D,2,0) | DG22: 1779169705944
B23: a:1WfN1QUq4KVhx-dYtNeLoFKYHSM-7d7P0WyInAiv5PzvnG4czYzEWkpfE18-h06T8tHUbJBZwZJKuspzy9hbuBnuw7FuXoB7_aN1r0YpOFEaFWAIqjedkY6Ujz061ppNj-1779179491907-FB000 | C23: =ROW(A23)-3 | D23: a:1WfN1QUq4KVhx-dYtNeLoFKYHSM-7d7P0WyInAiv5PzvnG4czYzEWkpfE18-h06T8tHUbJBZwZJKuspzy9hbuBnuw7FuXoB7_aN1r0YpOFEaFWAIqjedkY6Ujz061ppNj-1779179491907 | E23: 1779179491907 | F23: a:1WfN1QUq4KVhx-dYtNeLoFKYHSM-7d7P0WyInAiv5PzvnG4czYzEWkpfE18-h06T8tHUbJBZwZJKuspzy9hbuBnuw7FuXoB7_aN1r0YpOFEaFWAIqjedkY6Ujz061ppNj | G23: a:1WfN1QUq4KVhx-dYtNeLoFKYHSM-7d7P0WyInAiv5PzvnG4czYzEWkpfE18-h06T8tHUbJBZwZJKuspzy9hbuBnuw7FuXoB7_aN1r0YpOFEaFWAIqjedkY6Ujz061ppNj-S001 | H23: 1 | I23: 1 | J23: 1 | K23: Maika Kawamoto (河本 舞花) | L23: DM | M23: 人材派遣契約の解約する際は ・Staffiaにて契約終了日を更新する だけでいいのでしょうか。 いままではBPSの対応もあったため、確認です。 | N23: 人材派遣契約の解約する際は ・Staffiaにて契約終了日を更新する だけでいいのでしょうか。 いままではBPSの対応もあったため、確認です。 | O23: 1 | P23: 0 | Q23: 0 | R23: 0 | S23: 46161.355 | T23: 46161.355 | U23: 46161.73 | V23: 46161.73 | W23: 7.858 | X23: searchEmployeeRules | Y23: システム操作 > Staffia | AA23: システム操作 | AB23: システム操作 > Staffia | AC23: predicted | AD23: 0 | AE23: 人材派遣契約の解約手続きについてですが、現在はStaffiaで契約終了日を更新する運用となっています。 過去にはBPSでの対応が必要でしたが、最新の業務プロセスではStaffiaを利用して契約内容の管理や終了日更新を行う流れに統一されています。 主な手順は以下の通りです。 - Staffiaで契約終了日を更新する - 必要に応じて、契約内容の承認や決裁をG共通IT（決裁）で行う場合もあります BPSでの対応は現在不要となっていますので、Staffiaでの手続きのみで完了します。 ※AIの回答は必ずしも正確ではありません。参照情報も確認いただき、最終判断は所属部署の公式情報をご確認ください。 | AF23: 1 | AG23: 0 | AH23: 3 | AI23: 0 | AJ23: 0 | AL23: 4 | AM23: 4 | AN23: 0 | AO23: 【業務ID_6】Staffia業務マニュアル（派遣先組織向け）1.1版.pdf | AP23: ポイント 件名 決裁していただきたい事項 :契約期間、業務内容、取引先、費用 添付ファイル G決裁(決裁)利用メニュー :すべて ＞ 文書回覧 ＞ 文書回覧の新規作成 非公開フラグ 回覧ルート : 【実施伺い】人材派遣契約の実施について（○○担当）等 :Staffiaで作成した仕様書のPDFを添付する :個人情報が含まれる場合は「非公開フラグ」にチェックする :決裁者は派遣先責任者（派遣受入の決定権を持つ方）となるように承認フローを設定 44 | AQ23: 0.93295275 | AR23: 【業務ID_6】Staffia業務マニュアル（派遣先組織向け）1.1版.pdf | AS23: システムのインターフェースは異なるものの、スタッフ要求～個別契約についての流れは概ね同様。 スタッフ要求・見積依頼 個別契約 簡易申請に必要事項を記載し、 人員要求。 派遣会社から回答後、候補者選定 申請を実施し派遣会社確定。 共通申請で個別契約申請を実施。 派遣会社からの回答後、個別契約成立。 DREAMS ・ BUSKETS G共通IT（決裁）で実施伺い後、Staffiaに必要事項を記載し、 スタッフ要求・見積依頼を実施し、派遣会社からの回答を得る。 G共通IT（決裁）で実施伺い後、派遣会社を確定。Staffiaで個別契約内 容を派遣会社に提示。派遣会社からの回答内容を確認・承認後、個別契約 成立。 スタッフ要求書作成 派遣会社へ見積依頼 個別契約内容を作成し、派遣会社へ提示 派遣会社からの回答内容を確認・承認後、 個別契約成立 Staffia 6 | AT23: 0.9283278 | AU23: 【業務ID_6】Staffia業務マニュアル（派遣先組織向け）1.1版.pdf | AV23: 勤務管理においては、時間外・休暇・旅費申請の有無に関わらず、「派遣労働者による勤務時間と業務内容の申請」および 「勤務承認者の承認」がStaffiaでは毎日必要な点が異なる。支払は、システムのインターフェースは異なるものの、流れは概ね同様。 勤務管理 支払 スケジューラで勤務系申請（時間外・休暇・旅費等）を実施し、 上⾧が承認。（申請事項がない場合は、上⾧は承認不要） 前月の勤務実績および支払額を 確認し、簡易申請を実施。 派遣会社から回答後、検収を実施し 派遣料金を支払い。 支払額確認 検収 DREAMS ・ BUSKETS 時間外や休暇、旅費申請の有無に関わらず、派遣労働者は、毎日 当日 の勤務時間と業務内容を申請。 派遣労働者の申請に基づき、勤務承認者は内容を確認し日次承認。 月間の勤務実績を確認し、 勤務管理の月次承認を実施。 派遣会社から回答後、Staffiaで 支 払承認を実施。その後、G共通IT（財 務）に自動連係され支払い。 派遣労働者は毎日 勤務時間と業務内容を申請 勤務承認者は 勤務状況と業務内容を 日次承認 月次承認 支払承認 Staffia 7 | AW23: 0.93295275 | AX23: 【業務ID_6】Staffia業務マニュアル（派遣先組織向け）1.1版.pdf | AY23: 業務プロセス スタッフ要求 見積依頼 個別契約 勤務管理 支払  1 2   3 As-Is(～26.3) 利用システム 簡易申請 ・ BUSKETS 共通申請 ・ BUSKETS スケジューラ 簡易申請/検収 ・ BUSKETS オペレーション内容 人員要求申請 派遣会社回答 候補者選定申請（派遣会社決定） 人材派遣契約申請 決裁承認 派遣会社回答 契約締結 勤務系申請（時間外・休暇・旅費等） 承認 支払額確認 派遣会社回答 検収（支払） 1 業務プロセス 初期設定 スタッフ要求 見積依頼 個別契約 勤務管理 支払 ３ To-Be(26.4～) 利用システム Staffia 2 G共通IT（決裁） Staffia G共通IT（決裁） Staffia オペレーション内容 操作者登録や権限設定 等 スタッフ要求実施伺い申請/承認 スタッフ要求・見積依頼 派遣会社回答 個別契約実施伺い申請/承認 （派遣会社決定） 個別契約書案提示 派遣会社回答 個別契約承認 契約締結 勤務系申請 （業務内容登録・時間外・休暇・旅費 等） 日次承認 勤務管理 月次承認 派遣会社確認・請求書発行 請求額確認・支払 ※G共通IT（財務）に自動連係 4 | AZ23: 0.92340345 | BT23: 0 | BU23: 0 | BZ23: 0 | CA23: 0 | CB23: 20260519T071352-20260519T182604.csv | CC23: 5 | CD23: user > assistant > assistant > tool > assistant | CE23: 1.0.0 | CH23: =IF(OR(CG23="①", CG23="⑤"), "〇", "×") | CI23: =IF(OR(AND($CT23<>"",ISNUMBER(SEARCH($CT23, AP23))),AND($CU23<>"",ISNUMBER(SEARCH($CU23, AP23))),AND($CV23<>"",ISNUMBER(SEARCH($CV23, AP23)))),"〇","-") | CJ23: =IF(OR(AND($CT23<>"",ISNUMBER(SEARCH($CT23, AS23))),AND($CU23<>"",ISNUMBER(SEARCH($CU23, AS23))),AND($CV23<>"",ISNUMBER(SEARCH($CV23, AS23)))),"〇","-") | CK23: =IF(OR(AND($CT23<>"",ISNUMBER(SEARCH($CT23, AV23))),AND($CU23<>"",ISNUMBER(SEARCH($CU23, AV23))),AND($CV23<>"",ISNUMBER(SEARCH($CV23, AV23)))),"〇","-") | CL23: =IF(OR(AND($CT23<>"",ISNUMBER(SEARCH($CT23, AY23))),AND($CU23<>"",ISNUMBER(SEARCH($CU23, AY23))),AND($CV23<>"",ISNUMBER(SEARCH($CV23, AY23)))),"〇","-") | CM23: =IF(OR(AND($CT23<>"",ISNUMBER(SEARCH($CT23, BB23))),AND($CU23<>"",ISNUMBER(SEARCH($CU23, BB23))),AND($CV23<>"",ISNUMBER(SEARCH($CV23, BB23)))),"〇","-") | CN23: =IF(OR(AND($CT23<>"",ISNUMBER(SEARCH($CT23, BE23))),AND($CU23<>"",ISNUMBER(SEARCH($CU23, BE23))),AND($CV23<>"",ISNUMBER(SEARCH($CV23, BE23)))),"〇","-") | CO23: =IF(OR(AND($CT23<>"",ISNUMBER(SEARCH($CT23, BH23))),AND($CU23<>"",ISNUMBER(SEARCH($CU23, BH23))),AND($CV23<>"",ISNUMBER(SEARCH($CV23, BH23)))),"〇","-") | CP23: =IF(OR(AND($CT23<>"",ISNUMBER(SEARCH($CT23, BK23))),AND($CU23<>"",ISNUMBER(SEARCH($CU23, BK23))),AND($CV23<>"",ISNUMBER(SEARCH($CV23, BK23)))),"〇","-") | CQ23: =IF(OR(AND($CT23<>"",ISNUMBER(SEARCH($CT23, BN23))),AND($CU23<>"",ISNUMBER(SEARCH($CU23, BN23))),AND($CV23<>"",ISNUMBER(SEARCH($CV23, BN23)))),"〇","-") | CR23: =IF(OR(AND($CT23<>"",ISNUMBER(SEARCH($CT23, BQ23))),AND($CU23<>"",ISNUMBER(SEARCH($CU23, BQ23))),AND($CV23<>"",ISNUMBER(SEARCH($CV23, BQ23)))),"〇","-") | CW23: =IF(OR(CI23="〇",CJ23="〇",CK23="〇",CL23="〇",CM23="〇",CN23="〇",CO23="〇",CP23="〇",CQ23="〇",CR23="〇"),"〇","") | DE23: =TEXT(U23,"yyyy/mm/dd") | DF23: =VLOOKUP(K23,社員マスタ!C:D,2,0) | DG23: 1779179491907
B24: a:1MauaxVJ9d9mgArrebuAczxR5eudyM6cHaTjjZyFnI5DWJutBdICt9jx2jMDfHrMv8kfjPZrlIgALZP7ohSYQJe_d1ETRdHMG-Fh5Ds2v0W1RyQIDos97SFXF7dwrCjxm-1779180592777-FB000 | C24: =ROW(A24)-3 | D24: a:1MauaxVJ9d9mgArrebuAczxR5eudyM6cHaTjjZyFnI5DWJutBdICt9jx2jMDfHrMv8kfjPZrlIgALZP7ohSYQJe_d1ETRdHMG-Fh5Ds2v0W1RyQIDos97SFXF7dwrCjxm-1779180592777 | E24: 1779180592777 | F24: a:1MauaxVJ9d9mgArrebuAczxR5eudyM6cHaTjjZyFnI5DWJutBdICt9jx2jMDfHrMv8kfjPZrlIgALZP7ohSYQJe_d1ETRdHMG-Fh5Ds2v0W1RyQIDos97SFXF7dwrCjxm | G24: a:1MauaxVJ9d9mgArrebuAczxR5eudyM6cHaTjjZyFnI5DWJutBdICt9jx2jMDfHrMv8kfjPZrlIgALZP7ohSYQJe_d1ETRdHMG-Fh5Ds2v0W1RyQIDos97SFXF7dwrCjxm-S001 | H24: 1 | I24: 1 | J24: 1 | K24: You Ryuu (劉 洋) | L24: DM | M24: teamsで議事録の作成方 | N24: teamsで議事録の作成方 | O24: 1 | P24: 0 | Q24: 0 | R24: 0 | S24: 46161.368 | T24: 46161.368 | U24: 46161.743 | V24: 46161.743 | W24: 5.603 | X24: searchEmployeeRules | Y24: システム操作 | AA24: システム操作 | AB24: システム操作 | AC24: predicted | AD24: 0 | AE24: ご質問の内容に関する情報が見つかりませんでした。 以下操作を行っていただくことで回答を得やすくなるのでお試しください。 * 「カテゴリ」を選択：質問要件が絞りこまれることで回答が得やすくなります。 * 「リセット」を選択：会話記録をリセットすることで回答が得やすくなります。 * 「ヘルプ」を選択 ：回答が得やすくなるヒントが確認できます。 有人での確認が必要な内容や個別条件に関するご質問は、「個別問合せ」をご利用ください。 | AF24: 1 | AG24: 1 | AH24: 3 | AI24: 0 | AJ24: 0 | AL24: 4 | AM24: 4 | AN24: 0 | AO24: 【業務ID_6】Staffia業務マニュアル（派遣先組織向け）1.1版.pdf | AP24: ポイント 件名 決裁していただきたい事項 :契約期間、業務内容、取引先、費用 添付ファイル G決裁(決裁)利用メニュー :すべて ＞ 文書回覧 ＞ 文書回覧の新規作成 非公開フラグ 回覧ルート : 【実施伺い】人材派遣契約の実施について（○○担当）等 :Staffiaで作成した仕様書のPDFを添付する :個人情報が含まれる場合は「非公開フラグ」にチェックする :決裁者は派遣先責任者（派遣受入の決定権を持つ方）となるように承認フローを設定 44 | AQ24: 0.91470227 | AR24: 【業務ID_6】Staffia業務マニュアル（派遣先組織向け）1.1版.pdf | AS24: 改訂履歴 バージョン 更新日 1.0 2025.03.19 1.1 2025.10.31 更新内容 初版（eラーニング キーユーザー習熟用マニュアル） 業務フロー比較追記、実施伺い(G決裁) ポイント追記 2 | AT24: 0.91051417 | AU24: 【業務ID_6】Staffia業務マニュアル（派遣先組織向け）1.1版.pdf | AV24: ポイント 件名 決裁していただきたい事項 :派遣受入に至る背景、求めるスキル等 を適宜記入 G決裁(決裁)利用メニュー :すべて ＞ 文書回覧 ＞ 文書回覧の新規作成 回覧ルート : 【実施伺い】人材派遣の要求について（○○担当） 等 :決裁者は派遣先責任者（派遣受入の決定権を持つ方）となるように承認フローを設定 18 | AW24: 0.91470227 | AX24: 【社員用】タレントマネジメントサ-ビスマニュアル.pdf | AY24: 第３９章 資格情報管理 人担 育担 上長 社員 ● ● ● ６．「保存」ボタンを押下します。 （１）「申請内容の確認」画面が表示されます。 （２）上長（承認者）への伝達事項（「どの資格情報を追加したのか」等）をコメント欄に記入します。 （３）「確認」を押下します。 －208－ © 2022 NTT BUSINESS ASSOCIE | AZ24: 0.90365487 | BT24: 0 | BU24: 0 | BZ24: 0 | CA24: 0 | CB24: 20260519T071352-20260519T182604.csv | CC24: 5 | CD24: user > assistant > assistant > tool > assistant | CE24: 1.0.0 | CH24: =IF(OR(CG24="①", CG24="⑤"), "〇", "×") | CI24: =IF(OR(AND($CT24<>"",ISNUMBER(SEARCH($CT24, AP24))),AND($CU24<>"",ISNUMBER(SEARCH($CU24, AP24))),AND($CV24<>"",ISNUMBER(SEARCH($CV24, AP24)))),"〇","-") | CJ24: =IF(OR(AND($CT24<>"",ISNUMBER(SEARCH($CT24, AS24))),AND($CU24<>"",ISNUMBER(SEARCH($CU24, AS24))),AND($CV24<>"",ISNUMBER(SEARCH($CV24, AS24)))),"〇","-") | CK24: =IF(OR(AND($CT24<>"",ISNUMBER(SEARCH($CT24, AV24))),AND($CU24<>"",ISNUMBER(SEARCH($CU24, AV24))),AND($CV24<>"",ISNUMBER(SEARCH($CV24, AV24)))),"〇","-") | CL24: =IF(OR(AND($CT24<>"",ISNUMBER(SEARCH($CT24, AY24))),AND($CU24<>"",ISNUMBER(SEARCH($CU24, AY24))),AND($CV24<>"",ISNUMBER(SEARCH($CV24, AY24)))),"〇","-") | CM24: =IF(OR(AND($CT24<>"",ISNUMBER(SEARCH($CT24, BB24))),AND($CU24<>"",ISNUMBER(SEARCH($CU24, BB24))),AND($CV24<>"",ISNUMBER(SEARCH($CV24, BB24)))),"〇","-") | CN24: =IF(OR(AND($CT24<>"",ISNUMBER(SEARCH($CT24, BE24))),AND($CU24<>"",ISNUMBER(SEARCH($CU24, BE24))),AND($CV24<>"",ISNUMBER(SEARCH($CV24, BE24)))),"〇","-") | CO24: =IF(OR(AND($CT24<>"",ISNUMBER(SEARCH($CT24, BH24))),AND($CU24<>"",ISNUMBER(SEARCH($CU24, BH24))),AND($CV24<>"",ISNUMBER(SEARCH($CV24, BH24)))),"〇","-") | CP24: =IF(OR(AND($CT24<>"",ISNUMBER(SEARCH($CT24, BK24))),AND($CU24<>"",ISNUMBER(SEARCH($CU24, BK24))),AND($CV24<>"",ISNUMBER(SEARCH($CV24, BK24)))),"〇","-") | CQ24: =IF(OR(AND($CT24<>"",ISNUMBER(SEARCH($CT24, BN24))),AND($CU24<>"",ISNUMBER(SEARCH($CU24, BN24))),AND($CV24<>"",ISNUMBER(SEARCH($CV24, BN24)))),"〇","-") | CR24: =IF(OR(AND($CT24<>"",ISNUMBER(SEARCH($CT24, BQ24))),AND($CU24<>"",ISNUMBER(SEARCH($CU24, BQ24))),AND($CV24<>"",ISNUMBER(SEARCH($CV24, BQ24)))),"〇","-") | CW24: =IF(OR(CI24="〇",CJ24="〇",CK24="〇",CL24="〇",CM24="〇",CN24="〇",CO24="〇",CP24="〇",CQ24="〇",CR24="〇"),"〇","") | DE24: =TEXT(U24,"yyyy/mm/dd") | DF24: =VLOOKUP(K24,社員マスタ!C:D,2,0) | DG24: 1779180592777
B25: a:13A1wxb6vrCt4Foe28ITVAk6tpihTZByQurqV_IQIX2LrVkEdzURNHj2iS354nRrWe3J6AFlsui7oeXnrqe7XDuhyeaBdDvOzyz9XedOSPYJJV7pYnHNAJ-OK3zcDP0fY-1776773475198-FB001 | C25: =ROW(A25)-3 | D25: a:13A1wxb6vrCt4Foe28ITVAk6tpihTZByQurqV_IQIX2LrVkEdzURNHj2iS354nRrWe3J6AFlsui7oeXnrqe7XDuhyeaBdDvOzyz9XedOSPYJJV7pYnHNAJ-OK3zcDP0fY-1776773475198 | E25: 1776773475198 | F25: a:13A1wxb6vrCt4Foe28ITVAk6tpihTZByQurqV_IQIX2LrVkEdzURNHj2iS354nRrWe3J6AFlsui7oeXnrqe7XDuhyeaBdDvOzyz9XedOSPYJJV7pYnHNAJ-OK3zcDP0fY | G25: a:13A1wxb6vrCt4Foe28ITVAk6tpihTZByQurqV_IQIX2LrVkEdzURNHj2iS354nRrWe3J6AFlsui7oeXnrqe7XDuhyeaBdDvOzyz9XedOSPYJJV7pYnHNAJ-OK3zcDP0fY-S001 | H25: 1 | I25: 1 | J25: 1 | K25: Youko Iwamoto (岩本 洋子) | L25: DM | O25: 0 | P25: 0 | Q25: 0 | R25: 0 | S25: 46161.389 | T25: 46161.389 | U25: 46161.764 | V25: 46161.764 | W25: 0 | AB25: 未分類 | AC25: none | AD25: 1 | AF25: 0 | AG25: 0 | AH25: 0 | AI25: 0 | AJ25: 0 | AL25: 0 | AM25: 0 | AN25: 0 | BS25: a:13A1wxb6vrCt4Foe28ITVAk6tpihTZByQurqV_IQIX2LrVkEdzURNHj2iS354nRrWe3J6AFlsui7oeXnrqe7XDuhyeaBdDvOzyz9XedOSPYJJV7pYnHNAJ-OK3zcDP0fY-1776773475198-FB001 | BT25: 1 | BU25: 1 | BV25: good | BX25: 46161.389 | BY25: 46161.764 | BZ25: 1 | CA25: 0 | CB25: 20260519T071352-20260519T182604.csv | CC25: 1 | CD25: feedback | CE25: 1.0.0 | CF25: no answer found | CH25: =IF(OR(CG25="①", CG25="⑤"), "〇", "×") | CI25: =IF(OR(AND($CT25<>"",ISNUMBER(SEARCH($CT25, AP25))),AND($CU25<>"",ISNUMBER(SEARCH($CU25, AP25))),AND($CV25<>"",ISNUMBER(SEARCH($CV25, AP25)))),"〇","-") | CJ25: =IF(OR(AND($CT25<>"",ISNUMBER(SEARCH($CT25, AS25))),AND($CU25<>"",ISNUMBER(SEARCH($CU25, AS25))),AND($CV25<>"",ISNUMBER(SEARCH($CV25, AS25)))),"〇","-") | CK25: =IF(OR(AND($CT25<>"",ISNUMBER(SEARCH($CT25, AV25))),AND($CU25<>"",ISNUMBER(SEARCH($CU25, AV25))),AND($CV25<>"",ISNUMBER(SEARCH($CV25, AV25)))),"〇","-") | CL25: =IF(OR(AND($CT25<>"",ISNUMBER(SEARCH($CT25, AY25))),AND($CU25<>"",ISNUMBER(SEARCH($CU25, AY25))),AND($CV25<>"",ISNUMBER(SEARCH($CV25, AY25)))),"〇","-") | CM25: =IF(OR(AND($CT25<>"",ISNUMBER(SEARCH($CT25, BB25))),AND($CU25<>"",ISNUMBER(SEARCH($CU25, BB25))),AND($CV25<>"",ISNUMBER(SEARCH($CV25, BB25)))),"〇","-") | CN25: =IF(OR(AND($CT25<>"",ISNUMBER(SEARCH($CT25, BE25))),AND($CU25<>"",ISNUMBER(SEARCH($CU25, BE25))),AND($CV25<>"",ISNUMBER(SEARCH($CV25, BE25)))),"〇","-") | CO25: =IF(OR(AND($CT25<>"",ISNUMBER(SEARCH($CT25, BH25))),AND($CU25<>"",ISNUMBER(SEARCH($CU25, BH25))),AND($CV25<>"",ISNUMBER(SEARCH($CV25, BH25)))),"〇","-") | CP25: =IF(OR(AND($CT25<>"",ISNUMBER(SEARCH($CT25, BK25))),AND($CU25<>"",ISNUMBER(SEARCH($CU25, BK25))),AND($CV25<>"",ISNUMBER(SEARCH($CV25, BK25)))),"〇","-") | CQ25: =IF(OR(AND($CT25<>"",ISNUMBER(SEARCH($CT25, BN25))),AND($CU25<>"",ISNUMBER(SEARCH($CU25, BN25))),AND($CV25<>"",ISNUMBER(SEARCH($CV25, BN25)))),"〇","-") | CR25: =IF(OR(AND($CT25<>"",ISNUMBER(SEARCH($CT25, BQ25))),AND($CU25<>"",ISNUMBER(SEARCH($CU25, BQ25))),AND($CV25<>"",ISNUMBER(SEARCH($CV25, BQ25)))),"〇","-") | CW25: =IF(OR(CI25="〇",CJ25="〇",CK25="〇",CL25="〇",CM25="〇",CN25="〇",CO25="〇",CP25="〇",CQ25="〇",CR25="〇"),"〇","") | DE25: =TEXT(U25,"yyyy/mm/dd") | DF25: =VLOOKUP(K25,社員マスタ!C:D,2,0) | DG25: 1776773475198
B26: a:1Q-jqK-laMj77E-Zsprk_hIFCHxQFFrDmHsnB5pslAu1jS_XTyjul9yZQHeRE6xwcJUQWK1c3w1Hr0J2hLYwTA-7D5T4gkpnhx3NNxx5DF_X3_6tFpSbByET7Jx0Zffnb-1779182755902-FB000 | C26: =ROW(A26)-3 | D26: a:1Q-jqK-laMj77E-Zsprk_hIFCHxQFFrDmHsnB5pslAu1jS_XTyjul9yZQHeRE6xwcJUQWK1c3w1Hr0J2hLYwTA-7D5T4gkpnhx3NNxx5DF_X3_6tFpSbByET7Jx0Zffnb-1779182755902 | E26: 1779182755902 | F26: a:1Q-jqK-laMj77E-Zsprk_hIFCHxQFFrDmHsnB5pslAu1jS_XTyjul9yZQHeRE6xwcJUQWK1c3w1Hr0J2hLYwTA-7D5T4gkpnhx3NNxx5DF_X3_6tFpSbByET7Jx0Zffnb | G26: a:1Q-jqK-laMj77E-Zsprk_hIFCHxQFFrDmHsnB5pslAu1jS_XTyjul9yZQHeRE6xwcJUQWK1c3w1Hr0J2hLYwTA-7D5T4gkpnhx3NNxx5DF_X3_6tFpSbByET7Jx0Zffnb-S001 | H26: 1 | I26: 1 | J26: 1 | K26: Sayaka Itou (伊藤 さやか) | L26: DM | M26: 海外出張の申請をJTBトラベルのコンサルタントへ依頼しました。 予約確定→DREAMSにて予約内容を取り込み申請が完了→JTBトラベルにてeチケットが発券された状態です。DREAMSにて申請した内容とeチケット発行後の値段や内容に相違はありませんが、ビズバンスにて再申請のボタンが出ている状況です。内容に間違いもなく、金額も変わっていなのですが、再申請が必要になりますか？ | N26: 海外出張の申請をJTBトラベルのコンサルタントへ依頼しました。 予約確定→DREAMSにて予約内容を取り込み申請が完了→JTBトラベルにてeチケットが発券された状態です。DREAMSにて申請した内容とeチケット発行後の値段や内容に相違はありませんが、ビズバンスにて再申請のボタンが出ている状況です。内容に間違いもなく、金額も変わっていなのですが、再申請が必要になりますか？ | O26: 1 | P26: 0 | Q26: 0 | R26: 0 | S26: 46161.393 | T26: 46161.393 | U26: 46161.768 | V26: 46161.768 | W26: 7.851 | X26: searchEmployeeRules | Y26: 旅費 > その他 | AA26: 旅費 | AB26: 旅費 > その他 | AC26: predicted | AD26: 0 | AE26: 検索結果からは、dDREAMSで申請した内容とeチケット発行後の内容や金額に相違がない場合のビズバンスでの再申請の必要性について、明確な記載は見当たりませんでした。 この件については、詳細な対応方法が記載されていないため、適切な問い合わせ先への確認が推奨されています。 ※AIの回答は必ずしも正確ではありません。参照情報も確認いただき、最終判断は所属部署の公式情報をご確認ください。 | AF26: 1 | AG26: 0 | AH26: 3 | AI26: 0 | AJ26: 0 | AL26: 4 | AM26: 4 | AN26: 0 | AO26: QA176_policy-operations_travel_travel-assignment_office-work_domestic_training_home-travel-expenses_overseas_operational_travel-others.md | AP26: OBの方向け 赴任旅費申請マニュアル https://nttdocomo.sharepoint.com/:x:/r/sites/LifeAassist-kyuyo_Docomo_Com_Comware-all/Shared%20Documents/%E7%B5%A6%E4%B8%8E%E3%82%A2%E3%82%B7%E3%82%B9%E3%83%88HP/1.%E5%88%B6%E5%BA%A6%E3%83%BB%E7%94%B3%E8%AB%8B%E6%96%B9%E6%B3%95/%E2%91%A3%E8%B5%B4%E4%BB%BB%E6%97%85%E8%B2%BB/%E2%91%A0%E8%B5%B4%E4%BB%BB%E6%97%85%E8%B2%BB%E7%94%B3%E8%AB%8B%E3%83%9E%E3%83%8B%E3%83%A5%E3%82%A2%E3%83%AB.xlsx?d=w7934a11c73d548298f03c753256151f8&csf=1&web=1&e=9LwCMQ RSの方向け 『【RS】赴任旅費申請時の注意点』 | AQ26: 0.91980255 | AR26: QA176_policy-operations_travel_travel-assignment_office-work_domestic_training_home-travel-expenses_overseas_operational_travel-others.md | AS26: 質問 赴任旅費の申請方法を教えてください。 回答 赴任旅費の申請方法については、以下の注意点、およびマニュアルをご確認ください。 OBの方向け 『「赴任旅費」申請時の注意点』 https://nttdocomo.sharepoint.com/:p:/r/sites/LifeAassist-kyuyo_Docomo_Com_Comware-all/Shared%20Documents/%E7%B5%A6%E4%B8%8E%E3%82%A2%E3%82%B7%E3%82%B9%E3%83%88HP/1.%E5%88%B6%E5%BA%A6%E3%83%BB%E7%94%B3%E8%AB%8B%E6%96%B9%E6%B3%95/%E2%91%A3%E8%B5%B4%E4%BB%BB%E6%97%85%E8%B2%BB/%E3%80%90OB%E5%AF%BE%E8%B1%A1%E8%80%85%E7%94%A8%E3%80%91%E3%80%8C%E8%B5%B4%E4%BB%BB%E6%97%85%E8%B2%BB%E3%80%8D%E7%94%B3%E8%AB%8B%E6%99%82%E3%81%AE%E6%B3%A8%E6%84%8F%E7%82%B9.pptx?d=wfe80418354504c849904e10a8f67ccdc&csf=1&web=1&e=EZHhhX OBの方向け 赴任旅費申請マニュアル | AT26: 0.91923625 | AU26: QA213_policy-operations_travel_travel-assignment_office-work_domestic_training_home-travel-expenses_overseas_operational_travel-others.md | AV26: 質問 NTTトラベルの旅行パック・オンライン予約サービス・チケット手配は利用可能ですか。 回答 上記サービスは会社間精算が必要となるため、赴任にあたっては利用不可です。 交通手段と宿泊施設は自己手配をお願いいたします。 | AW26: 0.91980255 | AX26: QA214_policy-operations_travel_travel-assignment_office-work_domestic_training_home-travel-expenses_overseas_operational_travel-others.md | AY26: 質問 社宅について確認したいです。 回答 社宅について確認したい場合は、ライフアシストセンター総務・厚生アシスト担当HPをご確認ください。 http://ebis.ac.is.nttdocomo.co.jp/ | AZ26: 0.90122822 | BT26: 0 | BU26: 0 | BZ26: 0 | CA26: 0 | CB26: 20260519T071352-20260519T182604.csv | CC26: 5 | CD26: user > assistant > assistant > tool > assistant | CE26: 1.0.0 | CH26: =IF(OR(CG26="①", CG26="⑤"), "〇", "×") | CI26: =IF(OR(AND($CT26<>"",ISNUMBER(SEARCH($CT26, AP26))),AND($CU26<>"",ISNUMBER(SEARCH($CU26, AP26))),AND($CV26<>"",ISNUMBER(SEARCH($CV26, AP26)))),"〇","-") | CJ26: =IF(OR(AND($CT26<>"",ISNUMBER(SEARCH($CT26, AS26))),AND($CU26<>"",ISNUMBER(SEARCH($CU26, AS26))),AND($CV26<>"",ISNUMBER(SEARCH($CV26, AS26)))),"〇","-") | CK26: =IF(OR(AND($CT26<>"",ISNUMBER(SEARCH($CT26, AV26))),AND($CU26<>"",ISNUMBER(SEARCH($CU26, AV26))),AND($CV26<>"",ISNUMBER(SEARCH($CV26, AV26)))),"〇","-") | CL26: =IF(OR(AND($CT26<>"",ISNUMBER(SEARCH($CT26, AY26))),AND($CU26<>"",ISNUMBER(SEARCH($CU26, AY26))),AND($CV26<>"",ISNUMBER(SEARCH($CV26, AY26)))),"〇","-") | CM26: =IF(OR(AND($CT26<>"",ISNUMBER(SEARCH($CT26, BB26))),AND($CU26<>"",ISNUMBER(SEARCH($CU26, BB26))),AND($CV26<>"",ISNUMBER(SEARCH($CV26, BB26)))),"〇","-") | CN26: =IF(OR(AND($CT26<>"",ISNUMBER(SEARCH($CT26, BE26))),AND($CU26<>"",ISNUMBER(SEARCH($CU26, BE26))),AND($CV26<>"",ISNUMBER(SEARCH($CV26, BE26)))),"〇","-") | CO26: =IF(OR(AND($CT26<>"",ISNUMBER(SEARCH($CT26, BH26))),AND($CU26<>"",ISNUMBER(SEARCH($CU26, BH26))),AND($CV26<>"",ISNUMBER(SEARCH($CV26, BH26)))),"〇","-") | CP26: =IF(OR(AND($CT26<>"",ISNUMBER(SEARCH($CT26, BK26))),AND($CU26<>"",ISNUMBER(SEARCH($CU26, BK26))),AND($CV26<>"",ISNUMBER(SEARCH($CV26, BK26)))),"〇","-") | CQ26: =IF(OR(AND($CT26<>"",ISNUMBER(SEARCH($CT26, BN26))),AND($CU26<>"",ISNUMBER(SEARCH($CU26, BN26))),AND($CV26<>"",ISNUMBER(SEARCH($CV26, BN26)))),"〇","-") | CR26: =IF(OR(AND($CT26<>"",ISNUMBER(SEARCH($CT26, BQ26))),AND($CU26<>"",ISNUMBER(SEARCH($CU26, BQ26))),AND($CV26<>"",ISNUMBER(SEARCH($CV26, BQ26)))),"〇","-") | CW26: =IF(OR(CI26="〇",CJ26="〇",CK26="〇",CL26="〇",CM26="〇",CN26="〇",CO26="〇",CP26="〇",CQ26="〇",CR26="〇"),"〇","") | DE26: =TEXT(U26,"yyyy/mm/dd") | DF26: =VLOOKUP(K26,社員マスタ!C:D,2,0) | DG26: 1779182755902
B27: a:1Wue-93ng9YNfWzk9JEWBn6LbFbUsTkiYbOCjpT5XzQYYFlvbVEVdr0no5pUfMMvGlzqKQcuAtJ6n8nPuSg29Wyn8hY2RyLNAAzk1kXUpi9ut3EZSURX1hsM7srdrzKoj-1779235420131-FB000 | C27: =ROW(A27)-3 | D27: a:1Wue-93ng9YNfWzk9JEWBn6LbFbUsTkiYbOCjpT5XzQYYFlvbVEVdr0no5pUfMMvGlzqKQcuAtJ6n8nPuSg29Wyn8hY2RyLNAAzk1kXUpi9ut3EZSURX1hsM7srdrzKoj-1779235420131 | E27: 1779235420131 | F27: a:1Wue-93ng9YNfWzk9JEWBn6LbFbUsTkiYbOCjpT5XzQYYFlvbVEVdr0no5pUfMMvGlzqKQcuAtJ6n8nPuSg29Wyn8hY2RyLNAAzk1kXUpi9ut3EZSURX1hsM7srdrzKoj | G27: a:1Wue-93ng9YNfWzk9JEWBn6LbFbUsTkiYbOCjpT5XzQYYFlvbVEVdr0no5pUfMMvGlzqKQcuAtJ6n8nPuSg29Wyn8hY2RyLNAAzk1kXUpi9ut3EZSURX1hsM7srdrzKoj-S001 | H27: 1 | I27: 1 | J27: 1 | K27: Tadahiro Itou (伊藤 忠洋) | L27: DM | M27: リモートスタンダード勤務となりますが、 山王パークタワーに出社した際の通勤費が スケジューラ上で申請しても支給されていない状況です。 | N27: リモートスタンダード勤務となりますが、 山王パークタワーに出社した際の通勤費が スケジューラ上で申請しても支給されていない状況です。 | O27: 1 | P27: 0 | Q27: 0 | R27: 0 | S27: 46162.003 | T27: 46162.003 | U27: 46162.378 | V27: 46162.378 | W27: 7.035 | X27: searchEmployeeRules | Y27: 制度・運用 > 通勤費 | AA27: 制度・運用 | AB27: 制度・運用 > 通勤費 | AC27: predicted | AD27: 0 | AE27: リモートワークスタンダード勤務の場合、出社時の通勤費申請は「標準的出社経路申請」で行う必要があります。スケジューラ上で申請しても支給されていない場合、申請方法に誤りがある可能性があります。 申請誤りがあった場合は、以下の手順で対応してください。 - 申請誤りの申請を停止する（「標準的出社経路停止申請」など） ・停止事由は「その他（申請誤りのため）」とし、コメント欄にもその旨を記載 ・停止日は誤って登録した申請の開始日の翌日 - 正しい支給方法で再申請する ・リモートスタンダード勤務の場合は「標準的出社経路申請」を選択 ・経路変更事由は「その他（申請誤りのため）」とし、コメント欄にリカバリ申請である旨と本来の正しい開始日を記載 なお、定期代支給の場合で申請開始日が月途中となる場合、初月は不定期支給（片道運賃×2×勤務日数）となり、翌月から最長定期代が支給されます。 申請内容や支給方法に誤りがないか、上記手順を参考にご確認ください。 ※AIの回答は必ずしも正確ではありません。参照情報も確認いただき、最終判断は所属部署の公式情報をご確認ください。 | AF27: 1 | AG27: 0 | AH27: 3 | AI27: 0 | AJ27: 0 | AL27: 4 | AM27: 4 | AN27: 0 | AO27: QA228_policy-operations_commute-costs_com-others.md | AP27: 質問 オフィスベースの通勤費申請とリモートスタンダードの標準的出社経路申請を誤って申請してしまいました。どうすればいいですか。 回答 以下の手順で注意点を参考に申請を行ってください。 【STEP1】停止申請を実施（通勤費申請を行った場合は「通勤費停止申請」、標準的出社経路申請を行った場合は「標準的出社経路停止申請」） ※停止事由：その他（申請誤りのため） ※停止日：誤って登録した申請の開始日の翌日（4/1任命で4/1を開始日としていた場合、停止日は4/2） ※コメント欄に申請誤りのため停止申請を行う旨記載願います。 【STEP2】正しい支給方法の申請を実施 （リモートスタンダードの方・・・「標準的出社経路申請」、オフィスベースの方・・・「通勤費申請」※申請事由選択画面で「【定期代支払い】通勤経路申請」か「【実績支払い】通勤経路申請」を選択） ※経路変更事由：その他（申請誤りのため） ※開始日：停止日の翌日（【STEP1】で4/2を停止日とした場合、開始日は4/3） ※コメント欄に申請誤りのためのリカバリ申請である旨と、本来の正しい開始日を記載願います。 ※定期代支給の場合で、【STEP2】で登録した通勤開始日が月途中となる場合、定期代は翌月からの最長定期代を支給となり、初月は不定期支給（片道運賃×2×勤務日数）となります。 | AQ27: 0.93244472 | AR27: QA221_policy-operations_commute-costs_com-others.md | AS27: 質問 人事異動がありましたが、転居はなく、勤務ビルの変更のみで勤務地最寄り駅、及び通勤経路の変更はありません。 この場合、あらためて通勤費申請は必要ですか。 回答 自組織の通勤費支給方法（定期or実績orRS）については、上長または所属組織の総括担当にあらかじめご確認ください。 【通勤費の支給方法（定期or実績orRS）に変更がある場合】 異動前に「通勤費停止申請」を実施いただき、異動後はすみやかに支給方法に応じた通勤費申請を実施してください。（■1-01のパターン表参照） ※「勤務事業所変更申請」では、支給方法の切り替えはできませんので、「勤務事業所変更申請」は選択されないようご注意ください。 【通勤費の支給方法（定期or実績orRS）に変更がない場合】 定期又は実績の場合で、勤務事業所まで交通用具（自転車・自動車）を利用していない場合・・・「勤務事業変更申請」を選択して申請してください。（通勤費申請の申請事由選択画面において選択）現在の経路のまま勤務事業所のみ変更できます。 勤務事業所まで交通用具（自転車・自動車）を利用している場合、もしくはRSの場合・・・・支給方法に応じた申請（「【定期代支払】通勤経路申請」or「【実績支払】通勤経路申請」or「標準的出社経路申請」）を行ってください。 ※勤務事業所まで交通用具（自転車・自動車）を利用している場合には、利用距離により、利用可否や支給額等が変更になる場合がございますので、その場合には「勤務事業所変更申請」を選択しての申請はお控えください。 | AT27: 0.93083085 | AU27: QA218_policy-operations_commute-costs_com-others.md | AV27: 質問 リモートワークが多いので通勤費申請（RSの場合は標準的出社経路申請）はしばらく実施しなくても大丈夫ですか。 回答 業務状況により急遽出社を命じられる可能性があるので、異動後または転居後、速やかに申請してください。 | AW27: 0.93244472 | AX27: QA219_policy-operations_commute-costs_com-others.md | AY27: 質問 新しい勤務事業所まで現住居から片道３時間ほどかかりますが、リモートワークが多いため、できれば移転せず通勤したいと考えています。 通勤費申請は認められますか。 回答 社員の健康面を配慮し、原則「片道120分以内※」という基準を設け通勤経路設定を実施しておりますので、申請を認めることはできません。 ※自宅から勤務事業所まで徒歩を含めた片道通勤時間 | AZ27: 0.9301309 | BT27: 0 | BU27: 0 | BZ27: 0 | CA27: 0 | CB27: 20260520T090340-20260520T210308.csv | CC27: 5 | CD27: user > assistant > assistant > tool > assistant | CE27: 1.0.0 | CH27: =IF(OR(CG27="①", CG27="⑤"), "〇", "×") | CI27: =IF(OR(AND($CT27<>"",ISNUMBER(SEARCH($CT27, AP27))),AND($CU27<>"",ISNUMBER(SEARCH($CU27, AP27))),AND($CV27<>"",ISNUMBER(SEARCH($CV27, AP27)))),"〇","-") | CJ27: =IF(OR(AND($CT27<>"",ISNUMBER(SEARCH($CT27, AS27))),AND($CU27<>"",ISNUMBER(SEARCH($CU27, AS27))),AND($CV27<>"",ISNUMBER(SEARCH($CV27, AS27)))),"〇","-") | CK27: =IF(OR(AND($CT27<>"",ISNUMBER(SEARCH($CT27, AV27))),AND($CU27<>"",ISNUMBER(SEARCH($CU27, AV27))),AND($CV27<>"",ISNUMBER(SEARCH($CV27, AV27)))),"〇","-") | CL27: =IF(OR(AND($CT27<>"",ISNUMBER(SEARCH($CT27, AY27))),AND($CU27<>"",ISNUMBER(SEARCH($CU27, AY27))),AND($CV27<>"",ISNUMBER(SEARCH($CV27, AY27)))),"〇","-") | CM27: =IF(OR(AND($CT27<>"",ISNUMBER(SEARCH($CT27, BB27))),AND($CU27<>"",ISNUMBER(SEARCH($CU27, BB27))),AND($CV27<>"",ISNUMBER(SEARCH($CV27, BB27)))),"〇","-") | CN27: =IF(OR(AND($CT27<>"",ISNUMBER(SEARCH($CT27, BE27))),AND($CU27<>"",ISNUMBER(SEARCH($CU27, BE27))),AND($CV27<>"",ISNUMBER(SEARCH($CV27, BE27)))),"〇","-") | CO27: =IF(OR(AND($CT27<>"",ISNUMBER(SEARCH($CT27, BH27))),AND($CU27<>"",ISNUMBER(SEARCH($CU27, BH27))),AND($CV27<>"",ISNUMBER(SEARCH($CV27, BH27)))),"〇","-") | CP27: =IF(OR(AND($CT27<>"",ISNUMBER(SEARCH($CT27, BK27))),AND($CU27<>"",ISNUMBER(SEARCH($CU27, BK27))),AND($CV27<>"",ISNUMBER(SEARCH($CV27, BK27)))),"〇","-") | CQ27: =IF(OR(AND($CT27<>"",ISNUMBER(SEARCH($CT27, BN27))),AND($CU27<>"",ISNUMBER(SEARCH($CU27, BN27))),AND($CV27<>"",ISNUMBER(SEARCH($CV27, BN27)))),"〇","-") | CR27: =IF(OR(AND($CT27<>"",ISNUMBER(SEARCH($CT27, BQ27))),AND($CU27<>"",ISNUMBER(SEARCH($CU27, BQ27))),AND($CV27<>"",ISNUMBER(SEARCH($CV27, BQ27)))),"〇","-") | CW27: =IF(OR(CI27="〇",CJ27="〇",CK27="〇",CL27="〇",CM27="〇",CN27="〇",CO27="〇",CP27="〇",CQ27="〇",CR27="〇"),"〇","") | DE27: =TEXT(U27,"yyyy/mm/dd") | DF27: =VLOOKUP(K27,社員マスタ!C:D,2,0) | DG27: 1779235420131
B28: a:1Wue-93ng9YNfWzk9JEWBn6LbFbUsTkiYbOCjpT5XzQYYFlvbVEVdr0no5pUfMMvGlzqKQcuAtJ6n8nPuSg29Wyn8hY2RyLNAAzk1kXUpi9ut3EZSURX1hsM7srdrzKoj-f:a6718c3e-0a1b-2db8-a0b4-be641325c124-FB000 | C28: =ROW(A28)-3 | D28: a:1Wue-93ng9YNfWzk9JEWBn6LbFbUsTkiYbOCjpT5XzQYYFlvbVEVdr0no5pUfMMvGlzqKQcuAtJ6n8nPuSg29Wyn8hY2RyLNAAzk1kXUpi9ut3EZSURX1hsM7srdrzKoj-f:a6718c3e-0a1b-2db8-a0b4-be641325c124 | E28: f:a6718c3e-0a1b-2db8-a0b4-be641325c124 | F28: a:1Wue-93ng9YNfWzk9JEWBn6LbFbUsTkiYbOCjpT5XzQYYFlvbVEVdr0no5pUfMMvGlzqKQcuAtJ6n8nPuSg29Wyn8hY2RyLNAAzk1kXUpi9ut3EZSURX1hsM7srdrzKoj | G28: a:1Wue-93ng9YNfWzk9JEWBn6LbFbUsTkiYbOCjpT5XzQYYFlvbVEVdr0no5pUfMMvGlzqKQcuAtJ6n8nPuSg29Wyn8hY2RyLNAAzk1kXUpi9ut3EZSURX1hsM7srdrzKoj-S001 | H28: 1 | I28: 2 | J28: 1 | K28: Tadahiro Itou (伊藤 忠洋) | L28: DM | N28: [カテゴリ選択] | O28: 0 | P28: 0 | Q28: 1 | R28: 0 | S28: 46162.003 | T28: 46162.003 | U28: 46162.378 | V28: 46162.378 | W28: 0 | Z28: 制度・運用 | AB28: 制度・運用 | AC28: user_selected | AD28: 0 | AF28: 0 | AG28: 0 | AH28: 0 | AI28: 0 | AJ28: 0 | AL28: 0 | AM28: 0 | AN28: 0 | BT28: 0 | BU28: 0 | BZ28: 0 | CA28: 0 | CB28: 20260520T090340-20260520T210308.csv | CC28: 1 | CD28: user | CE28: 1.0.0 | CH28: =IF(OR(CG28="①", CG28="⑤"), "〇", "×") | CI28: =IF(OR(AND($CT28<>"",ISNUMBER(SEARCH($CT28, AP28))),AND($CU28<>"",ISNUMBER(SEARCH($CU28, AP28))),AND($CV28<>"",ISNUMBER(SEARCH($CV28, AP28)))),"〇","-") | CJ28: =IF(OR(AND($CT28<>"",ISNUMBER(SEARCH($CT28, AS28))),AND($CU28<>"",ISNUMBER(SEARCH($CU28, AS28))),AND($CV28<>"",ISNUMBER(SEARCH($CV28, AS28)))),"〇","-") | CK28: =IF(OR(AND($CT28<>"",ISNUMBER(SEARCH($CT28, AV28))),AND($CU28<>"",ISNUMBER(SEARCH($CU28, AV28))),AND($CV28<>"",ISNUMBER(SEARCH($CV28, AV28)))),"〇","-") | CL28: =IF(OR(AND($CT28<>"",ISNUMBER(SEARCH($CT28, AY28))),AND($CU28<>"",ISNUMBER(SEARCH($CU28, AY28))),AND($CV28<>"",ISNUMBER(SEARCH($CV28, AY28)))),"〇","-") | CM28: =IF(OR(AND($CT28<>"",ISNUMBER(SEARCH($CT28, BB28))),AND($CU28<>"",ISNUMBER(SEARCH($CU28, BB28))),AND($CV28<>"",ISNUMBER(SEARCH($CV28, BB28)))),"〇","-") | CN28: =IF(OR(AND($CT28<>"",ISNUMBER(SEARCH($CT28, BE28))),AND($CU28<>"",ISNUMBER(SEARCH($CU28, BE28))),AND($CV28<>"",ISNUMBER(SEARCH($CV28, BE28)))),"〇","-") | CO28: =IF(OR(AND($CT28<>"",ISNUMBER(SEARCH($CT28, BH28))),AND($CU28<>"",ISNUMBER(SEARCH($CU28, BH28))),AND($CV28<>"",ISNUMBER(SEARCH($CV28, BH28)))),"〇","-") | CP28: =IF(OR(AND($CT28<>"",ISNUMBER(SEARCH($CT28, BK28))),AND($CU28<>"",ISNUMBER(SEARCH($CU28, BK28))),AND($CV28<>"",ISNUMBER(SEARCH($CV28, BK28)))),"〇","-") | CQ28: =IF(OR(AND($CT28<>"",ISNUMBER(SEARCH($CT28, BN28))),AND($CU28<>"",ISNUMBER(SEARCH($CU28, BN28))),AND($CV28<>"",ISNUMBER(SEARCH($CV28, BN28)))),"〇","-") | CR28: =IF(OR(AND($CT28<>"",ISNUMBER(SEARCH($CT28, BQ28))),AND($CU28<>"",ISNUMBER(SEARCH($CU28, BQ28))),AND($CV28<>"",ISNUMBER(SEARCH($CV28, BQ28)))),"〇","-") | CW28: =IF(OR(CI28="〇",CJ28="〇",CK28="〇",CL28="〇",CM28="〇",CN28="〇",CO28="〇",CP28="〇",CQ28="〇",CR28="〇"),"〇","") | DE28: =TEXT(U28,"yyyy/mm/dd") | DF28: =VLOOKUP(K28,社員マスタ!C:D,2,0) | DG28: f:a6718c3e-0a1b-2db8-a0b4-be641325c124
B29: a:1Wue-93ng9YNfWzk9JEWBn6LbFbUsTkiYbOCjpT5XzQYYFlvbVEVdr0no5pUfMMvGlzqKQcuAtJ6n8nPuSg29Wyn8hY2RyLNAAzk1kXUpi9ut3EZSURX1hsM7srdrzKoj-f:3429b0ad-8fc8-bbec-06c5-5e45edc56783-FB000 | C29: =ROW(A29)-3 | D29: a:1Wue-93ng9YNfWzk9JEWBn6LbFbUsTkiYbOCjpT5XzQYYFlvbVEVdr0no5pUfMMvGlzqKQcuAtJ6n8nPuSg29Wyn8hY2RyLNAAzk1kXUpi9ut3EZSURX1hsM7srdrzKoj-f:3429b0ad-8fc8-bbec-06c5-5e45edc56783 | E29: f:3429b0ad-8fc8-bbec-06c5-5e45edc56783 | F29: a:1Wue-93ng9YNfWzk9JEWBn6LbFbUsTkiYbOCjpT5XzQYYFlvbVEVdr0no5pUfMMvGlzqKQcuAtJ6n8nPuSg29Wyn8hY2RyLNAAzk1kXUpi9ut3EZSURX1hsM7srdrzKoj | G29: a:1Wue-93ng9YNfWzk9JEWBn6LbFbUsTkiYbOCjpT5XzQYYFlvbVEVdr0no5pUfMMvGlzqKQcuAtJ6n8nPuSg29Wyn8hY2RyLNAAzk1kXUpi9ut3EZSURX1hsM7srdrzKoj-S001 | H29: 1 | I29: 3 | J29: 1 | K29: Tadahiro Itou (伊藤 忠洋) | L29: DM | N29: [カテゴリ選択] | O29: 0 | P29: 0 | Q29: 1 | R29: 0 | S29: 46162.003 | T29: 46162.003 | U29: 46162.378 | V29: 46162.378 | W29: 0 | Z29: 制度・運用 > 通勤費 | AB29: 制度・運用 > 通勤費 | AC29: user_selected | AD29: 0 | AF29: 0 | AG29: 0 | AH29: 0 | AI29: 0 | AJ29: 0 | AL29: 0 | AM29: 0 | AN29: 0 | BT29: 0 | BU29: 0 | BZ29: 0 | CA29: 0 | CB29: 20260520T090340-20260520T210308.csv | CC29: 1 | CD29: user | CE29: 1.0.0 | CH29: =IF(OR(CG29="①", CG29="⑤"), "〇", "×") | CI29: =IF(OR(AND($CT29<>"",ISNUMBER(SEARCH($CT29, AP29))),AND($CU29<>"",ISNUMBER(SEARCH($CU29, AP29))),AND($CV29<>"",ISNUMBER(SEARCH($CV29, AP29)))),"〇","-") | CJ29: =IF(OR(AND($CT29<>"",ISNUMBER(SEARCH($CT29, AS29))),AND($CU29<>"",ISNUMBER(SEARCH($CU29, AS29))),AND($CV29<>"",ISNUMBER(SEARCH($CV29, AS29)))),"〇","-") | CK29: =IF(OR(AND($CT29<>"",ISNUMBER(SEARCH($CT29, AV29))),AND($CU29<>"",ISNUMBER(SEARCH($CU29, AV29))),AND($CV29<>"",ISNUMBER(SEARCH($CV29, AV29)))),"〇","-") | CL29: =IF(OR(AND($CT29<>"",ISNUMBER(SEARCH($CT29, AY29))),AND($CU29<>"",ISNUMBER(SEARCH($CU29, AY29))),AND($CV29<>"",ISNUMBER(SEARCH($CV29, AY29)))),"〇","-") | CM29: =IF(OR(AND($CT29<>"",ISNUMBER(SEARCH($CT29, BB29))),AND($CU29<>"",ISNUMBER(SEARCH($CU29, BB29))),AND($CV29<>"",ISNUMBER(SEARCH($CV29, BB29)))),"〇","-") | CN29: =IF(OR(AND($CT29<>"",ISNUMBER(SEARCH($CT29, BE29))),AND($CU29<>"",ISNUMBER(SEARCH($CU29, BE29))),AND($CV29<>"",ISNUMBER(SEARCH($CV29, BE29)))),"〇","-") | CO29: =IF(OR(AND($CT29<>"",ISNUMBER(SEARCH($CT29, BH29))),AND($CU29<>"",ISNUMBER(SEARCH($CU29, BH29))),AND($CV29<>"",ISNUMBER(SEARCH($CV29, BH29)))),"〇","-") | CP29: =IF(OR(AND($CT29<>"",ISNUMBER(SEARCH($CT29, BK29))),AND($CU29<>"",ISNUMBER(SEARCH($CU29, BK29))),AND($CV29<>"",ISNUMBER(SEARCH($CV29, BK29)))),"〇","-") | CQ29: =IF(OR(AND($CT29<>"",ISNUMBER(SEARCH($CT29, BN29))),AND($CU29<>"",ISNUMBER(SEARCH($CU29, BN29))),AND($CV29<>"",ISNUMBER(SEARCH($CV29, BN29)))),"〇","-") | CR29: =IF(OR(AND($CT29<>"",ISNUMBER(SEARCH($CT29, BQ29))),AND($CU29<>"",ISNUMBER(SEARCH($CU29, BQ29))),AND($CV29<>"",ISNUMBER(SEARCH($CV29, BQ29)))),"〇","-") | CW29: =IF(OR(CI29="〇",CJ29="〇",CK29="〇",CL29="〇",CM29="〇",CN29="〇",CO29="〇",CP29="〇",CQ29="〇",CR29="〇"),"〇","") | DE29: =TEXT(U29,"yyyy/mm/dd") | DF29: =VLOOKUP(K29,社員マスタ!C:D,2,0) | DG29: f:3429b0ad-8fc8-bbec-06c5-5e45edc56783
B30: a:1Y-rUFLxiFRxcUHusDXmAnAfGBYZa4SsfTm9bIJnI4x0JcKLlMLgQOj4ZKB0AYPK93ybfFGfglVMtUpf96UwI9awdUI_WVcNTh2NwGctDZrjgaRs2t81Xt1uShLlRNiD1-1779236857582-FB000 | C30: =ROW(A30)-3 | D30: a:1Y-rUFLxiFRxcUHusDXmAnAfGBYZa4SsfTm9bIJnI4x0JcKLlMLgQOj4ZKB0AYPK93ybfFGfglVMtUpf96UwI9awdUI_WVcNTh2NwGctDZrjgaRs2t81Xt1uShLlRNiD1-1779236857582 | E30: 1779236857582 | F30: a:1Y-rUFLxiFRxcUHusDXmAnAfGBYZa4SsfTm9bIJnI4x0JcKLlMLgQOj4ZKB0AYPK93ybfFGfglVMtUpf96UwI9awdUI_WVcNTh2NwGctDZrjgaRs2t81Xt1uShLlRNiD1 | G30: a:1Y-rUFLxiFRxcUHusDXmAnAfGBYZa4SsfTm9bIJnI4x0JcKLlMLgQOj4ZKB0AYPK93ybfFGfglVMtUpf96UwI9awdUI_WVcNTh2NwGctDZrjgaRs2t81Xt1uShLlRNiD1-S001 | H30: 1 | I30: 1 | J30: 1 | K30: Nana Ookawara (大河原 奈那) | L30: DM | N30: カテゴリ | O30: 0 | P30: 0 | Q30: 0 | R30: 1 | S30: 46162.019 | T30: 46162.019 | U30: 46162.394 | V30: 46162.394 | W30: 0 | AB30: 未分類 | AC30: none | AD30: 1 | AF30: 0 | AG30: 0 | AH30: 0 | AI30: 0 | AJ30: 0 | AL30: 0 | AM30: 0 | AN30: 0 | BT30: 0 | BU30: 0 | BZ30: 0 | CA30: 0 | CB30: 20260520T090340-20260520T210308.csv | CC30: 1 | CD30: user | CE30: 1.0.0 | CF30: no answer found | CH30: =IF(OR(CG30="①", CG30="⑤"), "〇", "×") | CI30: =IF(OR(AND($CT30<>"",ISNUMBER(SEARCH($CT30, AP30))),AND($CU30<>"",ISNUMBER(SEARCH($CU30, AP30))),AND($CV30<>"",ISNUMBER(SEARCH($CV30, AP30)))),"〇","-") | CJ30: =IF(OR(AND($CT30<>"",ISNUMBER(SEARCH($CT30, AS30))),AND($CU30<>"",ISNUMBER(SEARCH($CU30, AS30))),AND($CV30<>"",ISNUMBER(SEARCH($CV30, AS30)))),"〇","-") | CK30: =IF(OR(AND($CT30<>"",ISNUMBER(SEARCH($CT30, AV30))),AND($CU30<>"",ISNUMBER(SEARCH($CU30, AV30))),AND($CV30<>"",ISNUMBER(SEARCH($CV30, AV30)))),"〇","-") | CL30: =IF(OR(AND($CT30<>"",ISNUMBER(SEARCH($CT30, AY30))),AND($CU30<>"",ISNUMBER(SEARCH($CU30, AY30))),AND($CV30<>"",ISNUMBER(SEARCH($CV30, AY30)))),"〇","-") | CM30: =IF(OR(AND($CT30<>"",ISNUMBER(SEARCH($CT30, BB30))),AND($CU30<>"",ISNUMBER(SEARCH($CU30, BB30))),AND($CV30<>"",ISNUMBER(SEARCH($CV30, BB30)))),"〇","-") | CN30: =IF(OR(AND($CT30<>"",ISNUMBER(SEARCH($CT30, BE30))),AND($CU30<>"",ISNUMBER(SEARCH($CU30, BE30))),AND($CV30<>"",ISNUMBER(SEARCH($CV30, BE30)))),"〇","-") | CO30: =IF(OR(AND($CT30<>"",ISNUMBER(SEARCH($CT30, BH30))),AND($CU30<>"",ISNUMBER(SEARCH($CU30, BH30))),AND($CV30<>"",ISNUMBER(SEARCH($CV30, BH30)))),"〇","-") | CP30: =IF(OR(AND($CT30<>"",ISNUMBER(SEARCH($CT30, BK30))),AND($CU30<>"",ISNUMBER(SEARCH($CU30, BK30))),AND($CV30<>"",ISNUMBER(SEARCH($CV30, BK30)))),"〇","-") | CQ30: =IF(OR(AND($CT30<>"",ISNUMBER(SEARCH($CT30, BN30))),AND($CU30<>"",ISNUMBER(SEARCH($CU30, BN30))),AND($CV30<>"",ISNUMBER(SEARCH($CV30, BN30)))),"〇","-") | CR30: =IF(OR(AND($CT30<>"",ISNUMBER(SEARCH($CT30, BQ30))),AND($CU30<>"",ISNUMBER(SEARCH($CU30, BQ30))),AND($CV30<>"",ISNUMBER(SEARCH($CV30, BQ30)))),"〇","-") | CW30: =IF(OR(CI30="〇",CJ30="〇",CK30="〇",CL30="〇",CM30="〇",CN30="〇",CO30="〇",CP30="〇",CQ30="〇",CR30="〇"),"〇","") | DE30: =TEXT(U30,"yyyy/mm/dd") | DF30: =VLOOKUP(K30,社員マスタ!C:D,2,0) | DG30: 1779236857582
B31: a:1Y-rUFLxiFRxcUHusDXmAnAfGBYZa4SsfTm9bIJnI4x0JcKLlMLgQOj4ZKB0AYPK93ybfFGfglVMtUpf96UwI9awdUI_WVcNTh2NwGctDZrjgaRs2t81Xt1uShLlRNiD1-f:fc105948-c7fe-014a-bd0d-fcaa474df1bd-FB000 | C31: =ROW(A31)-3 | D31: a:1Y-rUFLxiFRxcUHusDXmAnAfGBYZa4SsfTm9bIJnI4x0JcKLlMLgQOj4ZKB0AYPK93ybfFGfglVMtUpf96UwI9awdUI_WVcNTh2NwGctDZrjgaRs2t81Xt1uShLlRNiD1-f:fc105948-c7fe-014a-bd0d-fcaa474df1bd | E31: f:fc105948-c7fe-014a-bd0d-fcaa474df1bd | F31: a:1Y-rUFLxiFRxcUHusDXmAnAfGBYZa4SsfTm9bIJnI4x0JcKLlMLgQOj4ZKB0AYPK93ybfFGfglVMtUpf96UwI9awdUI_WVcNTh2NwGctDZrjgaRs2t81Xt1uShLlRNiD1 | G31: a:1Y-rUFLxiFRxcUHusDXmAnAfGBYZa4SsfTm9bIJnI4x0JcKLlMLgQOj4ZKB0AYPK93ybfFGfglVMtUpf96UwI9awdUI_WVcNTh2NwGctDZrjgaRs2t81Xt1uShLlRNiD1-S001 | H31: 1 | I31: 2 | J31: 1 | K31: Nana Ookawara (大河原 奈那) | L31: DM | N31: [カテゴリ選択] | O31: 0 | P31: 0 | Q31: 1 | R31: 0 | S31: 46162.019 | T31: 46162.019 | U31: 46162.394 | V31: 46162.394 | W31: 0 | Z31: 制度・運用 | AB31: 制度・運用 | AC31: user_selected | AD31: 0 | AF31: 0 | AG31: 0 | AH31: 0 | AI31: 0 | AJ31: 0 | AL31: 0 | AM31: 0 | AN31: 0 | BT31: 0 | BU31: 0 | BZ31: 0 | CA31: 0 | CB31: 20260520T090340-20260520T210308.csv | CC31: 1 | CD31: user | CE31: 1.0.0 | CH31: =IF(OR(CG31="①", CG31="⑤"), "〇", "×") | CI31: =IF(OR(AND($CT31<>"",ISNUMBER(SEARCH($CT31, AP31))),AND($CU31<>"",ISNUMBER(SEARCH($CU31, AP31))),AND($CV31<>"",ISNUMBER(SEARCH($CV31, AP31)))),"〇","-") | CJ31: =IF(OR(AND($CT31<>"",ISNUMBER(SEARCH($CT31, AS31))),AND($CU31<>"",ISNUMBER(SEARCH($CU31, AS31))),AND($CV31<>"",ISNUMBER(SEARCH($CV31, AS31)))),"〇","-") | CK31: =IF(OR(AND($CT31<>"",ISNUMBER(SEARCH($CT31, AV31))),AND($CU31<>"",ISNUMBER(SEARCH($CU31, AV31))),AND($CV31<>"",ISNUMBER(SEARCH($CV31, AV31)))),"〇","-") | CL31: =IF(OR(AND($CT31<>"",ISNUMBER(SEARCH($CT31, AY31))),AND($CU31<>"",ISNUMBER(SEARCH($CU31, AY31))),AND($CV31<>"",ISNUMBER(SEARCH($CV31, AY31)))),"〇","-") | CM31: =IF(OR(AND($CT31<>"",ISNUMBER(SEARCH($CT31, BB31))),AND($CU31<>"",ISNUMBER(SEARCH($CU31, BB31))),AND($CV31<>"",ISNUMBER(SEARCH($CV31, BB31)))),"〇","-") | CN31: =IF(OR(AND($CT31<>"",ISNUMBER(SEARCH($CT31, BE31))),AND($CU31<>"",ISNUMBER(SEARCH($CU31, BE31))),AND($CV31<>"",ISNUMBER(SEARCH($CV31, BE31)))),"〇","-") | CO31: =IF(OR(AND($CT31<>"",ISNUMBER(SEARCH($CT31, BH31))),AND($CU31<>"",ISNUMBER(SEARCH($CU31, BH31))),AND($CV31<>"",ISNUMBER(SEARCH($CV31, BH31)))),"〇","-") | CP31: =IF(OR(AND($CT31<>"",ISNUMBER(SEARCH($CT31, BK31))),AND($CU31<>"",ISNUMBER(SEARCH($CU31, BK31))),AND($CV31<>"",ISNUMBER(SEARCH($CV31, BK31)))),"〇","-") | CQ31: =IF(OR(AND($CT31<>"",ISNUMBER(SEARCH($CT31, BN31))),AND($CU31<>"",ISNUMBER(SEARCH($CU31, BN31))),AND($CV31<>"",ISNUMBER(SEARCH($CV31, BN31)))),"〇","-") | CR31: =IF(OR(AND($CT31<>"",ISNUMBER(SEARCH($CT31, BQ31))),AND($CU31<>"",ISNUMBER(SEARCH($CU31, BQ31))),AND($CV31<>"",ISNUMBER(SEARCH($CV31, BQ31)))),"〇","-") | CW31: =IF(OR(CI31="〇",CJ31="〇",CK31="〇",CL31="〇",CM31="〇",CN31="〇",CO31="〇",CP31="〇",CQ31="〇",CR31="〇"),"〇","") | DE31: =TEXT(U31,"yyyy/mm/dd") | DF31: =VLOOKUP(K31,社員マスタ!C:D,2,0) | DG31: f:fc105948-c7fe-014a-bd0d-fcaa474df1bd
B32: a:1Y-rUFLxiFRxcUHusDXmAnAfGBYZa4SsfTm9bIJnI4x0JcKLlMLgQOj4ZKB0AYPK93ybfFGfglVMtUpf96UwI9awdUI_WVcNTh2NwGctDZrjgaRs2t81Xt1uShLlRNiD1-f:71100c4f-7c46-ac08-adcb-c1c790e72ae5-FB000 | C32: =ROW(A32)-3 | D32: a:1Y-rUFLxiFRxcUHusDXmAnAfGBYZa4SsfTm9bIJnI4x0JcKLlMLgQOj4ZKB0AYPK93ybfFGfglVMtUpf96UwI9awdUI_WVcNTh2NwGctDZrjgaRs2t81Xt1uShLlRNiD1-f:71100c4f-7c46-ac08-adcb-c1c790e72ae5 | E32: f:71100c4f-7c46-ac08-adcb-c1c790e72ae5 | F32: a:1Y-rUFLxiFRxcUHusDXmAnAfGBYZa4SsfTm9bIJnI4x0JcKLlMLgQOj4ZKB0AYPK93ybfFGfglVMtUpf96UwI9awdUI_WVcNTh2NwGctDZrjgaRs2t81Xt1uShLlRNiD1 | G32: a:1Y-rUFLxiFRxcUHusDXmAnAfGBYZa4SsfTm9bIJnI4x0JcKLlMLgQOj4ZKB0AYPK93ybfFGfglVMtUpf96UwI9awdUI_WVcNTh2NwGctDZrjgaRs2t81Xt1uShLlRNiD1-S001 | H32: 1 | I32: 3 | J32: 1 | K32: Nana Ookawara (大河原 奈那) | L32: DM | N32: [カテゴリ選択] | O32: 0 | P32: 0 | Q32: 1 | R32: 0 | S32: 46162.019 | T32: 46162.019 | U32: 46162.394 | V32: 46162.394 | W32: 0 | Z32: 制度・運用 > 服務 | AB32: 制度・運用 > 服務 | AC32: user_selected | AD32: 0 | AF32: 0 | AG32: 0 | AH32: 0 | AI32: 0 | AJ32: 0 | AL32: 0 | AM32: 0 | AN32: 0 | BT32: 0 | BU32: 0 | BZ32: 0 | CA32: 0 | CB32: 20260520T090340-20260520T210308.csv | CC32: 1 | CD32: user | CE32: 1.0.0 | CH32: =IF(OR(CG32="①", CG32="⑤"), "〇", "×") | CI32: =IF(OR(AND($CT32<>"",ISNUMBER(SEARCH($CT32, AP32))),AND($CU32<>"",ISNUMBER(SEARCH($CU32, AP32))),AND($CV32<>"",ISNUMBER(SEARCH($CV32, AP32)))),"〇","-") | CJ32: =IF(OR(AND($CT32<>"",ISNUMBER(SEARCH($CT32, AS32))),AND($CU32<>"",ISNUMBER(SEARCH($CU32, AS32))),AND($CV32<>"",ISNUMBER(SEARCH($CV32, AS32)))),"〇","-") | CK32: =IF(OR(AND($CT32<>"",ISNUMBER(SEARCH($CT32, AV32))),AND($CU32<>"",ISNUMBER(SEARCH($CU32, AV32))),AND($CV32<>"",ISNUMBER(SEARCH($CV32, AV32)))),"〇","-") | CL32: =IF(OR(AND($CT32<>"",ISNUMBER(SEARCH($CT32, AY32))),AND($CU32<>"",ISNUMBER(SEARCH($CU32, AY32))),AND($CV32<>"",ISNUMBER(SEARCH($CV32, AY32)))),"〇","-") | CM32: =IF(OR(AND($CT32<>"",ISNUMBER(SEARCH($CT32, BB32))),AND($CU32<>"",ISNUMBER(SEARCH($CU32, BB32))),AND($CV32<>"",ISNUMBER(SEARCH($CV32, BB32)))),"〇","-") | CN32: =IF(OR(AND($CT32<>"",ISNUMBER(SEARCH($CT32, BE32))),AND($CU32<>"",ISNUMBER(SEARCH($CU32, BE32))),AND($CV32<>"",ISNUMBER(SEARCH($CV32, BE32)))),"〇","-") | CO32: =IF(OR(AND($CT32<>"",ISNUMBER(SEARCH($CT32, BH32))),AND($CU32<>"",ISNUMBER(SEARCH($CU32, BH32))),AND($CV32<>"",ISNUMBER(SEARCH($CV32, BH32)))),"〇","-") | CP32: =IF(OR(AND($CT32<>"",ISNUMBER(SEARCH($CT32, BK32))),AND($CU32<>"",ISNUMBER(SEARCH($CU32, BK32))),AND($CV32<>"",ISNUMBER(SEARCH($CV32, BK32)))),"〇","-") | CQ32: =IF(OR(AND($CT32<>"",ISNUMBER(SEARCH($CT32, BN32))),AND($CU32<>"",ISNUMBER(SEARCH($CU32, BN32))),AND($CV32<>"",ISNUMBER(SEARCH($CV32, BN32)))),"〇","-") | CR32: =IF(OR(AND($CT32<>"",ISNUMBER(SEARCH($CT32, BQ32))),AND($CU32<>"",ISNUMBER(SEARCH($CU32, BQ32))),AND($CV32<>"",ISNUMBER(SEARCH($CV32, BQ32)))),"〇","-") | CW32: =IF(OR(CI32="〇",CJ32="〇",CK32="〇",CL32="〇",CM32="〇",CN32="〇",CO32="〇",CP32="〇",CQ32="〇",CR32="〇"),"〇","") | DE32: =TEXT(U32,"yyyy/mm/dd") | DF32: =VLOOKUP(K32,社員マスタ!C:D,2,0) | DG32: f:71100c4f-7c46-ac08-adcb-c1c790e72ae5
B33: a:1npCU6m2UxvDQcZBCfdev4cJRITeoJQIubrBb1T4CT_iPrFGFV1JT7WT6tXk7tY4n-Q_On0IxtZLPxTSasHTjohVXzS4nmpKjT9q-IxQIIwMdBenvykvCkXZ89w5HogsW-1779237396168-FB000 | C33: =ROW(A33)-3 | D33: a:1npCU6m2UxvDQcZBCfdev4cJRITeoJQIubrBb1T4CT_iPrFGFV1JT7WT6tXk7tY4n-Q_On0IxtZLPxTSasHTjohVXzS4nmpKjT9q-IxQIIwMdBenvykvCkXZ89w5HogsW-1779237396168 | E33: 1779237396168 | F33: a:1npCU6m2UxvDQcZBCfdev4cJRITeoJQIubrBb1T4CT_iPrFGFV1JT7WT6tXk7tY4n-Q_On0IxtZLPxTSasHTjohVXzS4nmpKjT9q-IxQIIwMdBenvykvCkXZ89w5HogsW | G33: a:1npCU6m2UxvDQcZBCfdev4cJRITeoJQIubrBb1T4CT_iPrFGFV1JT7WT6tXk7tY4n-Q_On0IxtZLPxTSasHTjohVXzS4nmpKjT9q-IxQIIwMdBenvykvCkXZ89w5HogsW-S001 | H33: 1 | I33: 1 | J33: 1 | K33: Shin Nakamura (中村 伸) | L33: DM | M33: YourNaviとはなんですか | N33: YourNaviとはなんですか | O33: 1 | P33: 0 | Q33: 0 | R33: 0 | S33: 46162.025 | T33: 46162.025 | U33: 46162.4 | V33: 46162.4 | W33: 4.992 | X33: searchEmployeeRules | Y33: 未分類 | AA33: 未分類 | AB33: 未分類 | AC33: predicted | AD33: 1 | AE33: YourNaviについて、検索結果から直接的な説明は見つかりませんでしたが、利用開始時は資料を見て進める形であることが確認できます。 もし具体的な機能や目的について知りたい場合は、追加で質問していただければ、分かる範囲でご案内します。 ※AIの回答は必ずしも正確ではありません。参照情報も確認いただき、最終判断は所属部署の公式情報をご確認ください。 | AF33: 1 | AG33: 0 | AH33: 3 | AI33: 0 | AJ33: 0 | AL33: 4 | AM33: 4 | AN33: 0 | AO33: QA69_policy-operations_benefits_benefits-others.md | AP33: 質問 資料を見て利用開始するという理解で合っていますか。 回答 ご認識の通りです。 | AQ33: 0.9070548 | AR33: QA622_system_talemane_talemane-employee.md | AS33: 質問 アノテーションが表示されない場合、どうしたらいいでしょうか。 回答 アノテーションが表示されない場合は以下URLをご確認ください。 https://www.hdservice1.nttls.co.jp/hc/ja/articles/17310663546647 | AT33: 0.9007736 | AU33: QA598_system_talemane_talemane-employee.md | AV33: 質問 自己PR欄の記入方法を教えてください。 回答 自己PR欄の記入方法は以下URLをご確認ください。 https://www.hdservice1.nttls.co.jp/hc/ja/articles/24749933723927 | AW33: 0.9070548 | AX33: QA593_system_talemane_talemane-employee.md | AY33: 質問 略歴(NTTグループ内経歴)に欠落・誤りがある場合、どうしたらいいでしょうか。 回答 略歴(NTTグループ内経歴)に欠落・誤りがある場合は以下URLをご確認ください。 https://www.hdservice1.nttls.co.jp/hc/ja/articles/360060677274 | AZ33: 0.9120841 | BT33: 0 | BU33: 0 | BZ33: 0 | CA33: 0 | CB33: 20260520T090340-20260520T210308.csv | CC33: 5 | CD33: user > assistant > assistant > tool > assistant | CE33: 1.0.0 | CH33: =IF(OR(CG33="①", CG33="⑤"), "〇", "×") | CI33: =IF(OR(AND($CT33<>"",ISNUMBER(SEARCH($CT33, AP33))),AND($CU33<>"",ISNUMBER(SEARCH($CU33, AP33))),AND($CV33<>"",ISNUMBER(SEARCH($CV33, AP33)))),"〇","-") | CJ33: =IF(OR(AND($CT33<>"",ISNUMBER(SEARCH($CT33, AS33))),AND($CU33<>"",ISNUMBER(SEARCH($CU33, AS33))),AND($CV33<>"",ISNUMBER(SEARCH($CV33, AS33)))),"〇","-") | CK33: =IF(OR(AND($CT33<>"",ISNUMBER(SEARCH($CT33, AV33))),AND($CU33<>"",ISNUMBER(SEARCH($CU33, AV33))),AND($CV33<>"",ISNUMBER(SEARCH($CV33, AV33)))),"〇","-") | CL33: =IF(OR(AND($CT33<>"",ISNUMBER(SEARCH($CT33, AY33))),AND($CU33<>"",ISNUMBER(SEARCH($CU33, AY33))),AND($CV33<>"",ISNUMBER(SEARCH($CV33, AY33)))),"〇","-") | CM33: =IF(OR(AND($CT33<>"",ISNUMBER(SEARCH($CT33, BB33))),AND($CU33<>"",ISNUMBER(SEARCH($CU33, BB33))),AND($CV33<>"",ISNUMBER(SEARCH($CV33, BB33)))),"〇","-") | CN33: =IF(OR(AND($CT33<>"",ISNUMBER(SEARCH($CT33, BE33))),AND($CU33<>"",ISNUMBER(SEARCH($CU33, BE33))),AND($CV33<>"",ISNUMBER(SEARCH($CV33, BE33)))),"〇","-") | CO33: =IF(OR(AND($CT33<>"",ISNUMBER(SEARCH($CT33, BH33))),AND($CU33<>"",ISNUMBER(SEARCH($CU33, BH33))),AND($CV33<>"",ISNUMBER(SEARCH($CV33, BH33)))),"〇","-") | CP33: =IF(OR(AND($CT33<>"",ISNUMBER(SEARCH($CT33, BK33))),AND($CU33<>"",ISNUMBER(SEARCH($CU33, BK33))),AND($CV33<>"",ISNUMBER(SEARCH($CV33, BK33)))),"〇","-") | CQ33: =IF(OR(AND($CT33<>"",ISNUMBER(SEARCH($CT33, BN33))),AND($CU33<>"",ISNUMBER(SEARCH($CU33, BN33))),AND($CV33<>"",ISNUMBER(SEARCH($CV33, BN33)))),"〇","-") | CR33: =IF(OR(AND($CT33<>"",ISNUMBER(SEARCH($CT33, BQ33))),AND($CU33<>"",ISNUMBER(SEARCH($CU33, BQ33))),AND($CV33<>"",ISNUMBER(SEARCH($CV33, BQ33)))),"〇","-") | CW33: =IF(OR(CI33="〇",CJ33="〇",CK33="〇",CL33="〇",CM33="〇",CN33="〇",CO33="〇",CP33="〇",CQ33="〇",CR33="〇"),"〇","") | DE33: =TEXT(U33,"yyyy/mm/dd") | DF33: =VLOOKUP(K33,社員マスタ!C:D,2,0) | DG33: 1779237396168
B34: a:1PhxF6LfNBn-dJs9ZFIdmP1DhKmY4JHXidWI3tLy5N5wa8kE4qHffqdKFa0bF23-8JqAhxGULrGfCCJMPunC3EGqom9vNJRnYZ7qWxmVbayyQBsLEJwhD2hCH7nSeaj46-1779238074172-FB000 | C34: =ROW(A34)-3 | D34: a:1PhxF6LfNBn-dJs9ZFIdmP1DhKmY4JHXidWI3tLy5N5wa8kE4qHffqdKFa0bF23-8JqAhxGULrGfCCJMPunC3EGqom9vNJRnYZ7qWxmVbayyQBsLEJwhD2hCH7nSeaj46-1779238074172 | E34: 1779238074172 | F34: a:1PhxF6LfNBn-dJs9ZFIdmP1DhKmY4JHXidWI3tLy5N5wa8kE4qHffqdKFa0bF23-8JqAhxGULrGfCCJMPunC3EGqom9vNJRnYZ7qWxmVbayyQBsLEJwhD2hCH7nSeaj46 | G34: a:1PhxF6LfNBn-dJs9ZFIdmP1DhKmY4JHXidWI3tLy5N5wa8kE4qHffqdKFa0bF23-8JqAhxGULrGfCCJMPunC3EGqom9vNJRnYZ7qWxmVbayyQBsLEJwhD2hCH7nSeaj46-S001 | H34: 1 | I34: 1 | J34: 1 | K34: Kenji Miyakoshi (宮越 健二) | L34: DM | M34: 回線業務について | N34: 回線業務について | O34: 1 | P34: 0 | Q34: 0 | R34: 0 | S34: 46162.033 | T34: 46162.033 | U34: 46162.408 | V34: 46162.408 | W34: 5.733 | X34: searchEmployeeRules | Y34: 未分類 | AA34: 未分類 | AB34: 未分類 | AC34: predicted | AD34: 1 | AE34: 回線業務に関連する主なポイントは以下の通りです。 - リモートワーク時の通信費やプロバイダ利用料、光熱費などは自己負担となります。 - 業務上必要な場合、会社から端末や携帯電話が貸与されることがあります。 - リモートワークの実施場所までの交通費は、必要と認められた場合に旅費規程に基づき支給されます。 - 通信の秘密に関わる情報（通話明細や通信履歴、通話料金など）は厳重に管理され、情報管理規程等に従う必要があります。 - 法人顧客の機密情報や完了案件情報も慎重に取り扱う必要があります。 業務の詳細や取り扱いについては、情報管理規程や旅費規程などの社内規則に従って対応してください。 ※AIの回答は必ずしも正確ではありません。参照情報も確認いただき、最終判断は所属部署の公式情報をご確認ください。 | AF34: 1 | AG34: 0 | AH34: 3 | AI34: 0 | AJ34: 0 | AL34: 4 | AM34: 4 | AN34: 0 | AO34: QA218_policy-operations_commute-costs_com-others.md | AP34: 質問 リモートワークが多いので通勤費申請（RSの場合は標準的出社経路申請）はしばらく実施しなくても大丈夫ですか。 回答 業務状況により急遽出社を命じられる可能性があるので、異動後または転居後、速やかに申請してください。 | AQ34: 0.9296705 | AR34: 36 社員の勤務時間、休日及び休暇について_202504.docx | AS34: ア 対象作業が4週間以内で終了する場合 （ア）概ね5時間労働以上の勤務を行う必要がある場合は、原則として臨時服務線により対処することとする。 （イ）臨時服務線は夜勤服務、深夜勤服務又は宿直宿明服務とする。 （ウ）臨時服務線の実施方法については勤務割変更の例により行う。 イ 対象作業が4週間をこえる場合 当該期間について宿直宿明輪番交替服務等、必要な服務形態により対処する。 なお、当該期間が4週間をこえる場合であっても、当該期間における業務計画に関わらず、夜勤服務等の実施が予定できない場合又は不定期である場合には、臨時服務線により対処 する。 ７ 服務線表の作成及び変更 | AT34: 0.92220998 | AU34: 49 リモートワークの取扱いについて_202511.docx | AV34: （１）通信の秘密に係る情報（通話明細/通信履歴/通話料金など） （２）法人顧客情報の内、機密情報（特に機密性が高く慎重に扱わなければいけない情報(通話明細/通信内容/DWHデータ/料金シミュレーション/大量の顧客情報 等)）および完了案件情報（機密情報を除き、お客様法人対応が完了した情報で、完了案件後も継続して保管する情報）にあたる情報 13．情報セキュリティ対策 （１）リモートワークにおいては、「情報管理規程」（2003年５月27日社長達第８号）、「情報管理細則（2003年５月27日総第1162号）及び「クライアントＰＣ管理マニュアル」（2010年１月21日情セ第768号）等の会社・組織が定める各種の規則・規程等に定める事項に従わなければならない。 （２）情報管理規程に定める「レベルＳ」「レベルＡ」「レベルＢ」に区分された管理情報の紙及び記憶媒体による持ち出しは、禁止する。 14．服務管理等 （１）社員等がリモートワークを実施するときは、日々、始業時刻・終業時刻、分断時間、休憩時間及び業務の実施状況を直属上長に報告するものとする。 （２）直属上長は、社員等のリモートワークの実施状況について、適切な管理を行うものとする。 15. リモートスタンダード リモートワークを基本とする業務遂行を行う働き方として、リモートスタンダードを設定し、リモートワークを基本とする業務運営が可能であると組織長が判断した場合において適用する。 なお、具体的な扱いについては、第２章のとおりとする。 | AW34: 0.9296705 | AX34: 49 リモートワークの取扱いについて_202511.docx | AY34: （１）直属上長は、前項の申出・変更・取消を社員等から受けたときは、リモートワークの実施等の事前に、承認の是非を判断のうえ、その旨を社員等に通知する。 なお、承認しないときは、理由を付して社員等に通知する。 （２）直属上長は、緊急時等社員等の出社が必要となった場合は、リモートワークを取り消すこと ができるものとし、社員等は速やかに出社しなければならない。 ９．リモートワークの指示等 直属上長は、業務上の必要性等の理由により勤務事業所以外でのリモートワークを命じる場合がある。 10．費用負担等 （１）リモートワークに使用する端末は会社貸与、または各種社内規程に基づき利用を許可された個人所有端末とし、業務上の必要により携帯電話等が貸与される場合がある。 （２）前１項を除く、通信費、プロバイダ利用料及び光熱費等のリモートワークに関わる費用については、社員等の自己負担とする。 （３）社員等が自宅、または単身赴任者の帰郷地以外でリモートワークを実施する場合、その実施場所までの交通費について必要と認められる場合は、「旅費規程」（1992年７月１日社長達第36号）（以下、「旅費規程」という）に基づき支給される。 11．リモートワーク手当 リモートワークを社員等の自宅、または単身赴任者の帰郷地で実施し、かつ、現実に労働した時間の合計が１日３時間以上の社員等を対象に、「社員給与規則」（1992年７月１日社長達第22号、以下「社員給与規則」という。）第７章に基づき、リモートワリモートワ―ク手当が支給される。 12．取り扱うことができない管理情報 （１）通信の秘密に係る情報（通話明細/通信履歴/通話料金など） （２）法人顧客情報の内、機密情報（特に機密性が高く慎重に扱わなければいけない情報(通話明細/通信内容/DWHデータ/料金シミュレーション/大量の顧客情報 等)）および完了案件情報（機密情報を除き、お客様法人対応が完了した情報で、完了案件後も継続して保管する情報）にあたる情報 13．情報セキュリティ対策 | AZ34: 0.91930917 | BT34: 0 | BU34: 0 | BZ34: 0 | CA34: 0 | CB34: 20260520T090340-20260520T210308.csv | CC34: 5 | CD34: user > assistant > assistant > tool > assistant | CE34: 1.0.0 | CH34: =IF(OR(CG34="①", CG34="⑤"), "〇", "×") | CI34: =IF(OR(AND($CT34<>"",ISNUMBER(SEARCH($CT34, AP34))),AND($CU34<>"",ISNUMBER(SEARCH($CU34, AP34))),AND($CV34<>"",ISNUMBER(SEARCH($CV34, AP34)))),"〇","-") | CJ34: =IF(OR(AND($CT34<>"",ISNUMBER(SEARCH($CT34, AS34))),AND($CU34<>"",ISNUMBER(SEARCH($CU34, AS34))),AND($CV34<>"",ISNUMBER(SEARCH($CV34, AS34)))),"〇","-") | CK34: =IF(OR(AND($CT34<>"",ISNUMBER(SEARCH($CT34, AV34))),AND($CU34<>"",ISNUMBER(SEARCH($CU34, AV34))),AND($CV34<>"",ISNUMBER(SEARCH($CV34, AV34)))),"〇","-") | CL34: =IF(OR(AND($CT34<>"",ISNUMBER(SEARCH($CT34, AY34))),AND($CU34<>"",ISNUMBER(SEARCH($CU34, AY34))),AND($CV34<>"",ISNUMBER(SEARCH($CV34, AY34)))),"〇","-") | CM34: =IF(OR(AND($CT34<>"",ISNUMBER(SEARCH($CT34, BB34))),AND($CU34<>"",ISNUMBER(SEARCH($CU34, BB34))),AND($CV34<>"",ISNUMBER(SEARCH($CV34, BB34)))),"〇","-") | CN34: =IF(OR(AND($CT34<>"",ISNUMBER(SEARCH($CT34, BE34))),AND($CU34<>"",ISNUMBER(SEARCH($CU34, BE34))),AND($CV34<>"",ISNUMBER(SEARCH($CV34, BE34)))),"〇","-") | CO34: =IF(OR(AND($CT34<>"",ISNUMBER(SEARCH($CT34, BH34))),AND($CU34<>"",ISNUMBER(SEARCH($CU34, BH34))),AND($CV34<>"",ISNUMBER(SEARCH($CV34, BH34)))),"〇","-") | CP34: =IF(OR(AND($CT34<>"",ISNUMBER(SEARCH($CT34, BK34))),AND($CU34<>"",ISNUMBER(SEARCH($CU34, BK34))),AND($CV34<>"",ISNUMBER(SEARCH($CV34, BK34)))),"〇","-") | CQ34: =IF(OR(AND($CT34<>"",ISNUMBER(SEARCH($CT34, BN34))),AND($CU34<>"",ISNUMBER(SEARCH($CU34, BN34))),AND($CV34<>"",ISNUMBER(SEARCH($CV34, BN34)))),"〇","-") | CR34: =IF(OR(AND($CT34<>"",ISNUMBER(SEARCH($CT34, BQ34))),AND($CU34<>"",ISNUMBER(SEARCH($CU34, BQ34))),AND($CV34<>"",ISNUMBER(SEARCH($CV34, BQ34)))),"〇","-") | CW34: =IF(OR(CI34="〇",CJ34="〇",CK34="〇",CL34="〇",CM34="〇",CN34="〇",CO34="〇",CP34="〇",CQ34="〇",CR34="〇"),"〇","") | DE34: =TEXT(U34,"yyyy/mm/dd") | DF34: =VLOOKUP(K34,社員マスタ!C:D,2,0) | DG34: 1779238074172
B35: a:12ratvcr2opxWviitasntE_WdKINffd6WG_gaBGYG23mTMIQae-Fdp0V5W-TesIh-KoweqmBTYRav7roLU7vTg7TPPDeQmRCt8UjUidNptaiW__-HLkjBDxMSpJfe98rq-1779241443841-FB000 | C35: =ROW(A35)-3 | D35: a:12ratvcr2opxWviitasntE_WdKINffd6WG_gaBGYG23mTMIQae-Fdp0V5W-TesIh-KoweqmBTYRav7roLU7vTg7TPPDeQmRCt8UjUidNptaiW__-HLkjBDxMSpJfe98rq-1779241443841 | E35: 1779241443841 | F35: a:12ratvcr2opxWviitasntE_WdKINffd6WG_gaBGYG23mTMIQae-Fdp0V5W-TesIh-KoweqmBTYRav7roLU7vTg7TPPDeQmRCt8UjUidNptaiW__-HLkjBDxMSpJfe98rq | G35: a:12ratvcr2opxWviitasntE_WdKINffd6WG_gaBGYG23mTMIQae-Fdp0V5W-TesIh-KoweqmBTYRav7roLU7vTg7TPPDeQmRCt8UjUidNptaiW__-HLkjBDxMSpJfe98rq-S001 | H35: 1 | I35: 1 | J35: 1 | K35: Shizuka Shirakata (白方 靜佳) | L35: DM | M35: 出張の交通費の申請方法が知りたい | N35: 出張の交通費の申請方法が知りたい | O35: 1 | P35: 0 | Q35: 0 | R35: 0 | S35: 46162.072 | T35: 46162.072 | U35: 46162.447 | V35: 46162.447 | W35: 10.314 | X35: searchEmployeeRules | Y35: 制度・運用 > 旅費 | AA35: 制度・運用 | AB35: 制度・運用 > 旅費 | AC35: predicted | AD35: 0 | AF35: 0 | AG35: 0 | AH35: 2 | AI35: 1 | AJ35: 1 | AK35: Resending Failed: 出張の旅費を申請する場合、仮住居から勤務事業所までの交通費は「赴任滞在証明書画面」から申請できます。 申請時のポイントは以下の通りです。 - 仮住居から勤務地までの交通費は赴任旅費として支給されます。 - 赴任滞在期間を超えて仮住居へ宿泊している場合も、交通費は支給されます。 - 仮住居に滞在していたことがわかる証明書類（領収書や赴任滞在証明書など）を添付してください。 - 通勤費申請（新経路）を行う際は「通勤開始日＝転居日」となります。 申請画面から必要事項を入力し、証明書類を添付して申請してください。 ※AIの回答は必ずしも正確ではありません。参照情報も確認いただき、最終判断は所属部署の公式情報をご確認ください。 | AL35: 4 | AM35: 4 | AN35: 0 | AO35: QA196_policy-operations_travel_travel-assignment_office-work_domestic_training_home-travel-expenses_overseas_operational_travel-others.md | AP35: 質問 仮住居から勤務地までの交通費はどのように申請したらよいですか。 回答 仮住居から勤務事業所まで交通費については、赴任旅費で支給されます。「赴任滞在証明書画面」より申請してください。 その後、通勤費申請（新経路）を行なう際は「通勤開始日＝転居日」となります。 | AQ35: 0.93756895 | AR35: QA176_policy-operations_travel_travel-assignment_office-work_domestic_training_home-travel-expenses_overseas_operational_travel-others.md | AS35: OBの方向け 赴任旅費申請マニュアル https://nttdocomo.sharepoint.com/:x:/r/sites/LifeAassist-kyuyo_Docomo_Com_Comware-all/Shared%20Documents/%E7%B5%A6%E4%B8%8E%E3%82%A2%E3%82%B7%E3%82%B9%E3%83%88HP/1.%E5%88%B6%E5%BA%A6%E3%83%BB%E7%94%B3%E8%AB%8B%E6%96%B9%E6%B3%95/%E2%91%A3%E8%B5%B4%E4%BB%BB%E6%97%85%E8%B2%BB/%E2%91%A0%E8%B5%B4%E4%BB%BB%E6%97%85%E8%B2%BB%E7%94%B3%E8%AB%8B%E3%83%9E%E3%83%8B%E3%83%A5%E3%82%A2%E3%83%AB.xlsx?d=w7934a11c73d548298f03c753256151f8&csf=1&web=1&e=9LwCMQ RSの方向け 『【RS】赴任旅費申請時の注意点』 | AT35: 0.9335416 | AU35: QA176_policy-operations_travel_travel-assignment_office-work_domestic_training_home-travel-expenses_overseas_operational_travel-others.md | AV35: 質問 赴任旅費の申請方法を教えてください。 回答 赴任旅費の申請方法については、以下の注意点、およびマニュアルをご確認ください。 OBの方向け 『「赴任旅費」申請時の注意点』 https://nttdocomo.sharepoint.com/:p:/r/sites/LifeAassist-kyuyo_Docomo_Com_Comware-all/Shared%20Documents/%E7%B5%A6%E4%B8%8E%E3%82%A2%E3%82%B7%E3%82%B9%E3%83%88HP/1.%E5%88%B6%E5%BA%A6%E3%83%BB%E7%94%B3%E8%AB%8B%E6%96%B9%E6%B3%95/%E2%91%A3%E8%B5%B4%E4%BB%BB%E6%97%85%E8%B2%BB/%E3%80%90OB%E5%AF%BE%E8%B1%A1%E8%80%85%E7%94%A8%E3%80%91%E3%80%8C%E8%B5%B4%E4%BB%BB%E6%97%85%E8%B2%BB%E3%80%8D%E7%94%B3%E8%AB%8B%E6%99%82%E3%81%AE%E6%B3%A8%E6%84%8F%E7%82%B9.pptx?d=wfe80418354504c849904e10a8f67ccdc&csf=1&web=1&e=EZHhhX OBの方向け 赴任旅費申請マニュアル | AW35: 0.93756895 | AX35: QA198_policy-operations_travel_travel-assignment_office-work_domestic_training_home-travel-expenses_overseas_operational_travel-others.md | AY35: 質問 赴任滞在期間を超えて仮住居へ宿泊している場合も交通費は支給されますか。 回答 赴任滞在期間を超えていても、仮住居からの交通費については支給されます。 仮住居に滞在していたことがわかる証明書類（領収書・赴任滞在証明書等）を添付してください。 | AZ35: 0.93354362 | BT35: 0 | BU35: 0 | BZ35: 0 | CA35: 0 | CB35: 20260520T090340-20260520T210308.csv | CC35: 5 | CD35: user > assistant > assistant > tool > error | CE35: 1.0.0 | CF35: no answer found | CH35: =IF(OR(CG35="①", CG35="⑤"), "〇", "×") | CI35: =IF(OR(AND($CT35<>"",ISNUMBER(SEARCH($CT35, AP35))),AND($CU35<>"",ISNUMBER(SEARCH($CU35, AP35))),AND($CV35<>"",ISNUMBER(SEARCH($CV35, AP35)))),"〇","-") | CJ35: =IF(OR(AND($CT35<>"",ISNUMBER(SEARCH($CT35, AS35))),AND($CU35<>"",ISNUMBER(SEARCH($CU35, AS35))),AND($CV35<>"",ISNUMBER(SEARCH($CV35, AS35)))),"〇","-") | CK35: =IF(OR(AND($CT35<>"",ISNUMBER(SEARCH($CT35, AV35))),AND($CU35<>"",ISNUMBER(SEARCH($CU35, AV35))),AND($CV35<>"",ISNUMBER(SEARCH($CV35, AV35)))),"〇","-") | CL35: =IF(OR(AND($CT35<>"",ISNUMBER(SEARCH($CT35, AY35))),AND($CU35<>"",ISNUMBER(SEARCH($CU35, AY35))),AND($CV35<>"",ISNUMBER(SEARCH($CV35, AY35)))),"〇","-") | CM35: =IF(OR(AND($CT35<>"",ISNUMBER(SEARCH($CT35, BB35))),AND($CU35<>"",ISNUMBER(SEARCH($CU35, BB35))),AND($CV35<>"",ISNUMBER(SEARCH($CV35, BB35)))),"〇","-") | CN35: =IF(OR(AND($CT35<>"",ISNUMBER(SEARCH($CT35, BE35))),AND($CU35<>"",ISNUMBER(SEARCH($CU35, BE35))),AND($CV35<>"",ISNUMBER(SEARCH($CV35, BE35)))),"〇","-") | CO35: =IF(OR(AND($CT35<>"",ISNUMBER(SEARCH($CT35, BH35))),AND($CU35<>"",ISNUMBER(SEARCH($CU35, BH35))),AND($CV35<>"",ISNUMBER(SEARCH($CV35, BH35)))),"〇","-") | CP35: =IF(OR(AND($CT35<>"",ISNUMBER(SEARCH($CT35, BK35))),AND($CU35<>"",ISNUMBER(SEARCH($CU35, BK35))),AND($CV35<>"",ISNUMBER(SEARCH($CV35, BK35)))),"〇","-") | CQ35: =IF(OR(AND($CT35<>"",ISNUMBER(SEARCH($CT35, BN35))),AND($CU35<>"",ISNUMBER(SEARCH($CU35, BN35))),AND($CV35<>"",ISNUMBER(SEARCH($CV35, BN35)))),"〇","-") | CR35: =IF(OR(AND($CT35<>"",ISNUMBER(SEARCH($CT35, BQ35))),AND($CU35<>"",ISNUMBER(SEARCH($CU35, BQ35))),AND($CV35<>"",ISNUMBER(SEARCH($CV35, BQ35)))),"〇","-") | CW35: =IF(OR(CI35="〇",CJ35="〇",CK35="〇",CL35="〇",CM35="〇",CN35="〇",CO35="〇",CP35="〇",CQ35="〇",CR35="〇"),"〇","") | DE35: =TEXT(U35,"yyyy/mm/dd") | DF35: =VLOOKUP(K35,社員マスタ!C:D,2,0) | DG35: 1779241443841
B36: a:12ratvcr2opxWviitasntE_WdKINffd6WG_gaBGYG23mTMIQae-Fdp0V5W-TesIh-KoweqmBTYRav7roLU7vTg7TPPDeQmRCt8UjUidNptaiW__-HLkjBDxMSpJfe98rq-1779241536444-FB000 | C36: =ROW(A36)-3 | D36: a:12ratvcr2opxWviitasntE_WdKINffd6WG_gaBGYG23mTMIQae-Fdp0V5W-TesIh-KoweqmBTYRav7roLU7vTg7TPPDeQmRCt8UjUidNptaiW__-HLkjBDxMSpJfe98rq-1779241536444 | E36: 1779241536444 | F36: a:12ratvcr2opxWviitasntE_WdKINffd6WG_gaBGYG23mTMIQae-Fdp0V5W-TesIh-KoweqmBTYRav7roLU7vTg7TPPDeQmRCt8UjUidNptaiW__-HLkjBDxMSpJfe98rq | G36: a:12ratvcr2opxWviitasntE_WdKINffd6WG_gaBGYG23mTMIQae-Fdp0V5W-TesIh-KoweqmBTYRav7roLU7vTg7TPPDeQmRCt8UjUidNptaiW__-HLkjBDxMSpJfe98rq-S001 | H36: 1 | I36: 2 | J36: 1 | K36: Shizuka Shirakata (白方 靜佳) | L36: DM | M36: おーい | N36: おーい | O36: 1 | P36: 0 | Q36: 0 | R36: 0 | S36: 46162.073 | T36: 46162.073 | U36: 46162.448 | V36: 46162.448 | W36: 1.44 | AB36: 未分類 | AC36: none | AD36: 1 | AE36: はい、どうされましたか？出張の旅費申請について、ほかに知りたいことや不明点があれば教えてくださいね。 ※AIの回答は必ずしも正確ではありません。参照情報も確認いただき、最終判断は所属部署の公式情報をご確認ください。 | AF36: 1 | AG36: 0 | AH36: 1 | AI36: 0 | AJ36: 0 | AL36: 0 | AM36: 0 | AN36: 0 | BT36: 0 | BU36: 0 | BZ36: 0 | CA36: 0 | CB36: 20260520T090340-20260520T210308.csv | CC36: 2 | CD36: user > assistant | CE36: 1.0.0 | CH36: =IF(OR(CG36="①", CG36="⑤"), "〇", "×") | CI36: =IF(OR(AND($CT36<>"",ISNUMBER(SEARCH($CT36, AP36))),AND($CU36<>"",ISNUMBER(SEARCH($CU36, AP36))),AND($CV36<>"",ISNUMBER(SEARCH($CV36, AP36)))),"〇","-") | CJ36: =IF(OR(AND($CT36<>"",ISNUMBER(SEARCH($CT36, AS36))),AND($CU36<>"",ISNUMBER(SEARCH($CU36, AS36))),AND($CV36<>"",ISNUMBER(SEARCH($CV36, AS36)))),"〇","-") | CK36: =IF(OR(AND($CT36<>"",ISNUMBER(SEARCH($CT36, AV36))),AND($CU36<>"",ISNUMBER(SEARCH($CU36, AV36))),AND($CV36<>"",ISNUMBER(SEARCH($CV36, AV36)))),"〇","-") | CL36: =IF(OR(AND($CT36<>"",ISNUMBER(SEARCH($CT36, AY36))),AND($CU36<>"",ISNUMBER(SEARCH($CU36, AY36))),AND($CV36<>"",ISNUMBER(SEARCH($CV36, AY36)))),"〇","-") | CM36: =IF(OR(AND($CT36<>"",ISNUMBER(SEARCH($CT36, BB36))),AND($CU36<>"",ISNUMBER(SEARCH($CU36, BB36))),AND($CV36<>"",ISNUMBER(SEARCH($CV36, BB36)))),"〇","-") | CN36: =IF(OR(AND($CT36<>"",ISNUMBER(SEARCH($CT36, BE36))),AND($CU36<>"",ISNUMBER(SEARCH($CU36, BE36))),AND($CV36<>"",ISNUMBER(SEARCH($CV36, BE36)))),"〇","-") | CO36: =IF(OR(AND($CT36<>"",ISNUMBER(SEARCH($CT36, BH36))),AND($CU36<>"",ISNUMBER(SEARCH($CU36, BH36))),AND($CV36<>"",ISNUMBER(SEARCH($CV36, BH36)))),"〇","-") | CP36: =IF(OR(AND($CT36<>"",ISNUMBER(SEARCH($CT36, BK36))),AND($CU36<>"",ISNUMBER(SEARCH($CU36, BK36))),AND($CV36<>"",ISNUMBER(SEARCH($CV36, BK36)))),"〇","-") | CQ36: =IF(OR(AND($CT36<>"",ISNUMBER(SEARCH($CT36, BN36))),AND($CU36<>"",ISNUMBER(SEARCH($CU36, BN36))),AND($CV36<>"",ISNUMBER(SEARCH($CV36, BN36)))),"〇","-") | CR36: =IF(OR(AND($CT36<>"",ISNUMBER(SEARCH($CT36, BQ36))),AND($CU36<>"",ISNUMBER(SEARCH($CU36, BQ36))),AND($CV36<>"",ISNUMBER(SEARCH($CV36, BQ36)))),"〇","-") | CW36: =IF(OR(CI36="〇",CJ36="〇",CK36="〇",CL36="〇",CM36="〇",CN36="〇",CO36="〇",CP36="〇",CQ36="〇",CR36="〇"),"〇","") | DE36: =TEXT(U36,"yyyy/mm/dd") | DF36: =VLOOKUP(K36,社員マスタ!C:D,2,0) | DG36: 1779241536444
B37: a:12ratvcr2opxWviitasntE_WdKINffd6WG_gaBGYG23mTMIQae-Fdp0V5W-TesIh-KoweqmBTYRav7roLU7vTg7TPPDeQmRCt8UjUidNptaiW__-HLkjBDxMSpJfe98rq-1779241551008-FB000 | C37: =ROW(A37)-3 | D37: a:12ratvcr2opxWviitasntE_WdKINffd6WG_gaBGYG23mTMIQae-Fdp0V5W-TesIh-KoweqmBTYRav7roLU7vTg7TPPDeQmRCt8UjUidNptaiW__-HLkjBDxMSpJfe98rq-1779241551008 | E37: 1779241551008 | F37: a:12ratvcr2opxWviitasntE_WdKINffd6WG_gaBGYG23mTMIQae-Fdp0V5W-TesIh-KoweqmBTYRav7roLU7vTg7TPPDeQmRCt8UjUidNptaiW__-HLkjBDxMSpJfe98rq | G37: a:12ratvcr2opxWviitasntE_WdKINffd6WG_gaBGYG23mTMIQae-Fdp0V5W-TesIh-KoweqmBTYRav7roLU7vTg7TPPDeQmRCt8UjUidNptaiW__-HLkjBDxMSpJfe98rq-S001 | H37: 1 | I37: 3 | J37: 1 | K37: Shizuka Shirakata (白方 靜佳) | L37: DM | M37: 出張の交通費の申請方法が知りたい | N37: 出張の交通費の申請方法が知りたい | O37: 1 | P37: 0 | Q37: 0 | R37: 0 | S37: 46162.074 | T37: 46162.074 | U37: 46162.449 | V37: 46162.449 | W37: 3.127 | AB37: 未分類 | AC37: none | AD37: 1 | AE37: 出張の旅費申請については、仮住居から勤務事業所までの交通費は「赴任滞在証明書画面」から申請します。 ポイントは以下の通りです。 - 赴任旅費として支給されます。 - 赴任滞在期間を超えて仮住居に宿泊している場合も交通費は支給されます。 - 仮住居滞在の証明書類（領収書や赴任滞在証明書など）を添付してください。 - 通勤費申請（新経路）を行う際は「通勤開始日＝転居日」となります。 これらを踏まえて、申請画面で必要事項を入力し、証明書類を添付して申請してください。 ※AIの回答は必ずしも正確ではありません。参照情報も確認いただき、最終判断は所属部署の公式情報をご確認ください。 | AF37: 1 | AG37: 0 | AH37: 1 | AI37: 0 | AJ37: 0 | AL37: 0 | AM37: 0 | AN37: 0 | BT37: 0 | BU37: 0 | BZ37: 0 | CA37: 0 | CB37: 20260520T090340-20260520T210308.csv | CC37: 2 | CD37: user > assistant | CE37: 1.0.0 | CH37: =IF(OR(CG37="①", CG37="⑤"), "〇", "×") | CI37: =IF(OR(AND($CT37<>"",ISNUMBER(SEARCH($CT37, AP37))),AND($CU37<>"",ISNUMBER(SEARCH($CU37, AP37))),AND($CV37<>"",ISNUMBER(SEARCH($CV37, AP37)))),"〇","-") | CJ37: =IF(OR(AND($CT37<>"",ISNUMBER(SEARCH($CT37, AS37))),AND($CU37<>"",ISNUMBER(SEARCH($CU37, AS37))),AND($CV37<>"",ISNUMBER(SEARCH($CV37, AS37)))),"〇","-") | CK37: =IF(OR(AND($CT37<>"",ISNUMBER(SEARCH($CT37, AV37))),AND($CU37<>"",ISNUMBER(SEARCH($CU37, AV37))),AND($CV37<>"",ISNUMBER(SEARCH($CV37, AV37)))),"〇","-") | CL37: =IF(OR(AND($CT37<>"",ISNUMBER(SEARCH($CT37, AY37))),AND($CU37<>"",ISNUMBER(SEARCH($CU37, AY37))),AND($CV37<>"",ISNUMBER(SEARCH($CV37, AY37)))),"〇","-") | CM37: =IF(OR(AND($CT37<>"",ISNUMBER(SEARCH($CT37, BB37))),AND($CU37<>"",ISNUMBER(SEARCH($CU37, BB37))),AND($CV37<>"",ISNUMBER(SEARCH($CV37, BB37)))),"〇","-") | CN37: =IF(OR(AND($CT37<>"",ISNUMBER(SEARCH($CT37, BE37))),AND($CU37<>"",ISNUMBER(SEARCH($CU37, BE37))),AND($CV37<>"",ISNUMBER(SEARCH($CV37, BE37)))),"〇","-") | CO37: =IF(OR(AND($CT37<>"",ISNUMBER(SEARCH($CT37, BH37))),AND($CU37<>"",ISNUMBER(SEARCH($CU37, BH37))),AND($CV37<>"",ISNUMBER(SEARCH($CV37, BH37)))),"〇","-") | CP37: =IF(OR(AND($CT37<>"",ISNUMBER(SEARCH($CT37, BK37))),AND($CU37<>"",ISNUMBER(SEARCH($CU37, BK37))),AND($CV37<>"",ISNUMBER(SEARCH($CV37, BK37)))),"〇","-") | CQ37: =IF(OR(AND($CT37<>"",ISNUMBER(SEARCH($CT37, BN37))),AND($CU37<>"",ISNUMBER(SEARCH($CU37, BN37))),AND($CV37<>"",ISNUMBER(SEARCH($CV37, BN37)))),"〇","-") | CR37: =IF(OR(AND($CT37<>"",ISNUMBER(SEARCH($CT37, BQ37))),AND($CU37<>"",ISNUMBER(SEARCH($CU37, BQ37))),AND($CV37<>"",ISNUMBER(SEARCH($CV37, BQ37)))),"〇","-") | CW37: =IF(OR(CI37="〇",CJ37="〇",CK37="〇",CL37="〇",CM37="〇",CN37="〇",CO37="〇",CP37="〇",CQ37="〇",CR37="〇"),"〇","") | DE37: =TEXT(U37,"yyyy/mm/dd") | DF37: =VLOOKUP(K37,社員マスタ!C:D,2,0) | DG37: 1779241551008
B38: a:12ratvcr2opxWviitasntE_WdKINffd6WG_gaBGYG23mTMIQae-Fdp0V5W-TesIh-KoweqmBTYRav7roLU7vTg7TPPDeQmRCt8UjUidNptaiW__-HLkjBDxMSpJfe98rq-1779241598613-FB000 | C38: =ROW(A38)-3 | D38: a:12ratvcr2opxWviitasntE_WdKINffd6WG_gaBGYG23mTMIQae-Fdp0V5W-TesIh-KoweqmBTYRav7roLU7vTg7TPPDeQmRCt8UjUidNptaiW__-HLkjBDxMSpJfe98rq-1779241598613 | E38: 1779241598613 | F38: a:12ratvcr2opxWviitasntE_WdKINffd6WG_gaBGYG23mTMIQae-Fdp0V5W-TesIh-KoweqmBTYRav7roLU7vTg7TPPDeQmRCt8UjUidNptaiW__-HLkjBDxMSpJfe98rq | G38: a:12ratvcr2opxWviitasntE_WdKINffd6WG_gaBGYG23mTMIQae-Fdp0V5W-TesIh-KoweqmBTYRav7roLU7vTg7TPPDeQmRCt8UjUidNptaiW__-HLkjBDxMSpJfe98rq-S001 | H38: 1 | I38: 4 | J38: 1 | K38: Shizuka Shirakata (白方 靜佳) | L38: DM | M38: 赴任旅費じゃなくて単なるセミナー参加の出張旅費の申請方法が知りたい | N38: 赴任旅費じゃなくて単なるセミナー参加の出張旅費の申請方法が知りたい | O38: 1 | P38: 0 | Q38: 0 | R38: 0 | S38: 46162.074 | T38: 46162.074 | U38: 46162.449 | V38: 46162.449 | W38: 5.031 | X38: searchEmployeeRules | AB38: 未分類 | AC38: none | AD38: 1 | AE38: ご質問の内容に関する情報が見つかりませんでした。 以下操作を行っていただくことで回答を得やすくなるのでお試しください。 * 「カテゴリ」を選択：質問要件が絞りこまれることで回答が得やすくなります。 * 「リセット」を選択：会話記録をリセットすることで回答が得やすくなります。 * 「ヘルプ」を選択 ：回答が得やすくなるヒントが確認できます。 有人での確認が必要な内容や個別条件に関するご質問は、「個別問合せ」をご利用ください。 | AF38: 1 | AG38: 1 | AH38: 2 | AI38: 0 | AJ38: 0 | AL38: 4 | AM38: 4 | AN38: 0 | AO38: QA196_policy-operations_travel_travel-assignment_office-work_domestic_training_home-travel-expenses_overseas_operational_travel-others.md | AP38: 質問 仮住居から勤務地までの交通費はどのように申請したらよいですか。 回答 仮住居から勤務事業所まで交通費については、赴任旅費で支給されます。「赴任滞在証明書画面」より申請してください。 その後、通勤費申請（新経路）を行なう際は「通勤開始日＝転居日」となります。 | AQ38: 0.9305972 | AR38: QA198_policy-operations_travel_travel-assignment_office-work_domestic_training_home-travel-expenses_overseas_operational_travel-others.md | AS38: 質問 赴任滞在期間を超えて仮住居へ宿泊している場合も交通費は支給されますか。 回答 赴任滞在期間を超えていても、仮住居からの交通費については支給されます。 仮住居に滞在していたことがわかる証明書類（領収書・赴任滞在証明書等）を添付してください。 | AT38: 0.92746555 | AU38: QA176_policy-operations_travel_travel-assignment_office-work_domestic_training_home-travel-expenses_overseas_operational_travel-others.md | AV38: 質問 赴任旅費の申請方法を教えてください。 回答 赴任旅費の申請方法については、以下の注意点、およびマニュアルをご確認ください。 OBの方向け 『「赴任旅費」申請時の注意点』 https://nttdocomo.sharepoint.com/:p:/r/sites/LifeAassist-kyuyo_Docomo_Com_Comware-all/Shared%20Documents/%E7%B5%A6%E4%B8%8E%E3%82%A2%E3%82%B7%E3%82%B9%E3%83%88HP/1.%E5%88%B6%E5%BA%A6%E3%83%BB%E7%94%B3%E8%AB%8B%E6%96%B9%E6%B3%95/%E2%91%A3%E8%B5%B4%E4%BB%BB%E6%97%85%E8%B2%BB/%E3%80%90OB%E5%AF%BE%E8%B1%A1%E8%80%85%E7%94%A8%E3%80%91%E3%80%8C%E8%B5%B4%E4%BB%BB%E6%97%85%E8%B2%BB%E3%80%8D%E7%94%B3%E8%AB%8B%E6%99%82%E3%81%AE%E6%B3%A8%E6%84%8F%E7%82%B9.pptx?d=wfe80418354504c849904e10a8f67ccdc&csf=1&web=1&e=EZHhhX OBの方向け 赴任旅費申請マニュアル | AW38: 0.9305972 | AX38: QA177_policy-operations_travel_travel-assignment_office-work_domestic_training_home-travel-expenses_overseas_operational_travel-others.md | AY38: 質問 赴任に伴い単身赴任となりました。「赴任旅費申請」と「単身赴任申請」どちらを先に申請すればいいですか。 回答 先に「単身赴任申請」を実施してください。その後、「赴任旅費申請」を実施してください。 ※いずれも転居後に申請を実施してください。 | AZ38: 0.92485028 | BT38: 0 | BU38: 0 | BZ38: 0 | CA38: 0 | CB38: 20260520T090340-20260520T210308.csv | CC38: 4 | CD38: user > assistant > tool > assistant | CE38: 1.0.0 | CH38: =IF(OR(CG38="①", CG38="⑤"), "〇", "×") | CI38: =IF(OR(AND($CT38<>"",ISNUMBER(SEARCH($CT38, AP38))),AND($CU38<>"",ISNUMBER(SEARCH($CU38, AP38))),AND($CV38<>"",ISNUMBER(SEARCH($CV38, AP38)))),"〇","-") | CJ38: =IF(OR(AND($CT38<>"",ISNUMBER(SEARCH($CT38, AS38))),AND($CU38<>"",ISNUMBER(SEARCH($CU38, AS38))),AND($CV38<>"",ISNUMBER(SEARCH($CV38, AS38)))),"〇","-") | CK38: =IF(OR(AND($CT38<>"",ISNUMBER(SEARCH($CT38, AV38))),AND($CU38<>"",ISNUMBER(SEARCH($CU38, AV38))),AND($CV38<>"",ISNUMBER(SEARCH($CV38, AV38)))),"〇","-") | CL38: =IF(OR(AND($CT38<>"",ISNUMBER(SEARCH($CT38, AY38))),AND($CU38<>"",ISNUMBER(SEARCH($CU38, AY38))),AND($CV38<>"",ISNUMBER(SEARCH($CV38, AY38)))),"〇","-") | CM38: =IF(OR(AND($CT38<>"",ISNUMBER(SEARCH($CT38, BB38))),AND($CU38<>"",ISNUMBER(SEARCH($CU38, BB38))),AND($CV38<>"",ISNUMBER(SEARCH($CV38, BB38)))),"〇","-") | CN38: =IF(OR(AND($CT38<>"",ISNUMBER(SEARCH($CT38, BE38))),AND($CU38<>"",ISNUMBER(SEARCH($CU38, BE38))),AND($CV38<>"",ISNUMBER(SEARCH($CV38, BE38)))),"〇","-") | CO38: =IF(OR(AND($CT38<>"",ISNUMBER(SEARCH($CT38, BH38))),AND($CU38<>"",ISNUMBER(SEARCH($CU38, BH38))),AND($CV38<>"",ISNUMBER(SEARCH($CV38, BH38)))),"〇","-") | CP38: =IF(OR(AND($CT38<>"",ISNUMBER(SEARCH($CT38, BK38))),AND($CU38<>"",ISNUMBER(SEARCH($CU38, BK38))),AND($CV38<>"",ISNUMBER(SEARCH($CV38, BK38)))),"〇","-") | CQ38: =IF(OR(AND($CT38<>"",ISNUMBER(SEARCH($CT38, BN38))),AND($CU38<>"",ISNUMBER(SEARCH($CU38, BN38))),AND($CV38<>"",ISNUMBER(SEARCH($CV38, BN38)))),"〇","-") | CR38: =IF(OR(AND($CT38<>"",ISNUMBER(SEARCH($CT38, BQ38))),AND($CU38<>"",ISNUMBER(SEARCH($CU38, BQ38))),AND($CV38<>"",ISNUMBER(SEARCH($CV38, BQ38)))),"〇","-") | CW38: =IF(OR(CI38="〇",CJ38="〇",CK38="〇",CL38="〇",CM38="〇",CN38="〇",CO38="〇",CP38="〇",CQ38="〇",CR38="〇"),"〇","") | DE38: =TEXT(U38,"yyyy/mm/dd") | DF38: =VLOOKUP(K38,社員マスタ!C:D,2,0) | DG38: 1779241598613
B39: a:1WfN1QUq4KVhx-dYtNeLoFKYHSM-7d7P0WyInAiv5PzvnG4czYzEWkpfE18-h06T8tHUbJBZwZJKuspzy9hbuBnuw7FuXoB7_aN1r0YpOFEaFWAIqjedkY6Ujz061ppNj-1779243186871-FB000 | C39: =ROW(A39)-3 | D39: a:1WfN1QUq4KVhx-dYtNeLoFKYHSM-7d7P0WyInAiv5PzvnG4czYzEWkpfE18-h06T8tHUbJBZwZJKuspzy9hbuBnuw7FuXoB7_aN1r0YpOFEaFWAIqjedkY6Ujz061ppNj-1779243186871 | E39: 1779243186871 | F39: a:1WfN1QUq4KVhx-dYtNeLoFKYHSM-7d7P0WyInAiv5PzvnG4czYzEWkpfE18-h06T8tHUbJBZwZJKuspzy9hbuBnuw7FuXoB7_aN1r0YpOFEaFWAIqjedkY6Ujz061ppNj | G39: a:1WfN1QUq4KVhx-dYtNeLoFKYHSM-7d7P0WyInAiv5PzvnG4czYzEWkpfE18-h06T8tHUbJBZwZJKuspzy9hbuBnuw7FuXoB7_aN1r0YpOFEaFWAIqjedkY6Ujz061ppNj-S001 | H39: 1 | I39: 2 | J39: 1 | K39: Maika Kawamoto (河本 舞花) | L39: DM | M39: 現在人材派遣契約中の方を7月以降も新会社でも継続して契約したいと考えています。 新会社になるにあたって、事業所単位の制限の３年のカウントがクリアされると聞いていますが、その際のstaffiaでの人材派遣契約は人材要求から再度実施すべきなのか、事業所単位の制限の３年のカウントは気にせず継続契約としてstaffiaで処理をすすめればよいか教えていただきたいです。 | N39: 現在人材派遣契約中の方を7月以降も新会社でも継続して契約したいと考えています。 新会社になるにあたって、事業所単位の制限の３年のカウントがクリアされると聞いていますが、その際のstaffiaでの人材派遣契約は人材要求から再度実施すべきなのか、事業所単位の制限の３年のカウントは気にせず継続契約としてstaffiaで処理をすすめればよいか教えていただきたいです。 | O39: 1 | P39: 0 | Q39: 0 | R39: 0 | S39: 46162.092 | T39: 46162.093 | U39: 46162.467 | V39: 46162.468 | W39: 6.64 | X39: searchEmployeeRules | Y39: システム操作 > Staffia | AA39: システム操作 | AB39: システム操作 > Staffia | AC39: predicted | AD39: 0 | AE39: 新会社になることで勤務事業所単位の3年制限のカウントがクリアされる場合、staffiaでの人材派遣契約については、以下の流れが必要です。 - 新会社で契約を継続する場合でも、スタッフ要求（人材要求）から再度実施する必要があります。 - staffia上で、スタッフ要求・見積依頼を行い、派遣会社からの回答を受けて候補者選定・個別契約申請を進める形となります。 - 継続契約として処理するのではなく、新たな契約プロセスを踏むことが求められます。 この手順に沿って、staffiaで契約手続きを進めてください。 ※AIの回答は必ずしも正確ではありません。参照情報も確認いただき、最終判断は所属部署の公式情報をご確認ください。 | AF39: 1 | AG39: 0 | AH39: 3 | AI39: 0 | AJ39: 0 | AL39: 4 | AM39: 4 | AN39: 0 | AO39: 【業務ID_6】Staffia業務マニュアル（派遣先組織向け）1.1版.pdf | AP39: ポイント 件名 決裁していただきたい事項 :契約期間、業務内容、取引先、費用 添付ファイル G決裁(決裁)利用メニュー :すべて ＞ 文書回覧 ＞ 文書回覧の新規作成 非公開フラグ 回覧ルート : 【実施伺い】人材派遣契約の実施について（○○担当）等 :Staffiaで作成した仕様書のPDFを添付する :個人情報が含まれる場合は「非公開フラグ」にチェックする :決裁者は派遣先責任者（派遣受入の決定権を持つ方）となるように承認フローを設定 44 | AQ39: 0.9316549 | AR39: 【業務ID_6】Staffia業務マニュアル（派遣先組織向け）1.1版.pdf | AS39: システムのインターフェースは異なるものの、スタッフ要求～個別契約についての流れは概ね同様。 スタッフ要求・見積依頼 個別契約 簡易申請に必要事項を記載し、 人員要求。 派遣会社から回答後、候補者選定 申請を実施し派遣会社確定。 共通申請で個別契約申請を実施。 派遣会社からの回答後、個別契約成立。 DREAMS ・ BUSKETS G共通IT（決裁）で実施伺い後、Staffiaに必要事項を記載し、 スタッフ要求・見積依頼を実施し、派遣会社からの回答を得る。 G共通IT（決裁）で実施伺い後、派遣会社を確定。Staffiaで個別契約内 容を派遣会社に提示。派遣会社からの回答内容を確認・承認後、個別契約 成立。 スタッフ要求書作成 派遣会社へ見積依頼 個別契約内容を作成し、派遣会社へ提示 派遣会社からの回答内容を確認・承認後、 個別契約成立 Staffia 6 | AT39: 0.93334434 | AU39: 【業務ID_6】Staffia業務マニュアル（派遣先組織向け）1.1版.pdf | AV39: 勤務管理においては、時間外・休暇・旅費申請の有無に関わらず、「派遣労働者による勤務時間と業務内容の申請」および 「勤務承認者の承認」がStaffiaでは毎日必要な点が異なる。支払は、システムのインターフェースは異なるものの、流れは概ね同様。 勤務管理 支払 スケジューラで勤務系申請（時間外・休暇・旅費等）を実施し、 上⾧が承認。（申請事項がない場合は、上⾧は承認不要） 前月の勤務実績および支払額を 確認し、簡易申請を実施。 派遣会社から回答後、検収を実施し 派遣料金を支払い。 支払額確認 検収 DREAMS ・ BUSKETS 時間外や休暇、旅費申請の有無に関わらず、派遣労働者は、毎日 当日 の勤務時間と業務内容を申請。 派遣労働者の申請に基づき、勤務承認者は内容を確認し日次承認。 月間の勤務実績を確認し、 勤務管理の月次承認を実施。 派遣会社から回答後、Staffiaで 支 払承認を実施。その後、G共通IT（財 務）に自動連係され支払い。 派遣労働者は毎日 勤務時間と業務内容を申請 勤務承認者は 勤務状況と業務内容を 日次承認 月次承認 支払承認 Staffia 7 | AW39: 0.9316549 | AX39: 【業務ID_6】Staffia業務マニュアル（派遣先組織向け）1.1版.pdf | AY39: 業務プロセス スタッフ要求 見積依頼 個別契約 勤務管理 支払  1 2   3 As-Is(～26.3) 利用システム 簡易申請 ・ BUSKETS 共通申請 ・ BUSKETS スケジューラ 簡易申請/検収 ・ BUSKETS オペレーション内容 人員要求申請 派遣会社回答 候補者選定申請（派遣会社決定） 人材派遣契約申請 決裁承認 派遣会社回答 契約締結 勤務系申請（時間外・休暇・旅費等） 承認 支払額確認 派遣会社回答 検収（支払） 1 業務プロセス 初期設定 スタッフ要求 見積依頼 個別契約 勤務管理 支払 ３ To-Be(26.4～) 利用システム Staffia 2 G共通IT（決裁） Staffia G共通IT（決裁） Staffia オペレーション内容 操作者登録や権限設定 等 スタッフ要求実施伺い申請/承認 スタッフ要求・見積依頼 派遣会社回答 個別契約実施伺い申請/承認 （派遣会社決定） 個別契約書案提示 派遣会社回答 個別契約承認 契約締結 勤務系申請 （業務内容登録・時間外・休暇・旅費 等） 日次承認 勤務管理 月次承認 派遣会社確認・請求書発行 請求額確認・支払 ※G共通IT（財務）に自動連係 4 | AZ39: 0.93145865 | BT39: 0 | BU39: 0 | BZ39: 0 | CA39: 0 | CB39: 20260520T090340-20260520T210308.csv | CC39: 5 | CD39: user > assistant > assistant > tool > assistant | CE39: 1.0.0 | CH39: =IF(OR(CG39="①", CG39="⑤"), "〇", "×") | CI39: =IF(OR(AND($CT39<>"",ISNUMBER(SEARCH($CT39, AP39))),AND($CU39<>"",ISNUMBER(SEARCH($CU39, AP39))),AND($CV39<>"",ISNUMBER(SEARCH($CV39, AP39)))),"〇","-") | CJ39: =IF(OR(AND($CT39<>"",ISNUMBER(SEARCH($CT39, AS39))),AND($CU39<>"",ISNUMBER(SEARCH($CU39, AS39))),AND($CV39<>"",ISNUMBER(SEARCH($CV39, AS39)))),"〇","-") | CK39: =IF(OR(AND($CT39<>"",ISNUMBER(SEARCH($CT39, AV39))),AND($CU39<>"",ISNUMBER(SEARCH($CU39, AV39))),AND($CV39<>"",ISNUMBER(SEARCH($CV39, AV39)))),"〇","-") | CL39: =IF(OR(AND($CT39<>"",ISNUMBER(SEARCH($CT39, AY39))),AND($CU39<>"",ISNUMBER(SEARCH($CU39, AY39))),AND($CV39<>"",ISNUMBER(SEARCH($CV39, AY39)))),"〇","-") | CM39: =IF(OR(AND($CT39<>"",ISNUMBER(SEARCH($CT39, BB39))),AND($CU39<>"",ISNUMBER(SEARCH($CU39, BB39))),AND($CV39<>"",ISNUMBER(SEARCH($CV39, BB39)))),"〇","-") | CN39: =IF(OR(AND($CT39<>"",ISNUMBER(SEARCH($CT39, BE39))),AND($CU39<>"",ISNUMBER(SEARCH($CU39, BE39))),AND($CV39<>"",ISNUMBER(SEARCH($CV39, BE39)))),"〇","-") | CO39: =IF(OR(AND($CT39<>"",ISNUMBER(SEARCH($CT39, BH39))),AND($CU39<>"",ISNUMBER(SEARCH($CU39, BH39))),AND($CV39<>"",ISNUMBER(SEARCH($CV39, BH39)))),"〇","-") | CP39: =IF(OR(AND($CT39<>"",ISNUMBER(SEARCH($CT39, BK39))),AND($CU39<>"",ISNUMBER(SEARCH($CU39, BK39))),AND($CV39<>"",ISNUMBER(SEARCH($CV39, BK39)))),"〇","-") | CQ39: =IF(OR(AND($CT39<>"",ISNUMBER(SEARCH($CT39, BN39))),AND($CU39<>"",ISNUMBER(SEARCH($CU39, BN39))),AND($CV39<>"",ISNUMBER(SEARCH($CV39, BN39)))),"〇","-") | CR39: =IF(OR(AND($CT39<>"",ISNUMBER(SEARCH($CT39, BQ39))),AND($CU39<>"",ISNUMBER(SEARCH($CU39, BQ39))),AND($CV39<>"",ISNUMBER(SEARCH($CV39, BQ39)))),"〇","-") | CW39: =IF(OR(CI39="〇",CJ39="〇",CK39="〇",CL39="〇",CM39="〇",CN39="〇",CO39="〇",CP39="〇",CQ39="〇",CR39="〇"),"〇","") | DE39: =TEXT(U39,"yyyy/mm/dd") | DF39: =VLOOKUP(K39,社員マスタ!C:D,2,0) | DG39: 1779243186871
B40: a:1W3yxpjrBjwBQAEgoZCWhE4uYl9xI-su8JLethNQvLov3-SUd9an4XIzcZDQqhAjh9XWIrtRkxemSRhjKjD4lJR-37e6S_YmnBciWRojesNIEjnM_OwSHEMflhugSJSzE-1779251435183-FB000 | C40: =ROW(A40)-3 | D40: a:1W3yxpjrBjwBQAEgoZCWhE4uYl9xI-su8JLethNQvLov3-SUd9an4XIzcZDQqhAjh9XWIrtRkxemSRhjKjD4lJR-37e6S_YmnBciWRojesNIEjnM_OwSHEMflhugSJSzE-1779251435183 | E40: 1779251435183 | F40: a:1W3yxpjrBjwBQAEgoZCWhE4uYl9xI-su8JLethNQvLov3-SUd9an4XIzcZDQqhAjh9XWIrtRkxemSRhjKjD4lJR-37e6S_YmnBciWRojesNIEjnM_OwSHEMflhugSJSzE | G40: a:1W3yxpjrBjwBQAEgoZCWhE4uYl9xI-su8JLethNQvLov3-SUd9an4XIzcZDQqhAjh9XWIrtRkxemSRhjKjD4lJR-37e6S_YmnBciWRojesNIEjnM_OwSHEMflhugSJSzE-S001 | H40: 1 | I40: 1 | J40: 1 | K40: Sakino Onodera (小野寺 咲乃) | L40: DM | M40: これは何ができるアプリですか？ | N40: これは何ができるアプリですか？ | O40: 1 | P40: 0 | Q40: 0 | R40: 0 | S40: 46162.188 | T40: 46162.188 | U40: 46162.563 | V40: 46162.563 | W40: 5.349 | X40: searchEmployeeRules | Y40: 未分類 | AA40: 未分類 | AB40: 未分類 | AC40: predicted | AD40: 1 | AE40: 検索結果からは、利用開始にあたって資料を見て進めることや、会社のメールアドレスを入力する必要があること、利用申請は2025年5月1日以降に登録が必要になることがわかります。 ただし、このアプリで具体的に何ができるかについての詳細な情報は検索結果に含まれていませんでした。もし具体的な機能や用途について知りたい場合は、追加で質問していただくと、より詳しくお答えできる可能性があります。 ※AIの回答は必ずしも正確ではありません。参照情報も確認いただき、最終判断は所属部署の公式情報をご確認ください。 | AF40: 1 | AG40: 0 | AH40: 3 | AI40: 0 | AJ40: 0 | AL40: 4 | AM40: 4 | AN40: 0 | AO40: QA69_policy-operations_benefits_benefits-others.md | AP40: 質問 資料を見て利用開始するという理解で合っていますか。 回答 ご認識の通りです。 | AQ40: 0.91034693 | AR40: QA86_policy-operations_benefits_benefits-others.md | AS40: 質問 入力するメールアドレスは私用のものでよろしいですか。 回答 会社のメールアドレスをご入力ください。 | AT40: 0.90647 | AU40: QA68_policy-operations_benefits_benefits-others.md | AV40: 質問 現状は利用申請などは不要ですか。 回答 2025年5月1日より利用可能となりますので、その後利用登録等お願いします。 | AW40: 0.91034693 | AX40: QA584_system_talemane_talemane-employee.md | AY40: 質問 Chromeを最新化する方法を教えてください。 回答 Chrome最新化の方法は以下URLをご確認ください。 https://www.hdservice1.nttls.co.jp/hc/ja/articles/45200710157081 | AZ40: 0.9045471 | BT40: 0 | BU40: 0 | BZ40: 0 | CA40: 0 | CB40: 20260520T090340-20260520T210308.csv | CC40: 5 | CD40: user > assistant > assistant > tool > assistant | CE40: 1.0.0 | CH40: =IF(OR(CG40="①", CG40="⑤"), "〇", "×") | CI40: =IF(OR(AND($CT40<>"",ISNUMBER(SEARCH($CT40, AP40))),AND($CU40<>"",ISNUMBER(SEARCH($CU40, AP40))),AND($CV40<>"",ISNUMBER(SEARCH($CV40, AP40)))),"〇","-") | CJ40: =IF(OR(AND($CT40<>"",ISNUMBER(SEARCH($CT40, AS40))),AND($CU40<>"",ISNUMBER(SEARCH($CU40, AS40))),AND($CV40<>"",ISNUMBER(SEARCH($CV40, AS40)))),"〇","-") | CK40: =IF(OR(AND($CT40<>"",ISNUMBER(SEARCH($CT40, AV40))),AND($CU40<>"",ISNUMBER(SEARCH($CU40, AV40))),AND($CV40<>"",ISNUMBER(SEARCH($CV40, AV40)))),"〇","-") | CL40: =IF(OR(AND($CT40<>"",ISNUMBER(SEARCH($CT40, AY40))),AND($CU40<>"",ISNUMBER(SEARCH($CU40, AY40))),AND($CV40<>"",ISNUMBER(SEARCH($CV40, AY40)))),"〇","-") | CM40: =IF(OR(AND($CT40<>"",ISNUMBER(SEARCH($CT40, BB40))),AND($CU40<>"",ISNUMBER(SEARCH($CU40, BB40))),AND($CV40<>"",ISNUMBER(SEARCH($CV40, BB40)))),"〇","-") | CN40: =IF(OR(AND($CT40<>"",ISNUMBER(SEARCH($CT40, BE40))),AND($CU40<>"",ISNUMBER(SEARCH($CU40, BE40))),AND($CV40<>"",ISNUMBER(SEARCH($CV40, BE40)))),"〇","-") | CO40: =IF(OR(AND($CT40<>"",ISNUMBER(SEARCH($CT40, BH40))),AND($CU40<>"",ISNUMBER(SEARCH($CU40, BH40))),AND($CV40<>"",ISNUMBER(SEARCH($CV40, BH40)))),"〇","-") | CP40: =IF(OR(AND($CT40<>"",ISNUMBER(SEARCH($CT40, BK40))),AND($CU40<>"",ISNUMBER(SEARCH($CU40, BK40))),AND($CV40<>"",ISNUMBER(SEARCH($CV40, BK40)))),"〇","-") | CQ40: =IF(OR(AND($CT40<>"",ISNUMBER(SEARCH($CT40, BN40))),AND($CU40<>"",ISNUMBER(SEARCH($CU40, BN40))),AND($CV40<>"",ISNUMBER(SEARCH($CV40, BN40)))),"〇","-") | CR40: =IF(OR(AND($CT40<>"",ISNUMBER(SEARCH($CT40, BQ40))),AND($CU40<>"",ISNUMBER(SEARCH($CU40, BQ40))),AND($CV40<>"",ISNUMBER(SEARCH($CV40, BQ40)))),"〇","-") | CW40: =IF(OR(CI40="〇",CJ40="〇",CK40="〇",CL40="〇",CM40="〇",CN40="〇",CO40="〇",CP40="〇",CQ40="〇",CR40="〇"),"〇","") | DE40: =TEXT(U40,"yyyy/mm/dd") | DF40: =VLOOKUP(K40,社員マスタ!C:D,2,0) | DG40: 1779251435183
B41: a:1FYtUc9xZ1YQ1NOyVJqKT6flPbrq87XXrHLd5MoZw8zsmEVMv2rXL5FCa5YtWxbG2UXLu6RcdQbHtOBH3pmPzmoF7rnrzAH7WJXsQ1miGEXgNeYFAFhy4Cybat152lKq6-1779251448229-FB000 | C41: =ROW(A41)-3 | D41: a:1FYtUc9xZ1YQ1NOyVJqKT6flPbrq87XXrHLd5MoZw8zsmEVMv2rXL5FCa5YtWxbG2UXLu6RcdQbHtOBH3pmPzmoF7rnrzAH7WJXsQ1miGEXgNeYFAFhy4Cybat152lKq6-1779251448229 | E41: 1779251448229 | F41: a:1FYtUc9xZ1YQ1NOyVJqKT6flPbrq87XXrHLd5MoZw8zsmEVMv2rXL5FCa5YtWxbG2UXLu6RcdQbHtOBH3pmPzmoF7rnrzAH7WJXsQ1miGEXgNeYFAFhy4Cybat152lKq6 | G41: a:1FYtUc9xZ1YQ1NOyVJqKT6flPbrq87XXrHLd5MoZw8zsmEVMv2rXL5FCa5YtWxbG2UXLu6RcdQbHtOBH3pmPzmoF7rnrzAH7WJXsQ1miGEXgNeYFAFhy4Cybat152lKq6-S001 | H41: 1 | I41: 1 | J41: 1 | K41: Shigemitsu Byoudou (平等 滋充) | L41: DM | M41: 秘密度に応じた生成AIの使用制限について教えてください。 具体的にどんな情報は生成AIに読み込ませてはいけないかを知りたい。 | N41: 秘密度に応じた生成AIの使用制限について教えてください。 具体的にどんな情報は生成AIに読み込ませてはいけないかを知りたい。 | O41: 1 | P41: 0 | Q41: 0 | R41: 0 | S41: 46162.188 | T41: 46162.188 | U41: 46162.563 | V41: 46162.563 | W41: 7.442 | X41: searchEmployeeRules | Y41: 制度・運用 | AA41: 制度・運用 | AB41: 制度・運用 | AC41: predicted | AD41: 0 | AE41: 生成AIに読み込ませてはいけない情報は、秘密度に応じて以下のように制限されています。 - 通信の秘密に係る情報（通話明細、通信履歴、通話料金など） - 法人顧客情報のうち、機密性が高く慎重に扱うべき情報（通話明細、通信内容、DWHデータ、料金シミュレーション、大量の顧客情報など） - 完了案件情報（機密情報を除き、お客様法人対応が完了した情報で、完了案件後も継続して保管する情報） また、情報管理規程で「レベルS」「レベルA」「レベルB」に区分された管理情報の紙や記憶媒体による持ち出しは禁止されています。 これらの情報は生成AIへの入力や読み込みも禁止されているため、取り扱いには十分ご注意ください。 ※AIの回答は必ずしも正確ではありません。参照情報も確認いただき、最終判断は所属部署の公式情報をご確認ください。 | AF41: 1 | AG41: 0 | AH41: 3 | AI41: 0 | AJ41: 0 | AL41: 4 | AM41: 4 | AN41: 0 | AO41: QA69_policy-operations_benefits_benefits-others.md | AP41: 質問 資料を見て利用開始するという理解で合っていますか。 回答 ご認識の通りです。 | AQ41: 0.91019195 | AR41: 49 リモートワークの取扱いについて_202511.docx | AS41: （１）通信の秘密に係る情報（通話明細/通信履歴/通話料金など） （２）法人顧客情報の内、機密情報（特に機密性が高く慎重に扱わなければいけない情報(通話明細/通信内容/DWHデータ/料金シミュレーション/大量の顧客情報 等)）および完了案件情報（機密情報を除き、お客様法人対応が完了した情報で、完了案件後も継続して保管する情報）にあたる情報 13．情報セキュリティ対策 （１）リモートワークにおいては、「情報管理規程」（2003年５月27日社長達第８号）、「情報管理細則（2003年５月27日総第1162号）及び「クライアントＰＣ管理マニュアル」（2010年１月21日情セ第768号）等の会社・組織が定める各種の規則・規程等に定める事項に従わなければならない。 （２）情報管理規程に定める「レベルＳ」「レベルＡ」「レベルＢ」に区分された管理情報の紙及び記憶媒体による持ち出しは、禁止する。 14．服務管理等 （１）社員等がリモートワークを実施するときは、日々、始業時刻・終業時刻、分断時間、休憩時間及び業務の実施状況を直属上長に報告するものとする。 （２）直属上長は、社員等のリモートワークの実施状況について、適切な管理を行うものとする。 15. リモートスタンダード リモートワークを基本とする業務遂行を行う働き方として、リモートスタンダードを設定し、リモートワークを基本とする業務運営が可能であると組織長が判断した場合において適用する。 なお、具体的な扱いについては、第２章のとおりとする。 | AT41: 0.90521265 | AU41: 02 臨時雇就業規則_202512.docx | AV41: 含む）及び育児・介護関連諸制度の利用に関する言動又は優越的な関係を背景とした業務上必要かつ相当な範囲を超えた言動により、就業環境を害し、又は他の従業員若しくは取引先等の他の事業主に雇用される社員等に不利益を与えてはならない。 ４ 会社施設内において、みだりに飲酒めいていし、又はとばく等をしてはならない。 ５ 会社施設内において、みだりに火器その他の危険物を所持し、又は使用してはならない。 ６ 会社の物品又は財産を不当に棄却し、亡失し、き損し、又は私用に供してはならない。 ７ 会社施設内において、演説、集会、貼紙、掲示、ビラの配布その他これに類する行為をしようとするときは、事前にその会社施設の管理責任者の許可を受けなければならない。 ８ 会社施設内において、選挙運動その他の政治活動をしてはならない。 ９ 前各号のほか、会社施設内において風紀秩序を乱すような言動をしてはならない。 職務上の秘密及び個人情報を守る義務 第 ４ 条 通信の秘密及びその他の職務上知ることができた秘密を漏らしてはならない。 ２ 臨時雇は、職務上知ることができた個人情報（個人番号及び特定個人情報を含む。）を正当な理由なく使用し又は漏らしてはならない。 ３ 前１項及び２項は、その職を退いた後においても同様とする。 出勤退社 第 ５ 条 定刻までに出勤して、所定の手続きをとらなければならない。 ２ 特に命ぜられているときは、退社時にも所定の手続きをとらなければならない。 遅刻、早退、欠勤の届出 第 ６ 条 遅刻、早退又は欠勤をしようとするときは、あらかじめその理由を具して届け出て、承認を受けなければならない。ただし、病気その他の事故により、やむを得ずあらかじめ届け出ることができなかったときは、事後遅滞なく届け出なければならない。 居住地の届出等 第 ７ 条 特に命ぜられた者は、居住地を届け出ておかなければならない。 ２ 臨時雇は、会社が業務上必要がある自らの個人情報（個人番号及び特定個人情報を含む。）を提供しなければならない。その職を退いた後においても同様とする。 | AW41: 0.91019195 | AX41: QA86_policy-operations_benefits_benefits-others.md | AY41: 質問 入力するメールアドレスは私用のものでよろしいですか。 回答 会社のメールアドレスをご入力ください。 | AZ41: 0.90293065 | BT41: 0 | BU41: 0 | BZ41: 0 | CA41: 0 | CB41: 20260520T090340-20260520T210308.csv | CC41: 5 | CD41: user > assistant > assistant > tool > assistant | CE41: 1.0.0 | CH41: =IF(OR(CG41="①", CG41="⑤"), "〇", "×") | CI41: =IF(OR(AND($CT41<>"",ISNUMBER(SEARCH($CT41, AP41))),AND($CU41<>"",ISNUMBER(SEARCH($CU41, AP41))),AND($CV41<>"",ISNUMBER(SEARCH($CV41, AP41)))),"〇","-") | CJ41: =IF(OR(AND($CT41<>"",ISNUMBER(SEARCH($CT41, AS41))),AND($CU41<>"",ISNUMBER(SEARCH($CU41, AS41))),AND($CV41<>"",ISNUMBER(SEARCH($CV41, AS41)))),"〇","-") | CK41: =IF(OR(AND($CT41<>"",ISNUMBER(SEARCH($CT41, AV41))),AND($CU41<>"",ISNUMBER(SEARCH($CU41, AV41))),AND($CV41<>"",ISNUMBER(SEARCH($CV41, AV41)))),"〇","-") | CL41: =IF(OR(AND($CT41<>"",ISNUMBER(SEARCH($CT41, AY41))),AND($CU41<>"",ISNUMBER(SEARCH($CU41, AY41))),AND($CV41<>"",ISNUMBER(SEARCH($CV41, AY41)))),"〇","-") | CM41: =IF(OR(AND($CT41<>"",ISNUMBER(SEARCH($CT41, BB41))),AND($CU41<>"",ISNUMBER(SEARCH($CU41, BB41))),AND($CV41<>"",ISNUMBER(SEARCH($CV41, BB41)))),"〇","-") | CN41: =IF(OR(AND($CT41<>"",ISNUMBER(SEARCH($CT41, BE41))),AND($CU41<>"",ISNUMBER(SEARCH($CU41, BE41))),AND($CV41<>"",ISNUMBER(SEARCH($CV41, BE41)))),"〇","-") | CO41: =IF(OR(AND($CT41<>"",ISNUMBER(SEARCH($CT41, BH41))),AND($CU41<>"",ISNUMBER(SEARCH($CU41, BH41))),AND($CV41<>"",ISNUMBER(SEARCH($CV41, BH41)))),"〇","-") | CP41: =IF(OR(AND($CT41<>"",ISNUMBER(SEARCH($CT41, BK41))),AND($CU41<>"",ISNUMBER(SEARCH($CU41, BK41))),AND($CV41<>"",ISNUMBER(SEARCH($CV41, BK41)))),"〇","-") | CQ41: =IF(OR(AND($CT41<>"",ISNUMBER(SEARCH($CT41, BN41))),AND($CU41<>"",ISNUMBER(SEARCH($CU41, BN41))),AND($CV41<>"",ISNUMBER(SEARCH($CV41, BN41)))),"〇","-") | CR41: =IF(OR(AND($CT41<>"",ISNUMBER(SEARCH($CT41, BQ41))),AND($CU41<>"",ISNUMBER(SEARCH($CU41, BQ41))),AND($CV41<>"",ISNUMBER(SEARCH($CV41, BQ41)))),"〇","-") | CW41: =IF(OR(CI41="〇",CJ41="〇",CK41="〇",CL41="〇",CM41="〇",CN41="〇",CO41="〇",CP41="〇",CQ41="〇",CR41="〇"),"〇","") | DE41: =TEXT(U41,"yyyy/mm/dd") | DF41: =VLOOKUP(K41,社員マスタ!C:D,2,0) | DG41: 1779251448229
B42: a:1FYtUc9xZ1YQ1NOyVJqKT6flPbrq87XXrHLd5MoZw8zsmEVMv2rXL5FCa5YtWxbG2UXLu6RcdQbHtOBH3pmPzmoF7rnrzAH7WJXsQ1miGEXgNeYFAFhy4Cybat152lKq6-1779251540675-FB000 | C42: =ROW(A42)-3 | D42: a:1FYtUc9xZ1YQ1NOyVJqKT6flPbrq87XXrHLd5MoZw8zsmEVMv2rXL5FCa5YtWxbG2UXLu6RcdQbHtOBH3pmPzmoF7rnrzAH7WJXsQ1miGEXgNeYFAFhy4Cybat152lKq6-1779251540675 | E42: 1779251540675 | F42: a:1FYtUc9xZ1YQ1NOyVJqKT6flPbrq87XXrHLd5MoZw8zsmEVMv2rXL5FCa5YtWxbG2UXLu6RcdQbHtOBH3pmPzmoF7rnrzAH7WJXsQ1miGEXgNeYFAFhy4Cybat152lKq6 | G42: a:1FYtUc9xZ1YQ1NOyVJqKT6flPbrq87XXrHLd5MoZw8zsmEVMv2rXL5FCa5YtWxbG2UXLu6RcdQbHtOBH3pmPzmoF7rnrzAH7WJXsQ1miGEXgNeYFAFhy4Cybat152lKq6-S001 | H42: 1 | I42: 2 | J42: 1 | K42: Shigemitsu Byoudou (平等 滋充) | L42: DM | M42: 秘密度BはCopilot ChatBasicに読み込ませることがルール上認められていますか？エンタープライズデータ保護が有効になっていることを確認済みです。 | N42: 秘密度BはCopilot ChatBasicに読み込ませることがルール上認められていますか？エンタープライズデータ保護が有効になっていることを確認済みです。 | O42: 1 | P42: 0 | Q42: 0 | R42: 0 | S42: 46162.189 | T42: 46162.189 | U42: 46162.564 | V42: 46162.564 | W42: 6.985 | X42: searchEmployeeRules | AB42: 未分類 | AC42: none | AD42: 1 | AE42: 現時点のルール上、秘密度Bの情報については「紙や記憶媒体による持ち出しは禁止」とされていますが、Copilot ChatBasicへの読み込みに関する具体的な許可や禁止の記載は検索結果からは確認できませんでした。 エンタープライズデータ保護が有効になっている場合でも、秘密度Bの情報を生成AIに読み込ませることが認められているかどうかは、明確な記載が見当たりません。 このため、現状ではルール上の取り扱いが不明確です。 ※AIの回答は必ずしも正確ではありません。参照情報も確認いただき、最終判断は所属部署の公式情報をご確認ください。 | AF42: 1 | AG42: 0 | AH42: 2 | AI42: 0 | AJ42: 0 | AL42: 4 | AM42: 4 | AN42: 0 | AO42: アドバンスト-プロフェッショナル規程.pdf | AP42: 秘密度 B 作 成 者：総務人事部長 作成年月日：2025/3/31 SECRET B 制定 2019 年３月 28 日 社長達第 45 号 改正 2022 年６月 30 日 社長達第 24 号 2023 年３月 31 日 社長達第 127 号 2025 年３月 31 日 総人第 9368 号 アドバンスト・プロフェッショナル規程 社 長 達 第 4 5 号 2019 年 ３ 月 28 日 「アドバンスト・プロフェッショナル就業規則」（2019 年３月 28 日社長達第 44 号）における アドバンスト・プロフェッショナルについて次のように定める。 （目的） 第 １ 条 この規程は、第２条に定める者の委嘱に関する事項を定めることを目的とする。 ただし、別に定める場合はこの限りでない。 （定 義） 第 ２ 条 この規程において「アドバンスト・プロフェッショナル」とは、卓越した専門性 を有する人材を社員から認定し、特定の業務を委嘱した者、または卓越した専門性 を有する人材を会社の必要性に基づき社員以外の者で常態的に特定の業務を委嘱し た者で、期間を定めて雇用される者をいう。 また、呼称についても「アドバンスト・プロフェッショナル」とする。 （委嘱責任者） 第 ３ 条 委嘱責任者は、副社長（コーポレート担当）とする。 ２ 委嘱責任者は、アドバンスト・プロフェッショナルの委嘱、解嘱及びその他の嘱 託に関する業務を行う。 （労働条件等） 第 ４ 条 アドバンスト・プロフェッショナルの労働条件等について、「アドバンスト・プ ロフェッショナル就業規則」の定めによることとする。 なお、委嘱する業務の内容等を勘案し、委嘱契約締結の際個別に決定する場合は 1 | AQ42: 0.9035195 | AR42: 49 リモートワークの取扱いについて_202511.docx | AS42: （１）通信の秘密に係る情報（通話明細/通信履歴/通話料金など） （２）法人顧客情報の内、機密情報（特に機密性が高く慎重に扱わなければいけない情報(通話明細/通信内容/DWHデータ/料金シミュレーション/大量の顧客情報 等)）および完了案件情報（機密情報を除き、お客様法人対応が完了した情報で、完了案件後も継続して保管する情報）にあたる情報 13．情報セキュリティ対策 （１）リモートワークにおいては、「情報管理規程」（2003年５月27日社長達第８号）、「情報管理細則（2003年５月27日総第1162号）及び「クライアントＰＣ管理マニュアル」（2010年１月21日情セ第768号）等の会社・組織が定める各種の規則・規程等に定める事項に従わなければならない。 （２）情報管理規程に定める「レベルＳ」「レベルＡ」「レベルＢ」に区分された管理情報の紙及び記憶媒体による持ち出しは、禁止する。 14．服務管理等 （１）社員等がリモートワークを実施するときは、日々、始業時刻・終業時刻、分断時間、休憩時間及び業務の実施状況を直属上長に報告するものとする。 （２）直属上長は、社員等のリモートワークの実施状況について、適切な管理を行うものとする。 15. リモートスタンダード リモートワークを基本とする業務遂行を行う働き方として、リモートスタンダードを設定し、リモートワークを基本とする業務運営が可能であると組織長が判断した場合において適用する。 なお、具体的な扱いについては、第２章のとおりとする。 | AT42: 0.9111657 | AU42: QA69_policy-operations_benefits_benefits-others.md | AV42: 質問 資料を見て利用開始するという理解で合っていますか。 回答 ご認識の通りです。 | AW42: 0.9035195 | AX42: アドバンスト-プロフェッショナルの福利厚生の取扱いについて.pdf | AY42: 秘密度 C 作成者：総務人事部長 作成日：2025 年 3 月 28 日 制定 2019 年 3 月 27 日 人第 3356 号 改正 2020 年 3 月 31 日 人第 3793 号 改正 2021 年 3 月 31 日 人第 3580 号 改正 2022 年 3 月 30 日 人第 3374 号 改正 2025 年 3 月 28 日 総人第 324 号 人 第 3 3 5 6 号 2019 年 3 月 27 日 人 事 部 長 アドバンスト・プロフェッショナルの福利厚生の取扱いについて 「アドバンスト・プロフェッショナル規程」（2019 年 3 月 28 日 社長達第 44 号)により雇用される アドバンスト・プロフェッショナルの福利厚生については、次のとおり実施することとする。 １．福利厚生の種類 福利厚生の種類は、健康管理、業務災害補償等、慶弔金、ＮＴＴベネフィット・パッケージ、ｄ ヘルスケア（ベーシック）及びＭ３ＰＳＰ（専門医への健康相談）とする。 ２．健康管理 アドバンスト・プロフェッショナルの健康管理については、｢健康管理規程｣（1992 年 7 月 1 日 社長達第 33 号）を準用することとする。 なお、人間ドックを希望する場合は、健康診断の代替として年一回受健を可能とする。 ３．業務災害補償等 アドバンスト・プロフェッショナルの業務災害補償及び通勤災害補償については、労働災害補償 保険法（1947 年法律第 50 号）に定める保険給付のほか、「社員業務災害付加補償規則」（1992 年 7 月 1 日 社長達第 31 号）に定める業務災害付加補償又は「社員通勤災害付加給付規則」（1992 年 7 月 1 日 社長達第 64 号）に定める通勤災害付加給付、「業務災害に準ずる補償の取扱いについて」 （2002 年 3 月 29 日 総第 124 号）に定める業務災害に準ずる補償、「業務災害等に伴う私有物の損 害見舞いについて」（1992 年 7 月 1 日 総第 104 号）に定める見舞金給付を準用する。 | AZ42: 0.90187472 | BT42: 0 | BU42: 0 | BZ42: 0 | CA42: 0 | CB42: 20260520T090340-20260520T210308.csv | CC42: 4 | CD42: user > assistant > tool > assistant | CE42: 1.0.0 | CH42: =IF(OR(CG42="①", CG42="⑤"), "〇", "×") | CI42: =IF(OR(AND($CT42<>"",ISNUMBER(SEARCH($CT42, AP42))),AND($CU42<>"",ISNUMBER(SEARCH($CU42, AP42))),AND($CV42<>"",ISNUMBER(SEARCH($CV42, AP42)))),"〇","-") | CJ42: =IF(OR(AND($CT42<>"",ISNUMBER(SEARCH($CT42, AS42))),AND($CU42<>"",ISNUMBER(SEARCH($CU42, AS42))),AND($CV42<>"",ISNUMBER(SEARCH($CV42, AS42)))),"〇","-") | CK42: =IF(OR(AND($CT42<>"",ISNUMBER(SEARCH($CT42, AV42))),AND($CU42<>"",ISNUMBER(SEARCH($CU42, AV42))),AND($CV42<>"",ISNUMBER(SEARCH($CV42, AV42)))),"〇","-") | CL42: =IF(OR(AND($CT42<>"",ISNUMBER(SEARCH($CT42, AY42))),AND($CU42<>"",ISNUMBER(SEARCH($CU42, AY42))),AND($CV42<>"",ISNUMBER(SEARCH($CV42, AY42)))),"〇","-") | CM42: =IF(OR(AND($CT42<>"",ISNUMBER(SEARCH($CT42, BB42))),AND($CU42<>"",ISNUMBER(SEARCH($CU42, BB42))),AND($CV42<>"",ISNUMBER(SEARCH($CV42, BB42)))),"〇","-") | CN42: =IF(OR(AND($CT42<>"",ISNUMBER(SEARCH($CT42, BE42))),AND($CU42<>"",ISNUMBER(SEARCH($CU42, BE42))),AND($CV42<>"",ISNUMBER(SEARCH($CV42, BE42)))),"〇","-") | CO42: =IF(OR(AND($CT42<>"",ISNUMBER(SEARCH($CT42, BH42))),AND($CU42<>"",ISNUMBER(SEARCH($CU42, BH42))),AND($CV42<>"",ISNUMBER(SEARCH($CV42, BH42)))),"〇","-") | CP42: =IF(OR(AND($CT42<>"",ISNUMBER(SEARCH($CT42, BK42))),AND($CU42<>"",ISNUMBER(SEARCH($CU42, BK42))),AND($CV42<>"",ISNUMBER(SEARCH($CV42, BK42)))),"〇","-") | CQ42: =IF(OR(AND($CT42<>"",ISNUMBER(SEARCH($CT42, BN42))),AND($CU42<>"",ISNUMBER(SEARCH($CU42, BN42))),AND($CV42<>"",ISNUMBER(SEARCH($CV42, BN42)))),"〇","-") | CR42: =IF(OR(AND($CT42<>"",ISNUMBER(SEARCH($CT42, BQ42))),AND($CU42<>"",ISNUMBER(SEARCH($CU42, BQ42))),AND($CV42<>"",ISNUMBER(SEARCH($CV42, BQ42)))),"〇","-") | CW42: =IF(OR(CI42="〇",CJ42="〇",CK42="〇",CL42="〇",CM42="〇",CN42="〇",CO42="〇",CP42="〇",CQ42="〇",CR42="〇"),"〇","") | DE42: =TEXT(U42,"yyyy/mm/dd") | DF42: =VLOOKUP(K42,社員マスタ!C:D,2,0) | DG42: 1779251540675
B43: a:1FYtUc9xZ1YQ1NOyVJqKT6flPbrq87XXrHLd5MoZw8zsmEVMv2rXL5FCa5YtWxbG2UXLu6RcdQbHtOBH3pmPzmoF7rnrzAH7WJXsQ1miGEXgNeYFAFhy4Cybat152lKq6-1779251589857-FB000 | C43: =ROW(A43)-3 | D43: a:1FYtUc9xZ1YQ1NOyVJqKT6flPbrq87XXrHLd5MoZw8zsmEVMv2rXL5FCa5YtWxbG2UXLu6RcdQbHtOBH3pmPzmoF7rnrzAH7WJXsQ1miGEXgNeYFAFhy4Cybat152lKq6-1779251589857 | E43: 1779251589857 | F43: a:1FYtUc9xZ1YQ1NOyVJqKT6flPbrq87XXrHLd5MoZw8zsmEVMv2rXL5FCa5YtWxbG2UXLu6RcdQbHtOBH3pmPzmoF7rnrzAH7WJXsQ1miGEXgNeYFAFhy4Cybat152lKq6 | G43: a:1FYtUc9xZ1YQ1NOyVJqKT6flPbrq87XXrHLd5MoZw8zsmEVMv2rXL5FCa5YtWxbG2UXLu6RcdQbHtOBH3pmPzmoF7rnrzAH7WJXsQ1miGEXgNeYFAFhy4Cybat152lKq6-S001 | H43: 1 | I43: 3 | J43: 1 | K43: Shigemitsu Byoudou (平等 滋充) | L43: DM | M43: 生成AIに関する規定文書を探してください。 | N43: 生成AIに関する規定文書を探してください。 | O43: 1 | P43: 0 | Q43: 0 | R43: 0 | S43: 46162.19 | T43: 46162.19 | U43: 46162.565 | V43: 46162.565 | W43: 6.659 | X43: searchEmployeeRules | AB43: 未分類 | AC43: none | AD43: 1 | AE43: 検索結果から、生成AIに関する規定文書の具体的な記載や案内は見当たりませんでした。 現時点では、生成AIに関する規定文書の存在や内容については確認できません。 ※AIの回答は必ずしも正確ではありません。参照情報も確認いただき、最終判断は所属部署の公式情報をご確認ください。 | AF43: 1 | AG43: 0 | AH43: 2 | AI43: 0 | AJ43: 0 | AL43: 4 | AM43: 4 | AN43: 0 | AO43: 38 育児又は介護のための休職等について_202410.docx | AP43: について」に規定するところによる。 エ エキスパートⅡの賃金等の取扱いについては、「エキスパートⅡの賃金の取扱いについて」に規定するところによる。 オ 常勤嘱託の賃金等の取扱いについては、「嘱託の取扱いについて」に規定するところによる。 カ 臨時雇の賃金等の取扱いについては、「臨時雇賃金規則」に規定するところによる。 付 則 １ 本通達は、2023年４月１日より実施する。 ２ 本通達の実施に伴い、「育児休職について」（1992年７月１日総第10号）、「育児のための短時間勤務制度について」（2007年３月30日人育服第９号）及び「介護休職及び介護のための短時間勤務制度について」（1992年７月１日総第121号）を廃止する。 付 則 この改正は、2024年７月１日より実施する。 付 則 この改正は、2024年10月１日より実施する。 | AQ43: 0.90678078 | AR43: 40 特認休暇について_202511.docx | AS43: 付 則 この改正は、2025年11月７日から実施する。 | AT43: 0.90475435 | AU43: QA69_policy-operations_benefits_benefits-others.md | AV43: 質問 資料を見て利用開始するという理解で合っていますか。 回答 ご認識の通りです。 | AW43: 0.90678078 | AX43: 36 社員の勤務時間、休日及び休暇について_202504.docx | AY43: （８）第1項第8号（法令による業務の履行） 災害救助法による救助業務従事命令、自衛隊法（1954年法律第165号）による防衛召集命令、訓練召集命令等の法令による業務を履行する場合をいう。 （９）第1項第9号（官公署への出頭） 過失による犯罪若しくは事故のため、逮捕され又は被疑者として官公署に召喚された場合を含む。 （10）第1項第10号（レクリエーション行事） 「レクリエーションの取扱い等について」（1992年7月1日総第88号）に規定する行事へ参加する場合をいう。 （11）第1項第11号（部内外行事への参加） 社員が従事している職務又はこれに必要な資格等に関して、学会、協会その他の団体が主催する職務上必要と認められる行事へ参加する場合をいう。 （12）第1項第12号（結婚） ア 社員が結婚する場合において、挙式等を行う場合をいう。 イ 休暇の期間については、第4項の規定に関わらず、休日を除く連続した期間として取り扱うことができるものとする。 （13）第1項第13号（忌引） ア 社員と生計を同じくしているパートナーの父母、祖父母、兄弟姉妹及び伯叔父母が死亡した場合は、それぞれの社員の父母、祖父母、兄弟姉妹及び伯叔父母が死亡した場合と同じ日数とする。 イ 父母がすでに死亡して、社員が父母に代って祖父母の葬祭を行う場合は、父母が死亡した場合と同じ日数とする。 ウ 葬祭のため遠隔の地に行く必要のあるときは、実際に必要とした往復日数を加算した日数とする。 （14）第1項第14号（夏季） ア 6月1日から9月30日までの期間内において、社員より請求があった場合に与える。 イ 休暇の期間については、第4項の規定に関わらず、日を単位に分割することができるものとする。 ウ 前アの期間中に新たに採用された場合又は復職した場合等の日数については、採用等の日の属する月により次の日数とする。 6月、7月中の採用等 ・・・3日 8月中の採用等 ・・・・・・2日 9月中の採用等 ・・・・・・1日 （15）第1項第15号（出産） ア 出産には、流産、早産、死産及び母体保護法（1948年法律第156号）による妊娠中絶を含むものとする。 イ 出産の日は、出産前の休暇の期間に含める。 | AZ43: 0.90604279 | BT43: 0 | BU43: 0 | BZ43: 0 | CA43: 0 | CB43: 20260520T090340-20260520T210308.csv | CC43: 4 | CD43: user > assistant > tool > assistant | CE43: 1.0.0 | CH43: =IF(OR(CG43="①", CG43="⑤"), "〇", "×") | CI43: =IF(OR(AND($CT43<>"",ISNUMBER(SEARCH($CT43, AP43))),AND($CU43<>"",ISNUMBER(SEARCH($CU43, AP43))),AND($CV43<>"",ISNUMBER(SEARCH($CV43, AP43)))),"〇","-") | CJ43: =IF(OR(AND($CT43<>"",ISNUMBER(SEARCH($CT43, AS43))),AND($CU43<>"",ISNUMBER(SEARCH($CU43, AS43))),AND($CV43<>"",ISNUMBER(SEARCH($CV43, AS43)))),"〇","-") | CK43: =IF(OR(AND($CT43<>"",ISNUMBER(SEARCH($CT43, AV43))),AND($CU43<>"",ISNUMBER(SEARCH($CU43, AV43))),AND($CV43<>"",ISNUMBER(SEARCH($CV43, AV43)))),"〇","-") | CL43: =IF(OR(AND($CT43<>"",ISNUMBER(SEARCH($CT43, AY43))),AND($CU43<>"",ISNUMBER(SEARCH($CU43, AY43))),AND($CV43<>"",ISNUMBER(SEARCH($CV43, AY43)))),"〇","-") | CM43: =IF(OR(AND($CT43<>"",ISNUMBER(SEARCH($CT43, BB43))),AND($CU43<>"",ISNUMBER(SEARCH($CU43, BB43))),AND($CV43<>"",ISNUMBER(SEARCH($CV43, BB43)))),"〇","-") | CN43: =IF(OR(AND($CT43<>"",ISNUMBER(SEARCH($CT43, BE43))),AND($CU43<>"",ISNUMBER(SEARCH($CU43, BE43))),AND($CV43<>"",ISNUMBER(SEARCH($CV43, BE43)))),"〇","-") | CO43: =IF(OR(AND($CT43<>"",ISNUMBER(SEARCH($CT43, BH43))),AND($CU43<>"",ISNUMBER(SEARCH($CU43, BH43))),AND($CV43<>"",ISNUMBER(SEARCH($CV43, BH43)))),"〇","-") | CP43: =IF(OR(AND($CT43<>"",ISNUMBER(SEARCH($CT43, BK43))),AND($CU43<>"",ISNUMBER(SEARCH($CU43, BK43))),AND($CV43<>"",ISNUMBER(SEARCH($CV43, BK43)))),"〇","-") | CQ43: =IF(OR(AND($CT43<>"",ISNUMBER(SEARCH($CT43, BN43))),AND($CU43<>"",ISNUMBER(SEARCH($CU43, BN43))),AND($CV43<>"",ISNUMBER(SEARCH($CV43, BN43)))),"〇","-") | CR43: =IF(OR(AND($CT43<>"",ISNUMBER(SEARCH($CT43, BQ43))),AND($CU43<>"",ISNUMBER(SEARCH($CU43, BQ43))),AND($CV43<>"",ISNUMBER(SEARCH($CV43, BQ43)))),"〇","-") | CW43: =IF(OR(CI43="〇",CJ43="〇",CK43="〇",CL43="〇",CM43="〇",CN43="〇",CO43="〇",CP43="〇",CQ43="〇",CR43="〇"),"〇","") | DE43: =TEXT(U43,"yyyy/mm/dd") | DF43: =VLOOKUP(K43,社員マスタ!C:D,2,0) | DG43: 1779251589857
B44: a:15wLubgxMHuf3nJD5ftAarkap3V7FOowwxuEIiVkaeuVMbiVA4mQQHPgR-KaooWloxqJEPJqsxWYYxqQ3qLKNMwug5f6kWqTLGPo_7vPycIZp9i7UVWuXFMWM3pAK62PL-f:414a115b-0900-10d6-8332-b08c1f92dc3a-FB000 | C44: =ROW(A44)-3 | D44: a:15wLubgxMHuf3nJD5ftAarkap3V7FOowwxuEIiVkaeuVMbiVA4mQQHPgR-KaooWloxqJEPJqsxWYYxqQ3qLKNMwug5f6kWqTLGPo_7vPycIZp9i7UVWuXFMWM3pAK62PL-f:414a115b-0900-10d6-8332-b08c1f92dc3a | E44: f:414a115b-0900-10d6-8332-b08c1f92dc3a | F44: a:15wLubgxMHuf3nJD5ftAarkap3V7FOowwxuEIiVkaeuVMbiVA4mQQHPgR-KaooWloxqJEPJqsxWYYxqQ3qLKNMwug5f6kWqTLGPo_7vPycIZp9i7UVWuXFMWM3pAK62PL | G44: a:15wLubgxMHuf3nJD5ftAarkap3V7FOowwxuEIiVkaeuVMbiVA4mQQHPgR-KaooWloxqJEPJqsxWYYxqQ3qLKNMwug5f6kWqTLGPo_7vPycIZp9i7UVWuXFMWM3pAK62PL-S001 | H44: 1 | I44: 1 | J44: 1 | K44: Chiharu Mizukoshi (水越 千春) | L44: DM | N44: [カテゴリ選択] | O44: 0 | P44: 0 | Q44: 1 | R44: 0 | S44: 46162.194 | T44: 46162.194 | U44: 46162.569 | V44: 46162.569 | W44: 0 | Z44: システム操作 > ビズバンス | AB44: システム操作 > ビズバンス | AC44: user_selected | AD44: 0 | AF44: 0 | AG44: 0 | AH44: 0 | AI44: 0 | AJ44: 0 | AL44: 0 | AM44: 0 | AN44: 0 | BT44: 0 | BU44: 0 | BZ44: 0 | CA44: 0 | CB44: 20260520T090340-20260520T210308.csv | CC44: 1 | CD44: user | CE44: 1.0.0 | CH44: =IF(OR(CG44="①", CG44="⑤"), "〇", "×") | CI44: =IF(OR(AND($CT44<>"",ISNUMBER(SEARCH($CT44, AP44))),AND($CU44<>"",ISNUMBER(SEARCH($CU44, AP44))),AND($CV44<>"",ISNUMBER(SEARCH($CV44, AP44)))),"〇","-") | CJ44: =IF(OR(AND($CT44<>"",ISNUMBER(SEARCH($CT44, AS44))),AND($CU44<>"",ISNUMBER(SEARCH($CU44, AS44))),AND($CV44<>"",ISNUMBER(SEARCH($CV44, AS44)))),"〇","-") | CK44: =IF(OR(AND($CT44<>"",ISNUMBER(SEARCH($CT44, AV44))),AND($CU44<>"",ISNUMBER(SEARCH($CU44, AV44))),AND($CV44<>"",ISNUMBER(SEARCH($CV44, AV44)))),"〇","-") | CL44: =IF(OR(AND($CT44<>"",ISNUMBER(SEARCH($CT44, AY44))),AND($CU44<>"",ISNUMBER(SEARCH($CU44, AY44))),AND($CV44<>"",ISNUMBER(SEARCH($CV44, AY44)))),"〇","-") | CM44: =IF(OR(AND($CT44<>"",ISNUMBER(SEARCH($CT44, BB44))),AND($CU44<>"",ISNUMBER(SEARCH($CU44, BB44))),AND($CV44<>"",ISNUMBER(SEARCH($CV44, BB44)))),"〇","-") | CN44: =IF(OR(AND($CT44<>"",ISNUMBER(SEARCH($CT44, BE44))),AND($CU44<>"",ISNUMBER(SEARCH($CU44, BE44))),AND($CV44<>"",ISNUMBER(SEARCH($CV44, BE44)))),"〇","-") | CO44: =IF(OR(AND($CT44<>"",ISNUMBER(SEARCH($CT44, BH44))),AND($CU44<>"",ISNUMBER(SEARCH($CU44, BH44))),AND($CV44<>"",ISNUMBER(SEARCH($CV44, BH44)))),"〇","-") | CP44: =IF(OR(AND($CT44<>"",ISNUMBER(SEARCH($CT44, BK44))),AND($CU44<>"",ISNUMBER(SEARCH($CU44, BK44))),AND($CV44<>"",ISNUMBER(SEARCH($CV44, BK44)))),"〇","-") | CQ44: =IF(OR(AND($CT44<>"",ISNUMBER(SEARCH($CT44, BN44))),AND($CU44<>"",ISNUMBER(SEARCH($CU44, BN44))),AND($CV44<>"",ISNUMBER(SEARCH($CV44, BN44)))),"〇","-") | CR44: =IF(OR(AND($CT44<>"",ISNUMBER(SEARCH($CT44, BQ44))),AND($CU44<>"",ISNUMBER(SEARCH($CU44, BQ44))),AND($CV44<>"",ISNUMBER(SEARCH($CV44, BQ44)))),"〇","-") | CW44: =IF(OR(CI44="〇",CJ44="〇",CK44="〇",CL44="〇",CM44="〇",CN44="〇",CO44="〇",CP44="〇",CQ44="〇",CR44="〇"),"〇","") | DE44: =TEXT(U44,"yyyy/mm/dd") | DF44: =VLOOKUP(K44,社員マスタ!C:D,2,0) | DG44: f:414a115b-0900-10d6-8332-b08c1f92dc3a
B45: a:15wLubgxMHuf3nJD5ftAarkap3V7FOowwxuEIiVkaeuVMbiVA4mQQHPgR-KaooWloxqJEPJqsxWYYxqQ3qLKNMwug5f6kWqTLGPo_7vPycIZp9i7UVWuXFMWM3pAK62PL-1779252057831-FB000 | C45: =ROW(A45)-3 | D45: a:15wLubgxMHuf3nJD5ftAarkap3V7FOowwxuEIiVkaeuVMbiVA4mQQHPgR-KaooWloxqJEPJqsxWYYxqQ3qLKNMwug5f6kWqTLGPo_7vPycIZp9i7UVWuXFMWM3pAK62PL-1779252057831 | E45: 1779252057831 | F45: a:15wLubgxMHuf3nJD5ftAarkap3V7FOowwxuEIiVkaeuVMbiVA4mQQHPgR-KaooWloxqJEPJqsxWYYxqQ3qLKNMwug5f6kWqTLGPo_7vPycIZp9i7UVWuXFMWM3pAK62PL | G45: a:15wLubgxMHuf3nJD5ftAarkap3V7FOowwxuEIiVkaeuVMbiVA4mQQHPgR-KaooWloxqJEPJqsxWYYxqQ3qLKNMwug5f6kWqTLGPo_7vPycIZp9i7UVWuXFMWM3pAK62PL-S001 | H45: 1 | I45: 2 | J45: 1 | K45: Chiharu Mizukoshi (水越 千春) | L45: DM | M45: 清算部署が異なる代理者の依頼は可能ですか？ | N45: 清算部署が異なる代理者の依頼は可能ですか？ | O45: 1 | P45: 0 | Q45: 0 | R45: 0 | S45: 46162.195 | T45: 46162.195 | U45: 46162.57 | V45: 46162.57 | W45: 6.156 | X45: searchEmployeeRules | AB45: 未分類 | AC45: none | AD45: 1 | AE45: 検索結果からは、清算部署が異なる代理者の依頼について直接的な可否や手順の記載は見つかりませんでした。 この件については、詳細な情報が不足しているため、適切な問い合わせ先への確認が必要です。 ※AIの回答は必ずしも正確ではありません。参照情報も確認いただき、最終判断は所属部署の公式情報をご確認ください。 | AF45: 1 | AG45: 0 | AH45: 2 | AI45: 0 | AJ45: 0 | AL45: 1 | AM45: 1 | AN45: 0 | AO45: 【業務ID_1】チケット手配業務マニュアル1.1.1版.pdf | AP45: ＞「経費 ID 9 申請（申請編）」＞「 2-1-1. 社外支払(実施決裁)の作成・申請 」をご参照くださ い。 その他の項目の操作については 37 | AQ45: 0.90364015 | AW45: 0.90364015 | BT45: 0 | BU45: 0 | BZ45: 0 | CA45: 0 | CB45: 20260520T090340-20260520T210308.csv | CC45: 4 | CD45: user > assistant > tool > assistant | CE45: 1.0.0 | CH45: =IF(OR(CG45="①", CG45="⑤"), "〇", "×") | CI45: =IF(OR(AND($CT45<>"",ISNUMBER(SEARCH($CT45, AP45))),AND($CU45<>"",ISNUMBER(SEARCH($CU45, AP45))),AND($CV45<>"",ISNUMBER(SEARCH($CV45, AP45)))),"〇","-") | CJ45: =IF(OR(AND($CT45<>"",ISNUMBER(SEARCH($CT45, AS45))),AND($CU45<>"",ISNUMBER(SEARCH($CU45, AS45))),AND($CV45<>"",ISNUMBER(SEARCH($CV45, AS45)))),"〇","-") | CK45: =IF(OR(AND($CT45<>"",ISNUMBER(SEARCH($CT45, AV45))),AND($CU45<>"",ISNUMBER(SEARCH($CU45, AV45))),AND($CV45<>"",ISNUMBER(SEARCH($CV45, AV45)))),"〇","-") | CL45: =IF(OR(AND($CT45<>"",ISNUMBER(SEARCH($CT45, AY45))),AND($CU45<>"",ISNUMBER(SEARCH($CU45, AY45))),AND($CV45<>"",ISNUMBER(SEARCH($CV45, AY45)))),"〇","-") | CM45: =IF(OR(AND($CT45<>"",ISNUMBER(SEARCH($CT45, BB45))),AND($CU45<>"",ISNUMBER(SEARCH($CU45, BB45))),AND($CV45<>"",ISNUMBER(SEARCH($CV45, BB45)))),"〇","-") | CN45: =IF(OR(AND($CT45<>"",ISNUMBER(SEARCH($CT45, BE45))),AND($CU45<>"",ISNUMBER(SEARCH($CU45, BE45))),AND($CV45<>"",ISNUMBER(SEARCH($CV45, BE45)))),"〇","-") | CO45: =IF(OR(AND($CT45<>"",ISNUMBER(SEARCH($CT45, BH45))),AND($CU45<>"",ISNUMBER(SEARCH($CU45, BH45))),AND($CV45<>"",ISNUMBER(SEARCH($CV45, BH45)))),"〇","-") | CP45: =IF(OR(AND($CT45<>"",ISNUMBER(SEARCH($CT45, BK45))),AND($CU45<>"",ISNUMBER(SEARCH($CU45, BK45))),AND($CV45<>"",ISNUMBER(SEARCH($CV45, BK45)))),"〇","-") | CQ45: =IF(OR(AND($CT45<>"",ISNUMBER(SEARCH($CT45, BN45))),AND($CU45<>"",ISNUMBER(SEARCH($CU45, BN45))),AND($CV45<>"",ISNUMBER(SEARCH($CV45, BN45)))),"〇","-") | CR45: =IF(OR(AND($CT45<>"",ISNUMBER(SEARCH($CT45, BQ45))),AND($CU45<>"",ISNUMBER(SEARCH($CU45, BQ45))),AND($CV45<>"",ISNUMBER(SEARCH($CV45, BQ45)))),"〇","-") | CW45: =IF(OR(CI45="〇",CJ45="〇",CK45="〇",CL45="〇",CM45="〇",CN45="〇",CO45="〇",CP45="〇",CQ45="〇",CR45="〇"),"〇","") | DE45: =TEXT(U45,"yyyy/mm/dd") | DF45: =VLOOKUP(K45,社員マスタ!C:D,2,0) | DG45: 1779252057831
B46: a:1jT_wHs4OxT_8Iiv-bmsifaTQuwnGGXjX6nG6qGaFFdqgFQLC7E4IbcYRM6lsPm4XicDY7B4VGMA6UuWlnEuULO0l_0hNEjREK_C9xCAh3uDlFJO0GqFlKcRvJdlhoUaf-1779254493578-FB000 | C46: =ROW(A46)-3 | D46: a:1jT_wHs4OxT_8Iiv-bmsifaTQuwnGGXjX6nG6qGaFFdqgFQLC7E4IbcYRM6lsPm4XicDY7B4VGMA6UuWlnEuULO0l_0hNEjREK_C9xCAh3uDlFJO0GqFlKcRvJdlhoUaf-1779254493578 | E46: 1779254493578 | F46: a:1jT_wHs4OxT_8Iiv-bmsifaTQuwnGGXjX6nG6qGaFFdqgFQLC7E4IbcYRM6lsPm4XicDY7B4VGMA6UuWlnEuULO0l_0hNEjREK_C9xCAh3uDlFJO0GqFlKcRvJdlhoUaf | G46: a:1jT_wHs4OxT_8Iiv-bmsifaTQuwnGGXjX6nG6qGaFFdqgFQLC7E4IbcYRM6lsPm4XicDY7B4VGMA6UuWlnEuULO0l_0hNEjREK_C9xCAh3uDlFJO0GqFlKcRvJdlhoUaf-S001 | H46: 1 | I46: 1 | J46: 1 | K46: Makoto Ito (伊藤 誠) | L46: DM | M46: Staffiaで希望の振込先が表示されない | N46: Staffiaで希望の振込先が表示されない | O46: 1 | P46: 0 | Q46: 0 | R46: 0 | S46: 46162.223 | T46: 46162.223 | U46: 46162.598 | V46: 46162.598 | W46: 6.131 | X46: searchEmployeeRules | Y46: システム操作 > Staffia | AA46: システム操作 | AB46: システム操作 > Staffia | AC46: predicted | AD46: 0 | AE46: 検索結果から、Staffiaのシステム利用や支払業務の流れについては記載がありますが、「希望の振込先が表示されない」場合の具体的な対応方法や原因についての情報は見当たりませんでした。 このため、詳細な対応方法については、適切な問い合わせ先で確認する必要があります。 ※AIの回答は必ずしも正確ではありません。参照情報も確認いただき、最終判断は所属部署の公式情報をご確認ください。 | AF46: 1 | AG46: 0 | AH46: 3 | AI46: 0 | AJ46: 0 | AL46: 4 | AM46: 4 | AN46: 0 | AO46: 【業務ID_6】Staffia業務マニュアル（派遣先組織向け）1.1版.pdf | AP46: Staffiaはシステムの立ち上げ、利用に必要な手続き、出来る範囲が異なる システムの立ち上げ システムの利用にあたって メインメニューから立ち上げ 申請不要で利用可能 DREAMS ・ BUSKETS ブラウザからStaffiaにログイン Staffia利用には、操作者の登録が必要 • 操作者には実務業務に応じた権限を設定 （操作者登録・権限付与は各組織で実施可能） Staffia システムで出来る範囲 各工程において、使用するシステムが異なる 【人員要求】 【個別契約】 【勤務管理】 【支払】 【各種帳票出力】 モニタリング・BUSKETS 簡易申請・BUSKETS 共通申請・BUSKETS スケジューラ 簡易申請/検収・BUSKETS 実施伺い（文書回覧型申請）を除き、 派遣契約に関わる業務はStaffiaで一元管理 5 | AQ46: 0.9250048 | AR46: 【業務ID_6】Staffia業務マニュアル（派遣先組織向け）1.1版.pdf | AS46: 勤務管理においては、時間外・休暇・旅費申請の有無に関わらず、「派遣労働者による勤務時間と業務内容の申請」および 「勤務承認者の承認」がStaffiaでは毎日必要な点が異なる。支払は、システムのインターフェースは異なるものの、流れは概ね同様。 勤務管理 支払 スケジューラで勤務系申請（時間外・休暇・旅費等）を実施し、 上⾧が承認。（申請事項がない場合は、上⾧は承認不要） 前月の勤務実績および支払額を 確認し、簡易申請を実施。 派遣会社から回答後、検収を実施し 派遣料金を支払い。 支払額確認 検収 DREAMS ・ BUSKETS 時間外や休暇、旅費申請の有無に関わらず、派遣労働者は、毎日 当日 の勤務時間と業務内容を申請。 派遣労働者の申請に基づき、勤務承認者は内容を確認し日次承認。 月間の勤務実績を確認し、 勤務管理の月次承認を実施。 派遣会社から回答後、Staffiaで 支 払承認を実施。その後、G共通IT（財 務）に自動連係され支払い。 派遣労働者は毎日 勤務時間と業務内容を申請 勤務承認者は 勤務状況と業務内容を 日次承認 月次承認 支払承認 Staffia 7 | AT46: 0.91493886 | AU46: 【業務ID_6】Staffia業務マニュアル（派遣先組織向け）1.1版.pdf | AV46: システムのインターフェースは異なるものの、スタッフ要求～個別契約についての流れは概ね同様。 スタッフ要求・見積依頼 個別契約 簡易申請に必要事項を記載し、 人員要求。 派遣会社から回答後、候補者選定 申請を実施し派遣会社確定。 共通申請で個別契約申請を実施。 派遣会社からの回答後、個別契約成立。 DREAMS ・ BUSKETS G共通IT（決裁）で実施伺い後、Staffiaに必要事項を記載し、 スタッフ要求・見積依頼を実施し、派遣会社からの回答を得る。 G共通IT（決裁）で実施伺い後、派遣会社を確定。Staffiaで個別契約内 容を派遣会社に提示。派遣会社からの回答内容を確認・承認後、個別契約 成立。 スタッフ要求書作成 派遣会社へ見積依頼 個別契約内容を作成し、派遣会社へ提示 派遣会社からの回答内容を確認・承認後、 個別契約成立 Staffia 6 | AW46: 0.9250048 | AX46: 【業務ID_6】Staffia業務マニュアル（派遣先組織向け）1.1版.pdf | AY46: ポイント 件名 決裁していただきたい事項 :契約期間、業務内容、取引先、費用 添付ファイル G決裁(決裁)利用メニュー :すべて ＞ 文書回覧 ＞ 文書回覧の新規作成 非公開フラグ 回覧ルート : 【実施伺い】人材派遣契約の実施について（○○担当）等 :Staffiaで作成した仕様書のPDFを添付する :個人情報が含まれる場合は「非公開フラグ」にチェックする :決裁者は派遣先責任者（派遣受入の決定権を持つ方）となるように承認フローを設定 44 | AZ46: 0.90622675 | BT46: 0 | BU46: 0 | BZ46: 0 | CA46: 0 | CB46: 20260520T090340-20260520T210308.csv | CC46: 5 | CD46: user > assistant > assistant > tool > assistant | CE46: 1.0.0 | CH46: =IF(OR(CG46="①", CG46="⑤"), "〇", "×") | CI46: =IF(OR(AND($CT46<>"",ISNUMBER(SEARCH($CT46, AP46))),AND($CU46<>"",ISNUMBER(SEARCH($CU46, AP46))),AND($CV46<>"",ISNUMBER(SEARCH($CV46, AP46)))),"〇","-") | CJ46: =IF(OR(AND($CT46<>"",ISNUMBER(SEARCH($CT46, AS46))),AND($CU46<>"",ISNUMBER(SEARCH($CU46, AS46))),AND($CV46<>"",ISNUMBER(SEARCH($CV46, AS46)))),"〇","-") | CK46: =IF(OR(AND($CT46<>"",ISNUMBER(SEARCH($CT46, AV46))),AND($CU46<>"",ISNUMBER(SEARCH($CU46, AV46))),AND($CV46<>"",ISNUMBER(SEARCH($CV46, AV46)))),"〇","-") | CL46: =IF(OR(AND($CT46<>"",ISNUMBER(SEARCH($CT46, AY46))),AND($CU46<>"",ISNUMBER(SEARCH($CU46, AY46))),AND($CV46<>"",ISNUMBER(SEARCH($CV46, AY46)))),"〇","-") | CM46: =IF(OR(AND($CT46<>"",ISNUMBER(SEARCH($CT46, BB46))),AND($CU46<>"",ISNUMBER(SEARCH($CU46, BB46))),AND($CV46<>"",ISNUMBER(SEARCH($CV46, BB46)))),"〇","-") | CN46: =IF(OR(AND($CT46<>"",ISNUMBER(SEARCH($CT46, BE46))),AND($CU46<>"",ISNUMBER(SEARCH($CU46, BE46))),AND($CV46<>"",ISNUMBER(SEARCH($CV46, BE46)))),"〇","-") | CO46: =IF(OR(AND($CT46<>"",ISNUMBER(SEARCH($CT46, BH46))),AND($CU46<>"",ISNUMBER(SEARCH($CU46, BH46))),AND($CV46<>"",ISNUMBER(SEARCH($CV46, BH46)))),"〇","-") | CP46: =IF(OR(AND($CT46<>"",ISNUMBER(SEARCH($CT46, BK46))),AND($CU46<>"",ISNUMBER(SEARCH($CU46, BK46))),AND($CV46<>"",ISNUMBER(SEARCH($CV46, BK46)))),"〇","-") | CQ46: =IF(OR(AND($CT46<>"",ISNUMBER(SEARCH($CT46, BN46))),AND($CU46<>"",ISNUMBER(SEARCH($CU46, BN46))),AND($CV46<>"",ISNUMBER(SEARCH($CV46, BN46)))),"〇","-") | CR46: =IF(OR(AND($CT46<>"",ISNUMBER(SEARCH($CT46, BQ46))),AND($CU46<>"",ISNUMBER(SEARCH($CU46, BQ46))),AND($CV46<>"",ISNUMBER(SEARCH($CV46, BQ46)))),"〇","-") | CW46: =IF(OR(CI46="〇",CJ46="〇",CK46="〇",CL46="〇",CM46="〇",CN46="〇",CO46="〇",CP46="〇",CQ46="〇",CR46="〇"),"〇","") | DE46: =TEXT(U46,"yyyy/mm/dd") | DF46: =VLOOKUP(K46,社員マスタ!C:D,2,0) | DG46: 1779254493578
B47: a:1Wpdf-pdYaegjT0A3JzjbiZj0uIxzjTeBkH2pybJNeXEPZbYIvgWVH27WqMgK49tfDKYQXvUmziusSyGVtCD_rlPj9dNR3kJiFiPfNF7FIpYhovnj25NZgdajiEEgPrD8-1779260544385-FB000 | C47: =ROW(A47)-3 | D47: a:1Wpdf-pdYaegjT0A3JzjbiZj0uIxzjTeBkH2pybJNeXEPZbYIvgWVH27WqMgK49tfDKYQXvUmziusSyGVtCD_rlPj9dNR3kJiFiPfNF7FIpYhovnj25NZgdajiEEgPrD8-1779260544385 | E47: 1779260544385 | F47: a:1Wpdf-pdYaegjT0A3JzjbiZj0uIxzjTeBkH2pybJNeXEPZbYIvgWVH27WqMgK49tfDKYQXvUmziusSyGVtCD_rlPj9dNR3kJiFiPfNF7FIpYhovnj25NZgdajiEEgPrD8 | G47: a:1Wpdf-pdYaegjT0A3JzjbiZj0uIxzjTeBkH2pybJNeXEPZbYIvgWVH27WqMgK49tfDKYQXvUmziusSyGVtCD_rlPj9dNR3kJiFiPfNF7FIpYhovnj25NZgdajiEEgPrD8-S001 | H47: 1 | I47: 1 | J47: 1 | K47: Kenta Kashiwazaki (柏崎 健太) | L47: DM | M47: 国内勤務の社員の海外出張にて、航空券やホテルの宿泊料が規定の金額を超えた場合は自己負担になりますか？ | N47: 国内勤務の社員の海外出張にて、航空券やホテルの宿泊料が規定の金額を超えた場合は自己負担になりますか？ | O47: 1 | P47: 0 | Q47: 0 | R47: 0 | S47: 46162.293 | T47: 46162.293 | U47: 46162.668 | V47: 46162.668 | W47: 7.319 | X47: searchEmployeeRules | Y47: 制度・運用 > 旅費 | AA47: 制度・運用 | AB47: 制度・運用 > 旅費 | AC47: predicted | AD47: 0 | AE47: 規定額を超える宿泊施設や航空券を利用した場合、制度上、規定額を超えた分については支給されません。 そのため、超過した金額は自己負担となります。 次回以降は、必ず規定額内で手配するようご注意ください。 ※AIの回答は必ずしも正確ではありません。参照情報も確認いただき、最終判断は所属部署の公式情報をご確認ください。 | AF47: 1 | AG47: 0 | AH47: 3 | AI47: 0 | AJ47: 0 | AL47: 4 | AM47: 4 | AN47: 0 | AO47: 12 旅費規程_202601.docx | AP47: 付則（社長達第５号 2017年7月20日） この改正は、2017年8月1日から実施する。 ただし、外国出張の支給において、実施日前日までに予約が完了している旅費については、改正前の通達に基づき支給する。 付則（社長達第38号 2018年３月29日） この改正は、2018年４月１日から実施する。なお、実施日前日までに出発する旅行に係る旅費については、改正前の規程に基づき支給する。 ただし、第２章（内国旅行）第３節（赴任）において、住所の移転を伴う転勤を実施日に任命された社員の家族が、実施日の前日から仮住居に宿泊した場合の家族移転費については、改正後の規程に基づき支給する。 | AQ47: 0.93436387 | AR47: 13 外国旅費事務細則_202407.docx | AS47: ア 滞在日数３０日を超える日数につき １０分の１ イ 滞在日数６０日を超える日数につき １０分の２ ウ 滞在日数９０日を超える日数につき １０分の４ （留学生の滞在費等） 社員が留学等を目的として外国へ１年以内の出張を行ったときは、次項から第４項までに規定するところにより、日当、食事代、宿泊料及び滞在費を支給する。 ２ 日当は、勤務事業所を出発した日から、当該機関に到着した日までの日数及び当該機関を出発した日から、勤務事業所に到着した日までの日数に応じて、旅費規程第４７条に定める額を支給する。 ３ 食事代は、本国を出発した日から任地に到達した日までの分について、旅費規程第４８条に | AT47: 0.93827468 | AU47: QA198_policy-operations_travel_travel-assignment_office-work_domestic_training_home-travel-expenses_overseas_operational_travel-others.md | AV47: 質問 赴任滞在期間を超えて仮住居へ宿泊している場合も交通費は支給されますか。 回答 赴任滞在期間を超えていても、仮住居からの交通費については支給されます。 仮住居に滞在していたことがわかる証明書類（領収書・赴任滞在証明書等）を添付してください。 | AW47: 0.93436387 | AX47: QA191_policy-operations_travel_travel-assignment_office-work_domestic_training_home-travel-expenses_overseas_operational_travel-others.md | AY47: 質問 規定額を超える宿泊施設へ滞在してしまいましたが、超過した金額分も支給されますか。 回答 宿泊は可能ですが、制度上、規定額を超えての支給はできません。次回以降、必ず、規定額内におさまる宿泊施設を手配頂きますようお願いいたします。 ※新たな勤務事業所の近隣に、規定内におさまる宿泊施設がない場合、近隣以外の宿泊施設も宿泊可能です。 宿泊施設と新たな勤務事業所との交通費は支給となります。 | AZ47: 0.9427751 | BT47: 0 | BU47: 0 | BZ47: 0 | CA47: 0 | CB47: 20260520T090340-20260520T210308.csv | CC47: 5 | CD47: user > assistant > assistant > tool > assistant | CE47: 1.0.0 | CH47: =IF(OR(CG47="①", CG47="⑤"), "〇", "×") | CI47: =IF(OR(AND($CT47<>"",ISNUMBER(SEARCH($CT47, AP47))),AND($CU47<>"",ISNUMBER(SEARCH($CU47, AP47))),AND($CV47<>"",ISNUMBER(SEARCH($CV47, AP47)))),"〇","-") | CJ47: =IF(OR(AND($CT47<>"",ISNUMBER(SEARCH($CT47, AS47))),AND($CU47<>"",ISNUMBER(SEARCH($CU47, AS47))),AND($CV47<>"",ISNUMBER(SEARCH($CV47, AS47)))),"〇","-") | CK47: =IF(OR(AND($CT47<>"",ISNUMBER(SEARCH($CT47, AV47))),AND($CU47<>"",ISNUMBER(SEARCH($CU47, AV47))),AND($CV47<>"",ISNUMBER(SEARCH($CV47, AV47)))),"〇","-") | CL47: =IF(OR(AND($CT47<>"",ISNUMBER(SEARCH($CT47, AY47))),AND($CU47<>"",ISNUMBER(SEARCH($CU47, AY47))),AND($CV47<>"",ISNUMBER(SEARCH($CV47, AY47)))),"〇","-") | CM47: =IF(OR(AND($CT47<>"",ISNUMBER(SEARCH($CT47, BB47))),AND($CU47<>"",ISNUMBER(SEARCH($CU47, BB47))),AND($CV47<>"",ISNUMBER(SEARCH($CV47, BB47)))),"〇","-") | CN47: =IF(OR(AND($CT47<>"",ISNUMBER(SEARCH($CT47, BE47))),AND($CU47<>"",ISNUMBER(SEARCH($CU47, BE47))),AND($CV47<>"",ISNUMBER(SEARCH($CV47, BE47)))),"〇","-") | CO47: =IF(OR(AND($CT47<>"",ISNUMBER(SEARCH($CT47, BH47))),AND($CU47<>"",ISNUMBER(SEARCH($CU47, BH47))),AND($CV47<>"",ISNUMBER(SEARCH($CV47, BH47)))),"〇","-") | CP47: =IF(OR(AND($CT47<>"",ISNUMBER(SEARCH($CT47, BK47))),AND($CU47<>"",ISNUMBER(SEARCH($CU47, BK47))),AND($CV47<>"",ISNUMBER(SEARCH($CV47, BK47)))),"〇","-") | CQ47: =IF(OR(AND($CT47<>"",ISNUMBER(SEARCH($CT47, BN47))),AND($CU47<>"",ISNUMBER(SEARCH($CU47, BN47))),AND($CV47<>"",ISNUMBER(SEARCH($CV47, BN47)))),"〇","-") | CR47: =IF(OR(AND($CT47<>"",ISNUMBER(SEARCH($CT47, BQ47))),AND($CU47<>"",ISNUMBER(SEARCH($CU47, BQ47))),AND($CV47<>"",ISNUMBER(SEARCH($CV47, BQ47)))),"〇","-") | CW47: =IF(OR(CI47="〇",CJ47="〇",CK47="〇",CL47="〇",CM47="〇",CN47="〇",CO47="〇",CP47="〇",CQ47="〇",CR47="〇"),"〇","") | DE47: =TEXT(U47,"yyyy/mm/dd") | DF47: =VLOOKUP(K47,社員マスタ!C:D,2,0) | DG47: 1779260544385
B48: a:1Wpdf-pdYaegjT0A3JzjbiZj0uIxzjTeBkH2pybJNeXEPZbYIvgWVH27WqMgK49tfDKYQXvUmziusSyGVtCD_rlPj9dNR3kJiFiPfNF7FIpYhovnj25NZgdajiEEgPrD8-f:11994e39-2ecf-b3ff-de95-4af19acc45c9-FB000 | C48: =ROW(A48)-3 | D48: a:1Wpdf-pdYaegjT0A3JzjbiZj0uIxzjTeBkH2pybJNeXEPZbYIvgWVH27WqMgK49tfDKYQXvUmziusSyGVtCD_rlPj9dNR3kJiFiPfNF7FIpYhovnj25NZgdajiEEgPrD8-f:11994e39-2ecf-b3ff-de95-4af19acc45c9 | E48: f:11994e39-2ecf-b3ff-de95-4af19acc45c9 | F48: a:1Wpdf-pdYaegjT0A3JzjbiZj0uIxzjTeBkH2pybJNeXEPZbYIvgWVH27WqMgK49tfDKYQXvUmziusSyGVtCD_rlPj9dNR3kJiFiPfNF7FIpYhovnj25NZgdajiEEgPrD8 | G48: a:1Wpdf-pdYaegjT0A3JzjbiZj0uIxzjTeBkH2pybJNeXEPZbYIvgWVH27WqMgK49tfDKYQXvUmziusSyGVtCD_rlPj9dNR3kJiFiPfNF7FIpYhovnj25NZgdajiEEgPrD8-S001 | H48: 1 | I48: 2 | J48: 1 | K48: Kenta Kashiwazaki (柏崎 健太) | L48: DM | N48: [カテゴリ選択] | O48: 0 | P48: 0 | Q48: 1 | R48: 0 | S48: 46162.295 | T48: 46162.295 | U48: 46162.67 | V48: 46162.67 | W48: 0 | Z48: 制度・運用 | AB48: 制度・運用 | AC48: user_selected | AD48: 0 | AF48: 0 | AG48: 0 | AH48: 0 | AI48: 0 | AJ48: 0 | AL48: 0 | AM48: 0 | AN48: 0 | BT48: 0 | BU48: 0 | BZ48: 0 | CA48: 0 | CB48: 20260520T090340-20260520T210308.csv | CC48: 1 | CD48: user | CE48: 1.0.0 | CH48: =IF(OR(CG48="①", CG48="⑤"), "〇", "×") | CI48: =IF(OR(AND($CT48<>"",ISNUMBER(SEARCH($CT48, AP48))),AND($CU48<>"",ISNUMBER(SEARCH($CU48, AP48))),AND($CV48<>"",ISNUMBER(SEARCH($CV48, AP48)))),"〇","-") | CJ48: =IF(OR(AND($CT48<>"",ISNUMBER(SEARCH($CT48, AS48))),AND($CU48<>"",ISNUMBER(SEARCH($CU48, AS48))),AND($CV48<>"",ISNUMBER(SEARCH($CV48, AS48)))),"〇","-") | CK48: =IF(OR(AND($CT48<>"",ISNUMBER(SEARCH($CT48, AV48))),AND($CU48<>"",ISNUMBER(SEARCH($CU48, AV48))),AND($CV48<>"",ISNUMBER(SEARCH($CV48, AV48)))),"〇","-") | CL48: =IF(OR(AND($CT48<>"",ISNUMBER(SEARCH($CT48, AY48))),AND($CU48<>"",ISNUMBER(SEARCH($CU48, AY48))),AND($CV48<>"",ISNUMBER(SEARCH($CV48, AY48)))),"〇","-") | CM48: =IF(OR(AND($CT48<>"",ISNUMBER(SEARCH($CT48, BB48))),AND($CU48<>"",ISNUMBER(SEARCH($CU48, BB48))),AND($CV48<>"",ISNUMBER(SEARCH($CV48, BB48)))),"〇","-") | CN48: =IF(OR(AND($CT48<>"",ISNUMBER(SEARCH($CT48, BE48))),AND($CU48<>"",ISNUMBER(SEARCH($CU48, BE48))),AND($CV48<>"",ISNUMBER(SEARCH($CV48, BE48)))),"〇","-") | CO48: =IF(OR(AND($CT48<>"",ISNUMBER(SEARCH($CT48, BH48))),AND($CU48<>"",ISNUMBER(SEARCH($CU48, BH48))),AND($CV48<>"",ISNUMBER(SEARCH($CV48, BH48)))),"〇","-") | CP48: =IF(OR(AND($CT48<>"",ISNUMBER(SEARCH($CT48, BK48))),AND($CU48<>"",ISNUMBER(SEARCH($CU48, BK48))),AND($CV48<>"",ISNUMBER(SEARCH($CV48, BK48)))),"〇","-") | CQ48: =IF(OR(AND($CT48<>"",ISNUMBER(SEARCH($CT48, BN48))),AND($CU48<>"",ISNUMBER(SEARCH($CU48, BN48))),AND($CV48<>"",ISNUMBER(SEARCH($CV48, BN48)))),"〇","-") | CR48: =IF(OR(AND($CT48<>"",ISNUMBER(SEARCH($CT48, BQ48))),AND($CU48<>"",ISNUMBER(SEARCH($CU48, BQ48))),AND($CV48<>"",ISNUMBER(SEARCH($CV48, BQ48)))),"〇","-") | CW48: =IF(OR(CI48="〇",CJ48="〇",CK48="〇",CL48="〇",CM48="〇",CN48="〇",CO48="〇",CP48="〇",CQ48="〇",CR48="〇"),"〇","") | DE48: =TEXT(U48,"yyyy/mm/dd") | DF48: =VLOOKUP(K48,社員マスタ!C:D,2,0) | DG48: f:11994e39-2ecf-b3ff-de95-4af19acc45c9
B49: a:1Wpdf-pdYaegjT0A3JzjbiZj0uIxzjTeBkH2pybJNeXEPZbYIvgWVH27WqMgK49tfDKYQXvUmziusSyGVtCD_rlPj9dNR3kJiFiPfNF7FIpYhovnj25NZgdajiEEgPrD8-f:eab5176c-9778-af05-d37f-780da8f8ff5c-FB000 | C49: =ROW(A49)-3 | D49: a:1Wpdf-pdYaegjT0A3JzjbiZj0uIxzjTeBkH2pybJNeXEPZbYIvgWVH27WqMgK49tfDKYQXvUmziusSyGVtCD_rlPj9dNR3kJiFiPfNF7FIpYhovnj25NZgdajiEEgPrD8-f:eab5176c-9778-af05-d37f-780da8f8ff5c | E49: f:eab5176c-9778-af05-d37f-780da8f8ff5c | F49: a:1Wpdf-pdYaegjT0A3JzjbiZj0uIxzjTeBkH2pybJNeXEPZbYIvgWVH27WqMgK49tfDKYQXvUmziusSyGVtCD_rlPj9dNR3kJiFiPfNF7FIpYhovnj25NZgdajiEEgPrD8 | G49: a:1Wpdf-pdYaegjT0A3JzjbiZj0uIxzjTeBkH2pybJNeXEPZbYIvgWVH27WqMgK49tfDKYQXvUmziusSyGVtCD_rlPj9dNR3kJiFiPfNF7FIpYhovnj25NZgdajiEEgPrD8-S001 | H49: 1 | I49: 3 | J49: 1 | K49: Kenta Kashiwazaki (柏崎 健太) | L49: DM | N49: [カテゴリ選択] | O49: 0 | P49: 0 | Q49: 1 | R49: 0 | S49: 46162.295 | T49: 46162.295 | U49: 46162.67 | V49: 46162.67 | W49: 0 | Z49: 制度・運用 > 旅費 | AB49: 制度・運用 > 旅費 | AC49: user_selected | AD49: 0 | AF49: 0 | AG49: 0 | AH49: 0 | AI49: 0 | AJ49: 0 | AL49: 0 | AM49: 0 | AN49: 0 | BT49: 0 | BU49: 0 | BZ49: 0 | CA49: 0 | CB49: 20260520T090340-20260520T210308.csv | CC49: 1 | CD49: user | CE49: 1.0.0 | CH49: =IF(OR(CG49="①", CG49="⑤"), "〇", "×") | CI49: =IF(OR(AND($CT49<>"",ISNUMBER(SEARCH($CT49, AP49))),AND($CU49<>"",ISNUMBER(SEARCH($CU49, AP49))),AND($CV49<>"",ISNUMBER(SEARCH($CV49, AP49)))),"〇","-") | CJ49: =IF(OR(AND($CT49<>"",ISNUMBER(SEARCH($CT49, AS49))),AND($CU49<>"",ISNUMBER(SEARCH($CU49, AS49))),AND($CV49<>"",ISNUMBER(SEARCH($CV49, AS49)))),"〇","-") | CK49: =IF(OR(AND($CT49<>"",ISNUMBER(SEARCH($CT49, AV49))),AND($CU49<>"",ISNUMBER(SEARCH($CU49, AV49))),AND($CV49<>"",ISNUMBER(SEARCH($CV49, AV49)))),"〇","-") | CL49: =IF(OR(AND($CT49<>"",ISNUMBER(SEARCH($CT49, AY49))),AND($CU49<>"",ISNUMBER(SEARCH($CU49, AY49))),AND($CV49<>"",ISNUMBER(SEARCH($CV49, AY49)))),"〇","-") | CM49: =IF(OR(AND($CT49<>"",ISNUMBER(SEARCH($CT49, BB49))),AND($CU49<>"",ISNUMBER(SEARCH($CU49, BB49))),AND($CV49<>"",ISNUMBER(SEARCH($CV49, BB49)))),"〇","-") | CN49: =IF(OR(AND($CT49<>"",ISNUMBER(SEARCH($CT49, BE49))),AND($CU49<>"",ISNUMBER(SEARCH($CU49, BE49))),AND($CV49<>"",ISNUMBER(SEARCH($CV49, BE49)))),"〇","-") | CO49: =IF(OR(AND($CT49<>"",ISNUMBER(SEARCH($CT49, BH49))),AND($CU49<>"",ISNUMBER(SEARCH($CU49, BH49))),AND($CV49<>"",ISNUMBER(SEARCH($CV49, BH49)))),"〇","-") | CP49: =IF(OR(AND($CT49<>"",ISNUMBER(SEARCH($CT49, BK49))),AND($CU49<>"",ISNUMBER(SEARCH($CU49, BK49))),AND($CV49<>"",ISNUMBER(SEARCH($CV49, BK49)))),"〇","-") | CQ49: =IF(OR(AND($CT49<>"",ISNUMBER(SEARCH($CT49, BN49))),AND($CU49<>"",ISNUMBER(SEARCH($CU49, BN49))),AND($CV49<>"",ISNUMBER(SEARCH($CV49, BN49)))),"〇","-") | CR49: =IF(OR(AND($CT49<>"",ISNUMBER(SEARCH($CT49, BQ49))),AND($CU49<>"",ISNUMBER(SEARCH($CU49, BQ49))),AND($CV49<>"",ISNUMBER(SEARCH($CV49, BQ49)))),"〇","-") | CW49: =IF(OR(CI49="〇",CJ49="〇",CK49="〇",CL49="〇",CM49="〇",CN49="〇",CO49="〇",CP49="〇",CQ49="〇",CR49="〇"),"〇","") | DE49: =TEXT(U49,"yyyy/mm/dd") | DF49: =VLOOKUP(K49,社員マスタ!C:D,2,0) | DG49: f:eab5176c-9778-af05-d37f-780da8f8ff5c
